Workbook

Sheet Fact_Sales
A1: Date | B1: CustomerID | C1: ProductID | D1: Revenue | E1: Quantity | F1: Discount | G1: ActualCost | H1: CalculatedProfit | I1: Month | J1: COGS
A2: 2024-01-04 | B2: CUST-008 | C2: PRD-001 | D2: 14763 | E2: 37 | F2: 0 | G2: {=IFERROR(--SUBSTITUTE(INDEX(Product_Costing!$I$2:$I$201,MATCH(1,(Product_Costing!$B$2:$B$201=Fact_Sales[[#This Row],[ProductID]])*(Product_Costing!$C$2:$C$201=DATE(YEAR(Fact_Sales[[#This Row],[Date]]),MONTH(Fact_Sales[[#This Row],[Date]]),1)),0))&""," USD",""),"")} -> 186.97 | H2: =IF(Fact_Sales[[#This Row],[Revenue]]="","",IFERROR(--SUBSTITUTE(Fact_Sales[[#This Row],[Revenue]]&""," USD",""),Fact_Sales[[#This Row],[Revenue]])-Fact_Sales[[#This Row],[Quantity]]*Fact_Sales[[#This Row],[ActualCost]]) -> 7845.11 | I2: =EOMONTH(Fact_Sales[[#This Row],[Date]],-1)+1 -> 45292 | J2: =IFERROR(Fact_Sales[[#This Row],[Quantity]]*Fact_Sales[[#This Row],[ActualCost]],0) -> 6917.89
A3: 2024-01-19 | B3: CUST-007 | C3: PRD-001 | D3: 61725.3 | E3: 182 | F3: 0.15 | G3: {=IFERROR(--SUBSTITUTE(INDEX(Product_Costing!$I$2:$I$201,MATCH(1,(Product_Costing!$B$2:$B$201=Fact_Sales[[#This Row],[ProductID]])*(Product_Costing!$C$2:$C$201=DATE(YEAR(Fact_Sales[[#This Row],[Date]]),MONTH(Fact_Sales[[#This Row],[Date]]),1)),0))&""," USD",""),"")} -> 186.97 | H3: =IF(Fact_Sales[[#This Row],[Revenue]]="","",IFERROR(--SUBSTITUTE(Fact_Sales[[#This Row],[Revenue]]&""," USD",""),Fact_Sales[[#This Row],[Revenue]])-Fact_Sales[[#This Row],[Quantity]]*Fact_Sales[[#This Row],[ActualCost]]) -> 27696.76 | I3: =EOMONTH(Fact_Sales[[#This Row],[Date]],-1)+1 -> 45292 | J3: =IFERROR(Fact_Sales[[#This Row],[Quantity]]*Fact_Sales[[#This Row],[ActualCost]],0) -> 34028.54
A4: 2024-01-01 | B4: CUST-008 | C4: PRD-001 | D4: 46623.15 | E4: 123 | F4: 0.05 | G4: {=IFERROR(--SUBSTITUTE(INDEX(Product_Costing!$I$2:$I$201,MATCH(1,(Product_Costing!$B$2:$B$201=Fact_Sales[[#This Row],[ProductID]])*(Product_Costing!$C$2:$C$201=DATE(YEAR(Fact_Sales[[#This Row],[Date]]),MONTH(Fact_Sales[[#This Row],[Date]]),1)),0))&""," USD",""),"")} -> 186.97 | H4: =IF(Fact_Sales[[#This Row],[Revenue]]="","",IFERROR(--SUBSTITUTE(Fact_Sales[[#This Row],[Revenue]]&""," USD",""),Fact_Sales[[#This Row],[Revenue]])-Fact_Sales[[#This Row],[Quantity]]*Fact_Sales[[#This Row],[ActualCost]]) -> 23625.84 | I4: =EOMONTH(Fact_Sales[[#This Row],[Date]],-1)+1 -> 45292 | J4: =IFERROR(Fact_Sales[[#This Row],[Quantity]]*Fact_Sales[[#This Row],[ActualCost]],0) -> 22997.31
A5: 2024-01-12 | B5: CUST-009 | C5: PRD-001 | D5: 69027 | E5: 173 | F5: 0 | G5: {=IFERROR(--SUBSTITUTE(INDEX(Product_Costing!$I$2:$I$201,MATCH(1,(Product_Costing!$B$2:$B$201=Fact_Sales[[#This Row],[ProductID]])*(Product_Costing!$C$2:$C$201=DATE(YEAR(Fact_Sales[[#This Row],[Date]]),MONTH(Fact_Sales[[#This Row],[Date]]),1)),0))&""," USD",""),"")} -> 186.97 | H5: =IF(Fact_Sales[[#This Row],[Revenue]]="","",IFERROR(--SUBSTITUTE(Fact_Sales[[#This Row],[Revenue]]&""," USD",""),Fact_Sales[[#This Row],[Revenue]])-Fact_Sales[[#This Row],[Quantity]]*Fact_Sales[[#This Row],[ActualCost]]) -> 36681.19 | I5: =EOMONTH(Fact_Sales[[#This Row],[Date]],-1)+1 -> 45292 | J5: =IFERROR(Fact_Sales[[#This Row],[Quantity]]*Fact_Sales[[#This Row],[ActualCost]],0) -> 32345.81
A6: 2024-01-26 | B6: CUST-009 | C6: PRD-001 | D6: 68229 | E6: 171 | F6: 0 | G6: {=IFERROR(--SUBSTITUTE(INDEX(Product_Costing!$I$2:$I$201,MATCH(1,(Product_Costing!$B$2:$B$201=Fact_Sales[[#This Row],[ProductID]])*(Product_Costing!$C$2:$C$201=DATE(YEAR(Fact_Sales[[#This Row],[Date]]),MONTH(Fact_Sales[[#This Row],[Date]]),1)),0))&""," USD",""),"")} -> 186.97 | H6: =IF(Fact_Sales[[#This Row],[Revenue]]="","",IFERROR(--SUBSTITUTE(Fact_Sales[[#This Row],[Revenue]]&""," USD",""),Fact_Sales[[#This Row],[Revenue]])-Fact_Sales[[#This Row],[Quantity]]*Fact_Sales[[#This Row],[ActualCost]]) -> 36257.13 | I6: =EOMONTH(Fact_Sales[[#This Row],[Date]],-1)+1 -> 45292 | J6: =IFERROR(Fact_Sales[[#This Row],[Quantity]]*Fact_Sales[[#This Row],[ActualCost]],0) -> 31971.87
A7: 2024-01-01 | B7: CUST-001 | C7: PRD-001 | D7: 46463.55 | E7: 137 | F7: 0.15 | G7: {=IFERROR(--SUBSTITUTE(INDEX(Product_Costing!$I$2:$I$201,MATCH(1,(Product_Costing!$B$2:$B$201=Fact_Sales[[#This Row],[ProductID]])*(Product_Costing!$C$2:$C$201=DATE(YEAR(Fact_Sales[[#This Row],[Date]]),MONTH(Fact_Sales[[#This Row],[Date]]),1)),0))&""," USD",""),"")} -> 186.97 | H7: =IF(Fact_Sales[[#This Row],[Revenue]]="","",IFERROR(--SUBSTITUTE(Fact_Sales[[#This Row],[Revenue]]&""," USD",""),Fact_Sales[[#This Row],[Revenue]])-Fact_Sales[[#This Row],[Quantity]]*Fact_Sales[[#This Row],[ActualCost]]) -> 20848.66 | I7: =EOMONTH(Fact_Sales[[#This Row],[Date]],-1)+1 -> 45292 | J7: =IFERROR(Fact_Sales[[#This Row],[Quantity]]*Fact_Sales[[#This Row],[ActualCost]],0) -> 25614.89
A8: 2024-01-21 | B8: CUST-010 | C8: PRD-001 | D8: 54663 | E8: 137 | F8: 0 | G8: {=IFERROR(--SUBSTITUTE(INDEX(Product_Costing!$I$2:$I$201,MATCH(1,(Product_Costing!$B$2:$B$201=Fact_Sales[[#This Row],[ProductID]])*(Product_Costing!$C$2:$C$201=DATE(YEAR(Fact_Sales[[#This Row],[Date]]),MONTH(Fact_Sales[[#This Row],[Date]]),1)),0))&""," USD",""),"")} -> 186.97 | H8: =IF(Fact_Sales[[#This Row],[Revenue]]="","",IFERROR(--SUBSTITUTE(Fact_Sales[[#This Row],[Revenue]]&""," USD",""),Fact_Sales[[#This Row],[Revenue]])-Fact_Sales[[#This Row],[Quantity]]*Fact_Sales[[#This Row],[ActualCost]]) -> 29048.11 | I8: =EOMONTH(Fact_Sales[[#This Row],[Date]],-1)+1 -> 45292 | J8: =IFERROR(Fact_Sales[[#This Row],[Quantity]]*Fact_Sales[[#This Row],[ActualCost]],0) -> 25614.89
A9: 2024-01-07 | B9: CUST-010 | C9: PRD-002 | D9: 37677.1 | E9: 74 | F9: 0.15 | G9: {=IFERROR(--SUBSTITUTE(INDEX(Product_Costing!$I$2:$I$201,MATCH(1,(Product_Costing!$B$2:$B$201=Fact_Sales[[#This Row],[ProductID]])*(Product_Costing!$C$2:$C$201=DATE(YEAR(Fact_Sales[[#This Row],[Date]]),MONTH(Fact_Sales[[#This Row],[Date]]),1)),0))&""," USD",""),"")} -> 253.51 | H9: =IF(Fact_Sales[[#This Row],[Revenue]]="","",IFERROR(--SUBSTITUTE(Fact_Sales[[#This Row],[Revenue]]&""," USD",""),Fact_Sales[[#This Row],[Revenue]])-Fact_Sales[[#This Row],[Quantity]]*Fact_Sales[[#This Row],[ActualCost]]) -> 18917.36 | I9: =EOMONTH(Fact_Sales[[#This Row],[Date]],-1)+1 -> 45292 | J9: =IFERROR(Fact_Sales[[#This Row],[Quantity]]*Fact_Sales[[#This Row],[ActualCost]],0) -> 18759.74
A10: 2024-01-18 | B10: CUST-007 | C10: PRD-002 | D10: 9584 | E10: 16 | F10: 0 | G10: {=IFERROR(--SUBSTITUTE(INDEX(Product_Costing!$I$2:$I$201,MATCH(1,(Product_Costing!$B$2:$B$201=Fact_Sales[[#This Row],[ProductID]])*(Product_Costing!$C$2:$C$201=DATE(YEAR(Fact_Sales[[#This Row],[Date]]),MONTH(Fact_Sales[[#This Row],[Date]]),1)),0))&""," USD",""),"")} -> 253.51 | H10: =IF(Fact_Sales[[#This Row],[Revenue]]="","",IFERROR(--SUBSTITUTE(Fact_Sales[[#This Row],[Revenue]]&""," USD",""),Fact_Sales[[#This Row],[Revenue]])-Fact_Sales[[#This Row],[Quantity]]*Fact_Sales[[#This Row],[ActualCost]]) -> 5527.84 | I10: =EOMONTH(Fact_Sales[[#This Row],[Date]],-1)+1 -> 45292 | J10: =IFERROR(Fact_Sales[[#This Row],[Quantity]]*Fact_Sales[[#This Row],[ActualCost]],0) -> 4056.16
A11: 2024-01-16 | B11: CUST-013 | C11: PRD-002 | D11: 62625.45 | E11: 123 | F11: 0.15 | G11: {=IFERROR(--SUBSTITUTE(INDEX(Product_Costing!$I$2:$I$201,MATCH(1,(Product_Costing!$B$2:$B$201=Fact_Sales[[#This Row],[ProductID]])*(Product_Costing!$C$2:$C$201=DATE(YEAR(Fact_Sales[[#This Row],[Date]]),MONTH(Fact_Sales[[#This Row],[Date]]),1)),0))&""," USD",""),"")} -> 253.51 | H11: =IF(Fact_Sales[[#This Row],[Revenue]]="","",IFERROR(--SUBSTITUTE(Fact_Sales[[#This Row],[Revenue]]&""," USD",""),Fact_Sales[[#This Row],[Revenue]])-Fact_Sales[[#This Row],[Quantity]]*Fact_Sales[[#This Row],[ActualCost]]) -> 31443.72 | I11: =EOMONTH(Fact_Sales[[#This Row],[Date]],-1)+1 -> 45292 | J11: =IFERROR(Fact_Sales[[#This Row],[Quantity]]*Fact_Sales[[#This Row],[ActualCost]],0) -> 31181.73
A12: 2024-01-20 | B12: CUST-010 | C12: PRD-002 | D12: 41331 | E12: 69 | F12: 0 | G12: {=IFERROR(--SUBSTITUTE(INDEX(Product_Costing!$I$2:$I$201,MATCH(1,(Product_Costing!$B$2:$B$201=Fact_Sales[[#This Row],[ProductID]])*(Product_Costing!$C$2:$C$201=DATE(YEAR(Fact_Sales[[#This Row],[Date]]),MONTH(Fact_Sales[[#This Row],[Date]]),1)),0))&""," USD",""),"")} -> 253.51 | H12: =IF(Fact_Sales[[#This Row],[Revenue]]="","",IFERROR(--SUBSTITUTE(Fact_Sales[[#This Row],[Revenue]]&""," USD",""),Fact_Sales[[#This Row],[Revenue]])-Fact_Sales[[#This Row],[Quantity]]*Fact_Sales[[#This Row],[ActualCost]]) -> 23838.81 | I12: =EOMONTH(Fact_Sales[[#This Row],[Date]],-1)+1 -> 45292 | J12: =IFERROR(Fact_Sales[[#This Row],[Quantity]]*Fact_Sales[[#This Row],[ActualCost]],0) -> 17492.19
A13: 2024-01-14 | B13: CUST-007 | C13: PRD-002 | D13: 95720.2 | E13: 188 | F13: 0.15 | G13: {=IFERROR(--SUBSTITUTE(INDEX(Product_Costing!$I$2:$I$201,MATCH(1,(Product_Costing!$B$2:$B$201=Fact_Sales[[#This Row],[ProductID]])*(Product_Costing!$C$2:$C$201=DATE(YEAR(Fact_Sales[[#This Row],[Date]]),MONTH(Fact_Sales[[#This Row],[Date]]),1)),0))&""," USD",""),"")} -> 253.51 | H13: =IF(Fact_Sales[[#This Row],[Revenue]]="","",IFERROR(--SUBSTITUTE(Fact_Sales[[#This Row],[Revenue]]&""," USD",""),Fact_Sales[[#This Row],[Revenue]])-Fact_Sales[[#This Row],[Quantity]]*Fact_Sales[[#This Row],[ActualCost]]) -> 48060.32 | I13: =EOMONTH(Fact_Sales[[#This Row],[Date]],-1)+1 -> 45292 | J13: =IFERROR(Fact_Sales[[#This Row],[Quantity]]*Fact_Sales[[#This Row],[ActualCost]],0) -> 47659.88
... A53: 2024-01-12 | B53: CUST-015 | C53: PRD-009 | D53: 76010.45 | E53: 89 | F53: 0.05 | G53: {=IFERROR(--SUBSTITUTE(INDEX(Product_Costing!$I$2:$I$201,MATCH(1,(Product_Costing!$B$2:$B$201=Fact_Sales[[#This Row],[ProductID]])*(Product_Costing!$C$2:$C$201=DATE(YEAR(Fact_Sales[[#This Row],[Date]]),MONTH(Fact_Sales[[#This Row],[Date]]),1)),0))&""," USD",""),"")} -> 358.68 | H53: =IF(Fact_Sales[[#This Row],[Revenue]]="","",IFERROR(--SUBSTITUTE(Fact_Sales[[#This Row],[Revenue]]&""," USD",""),Fact_Sales[[#This Row],[Revenue]])-Fact_Sales[[#This Row],[Quantity]]*Fact_Sales[[#This Row],[ActualCost]]) -> 44087.93 | I53: =EOMONTH(Fact_Sales[[#This Row],[Date]],-1)+1 -> 45292 | J53: =IFERROR(Fact_Sales[[#This Row],[Quantity]]*Fact_Sales[[#This Row],[ActualCost]],0) -> 31922.52
A54: 2024-01-18 | B54: CUST-005 | C54: PRD-009 | E54: 197 | F54: 0.05 | G54: {=IFERROR(--SUBSTITUTE(INDEX(Product_Costing!$I$2:$I$201,MATCH(1,(Product_Costing!$B$2:$B$201=Fact_Sales[[#This Row],[ProductID]])*(Product_Costing!$C$2:$C$201=DATE(YEAR(Fact_Sales[[#This Row],[Date]]),MONTH(Fact_Sales[[#This Row],[Date]]),1)),0))&""," USD",""),"")} -> 358.68 | H54: =IF(Fact_Sales[[#This Row],[Revenue]]="","",IFERROR(--SUBSTITUTE(Fact_Sales[[#This Row],[Revenue]]&""," USD",""),Fact_Sales[[#This Row],[Revenue]])-Fact_Sales[[#This Row],[Quantity]]*Fact_Sales[[#This Row],[ActualCost]]) | I54: =EOMONTH(Fact_Sales[[#This Row],[Date]],-1)+1 -> 45292 | J54: =IFERROR(Fact_Sales[[#This Row],[Quantity]]*Fact_Sales[[#This Row],[ActualCost]],0) -> 70659.96
A55: 2024-01-20 | B55: CUST-010 | C55: PRD-009 | D55: 28273.55 | E55: 37 | F55: 0.15 | G55: {=IFERROR(--SUBSTITUTE(INDEX(Product_Costing!$I$2:$I$201,MATCH(1,(Product_Costing!$B$2:$B$201=Fact_Sales[[#This Row],[ProductID]])*(Product_Costing!$C$2:$C$201=DATE(YEAR(Fact_Sales[[#This Row],[Date]]),MONTH(Fact_Sales[[#This Row],[Date]]),1)),0))&""," USD",""),"")} -> 358.68 | H55: =IF(Fact_Sales[[#This Row],[Revenue]]="","",IFERROR(--SUBSTITUTE(Fact_Sales[[#This Row],[Revenue]]&""," USD",""),Fact_Sales[[#This Row],[Revenue]])-Fact_Sales[[#This Row],[Quantity]]*Fact_Sales[[#This Row],[ActualCost]]) -> 15002.39 | I55: =EOMONTH(Fact_Sales[[#This Row],[Date]],-1)+1 -> 45292 | J55: =IFERROR(Fact_Sales[[#This Row],[Quantity]]*Fact_Sales[[#This Row],[ActualCost]],0) -> 13271.16
A56: 2024-01-18 | B56: CUST-012 | C56: PRD-010 | D56: -297851 | E56: 149 | F56: 0 | G56: {=IFERROR(--SUBSTITUTE(INDEX(Product_Costing!$I$2:$I$201,MATCH(1,(Product_Costing!$B$2:$B$201=Fact_Sales[[#This Row],[ProductID]])*(Product_Costing!$C$2:$C$201=DATE(YEAR(Fact_Sales[[#This Row],[Date]]),MONTH(Fact_Sales[[#This Row],[Date]]),1)),0))&""," USD",""),"")} -> 840.57 | H56: =IF(Fact_Sales[[#This Row],[Revenue]]="","",IFERROR(--SUBSTITUTE(Fact_Sales[[#This Row],[Revenue]]&""," USD",""),Fact_Sales[[#This Row],[Revenue]])-Fact_Sales[[#This Row],[Quantity]]*Fact_Sales[[#This Row],[ActualCost]]) -> -423095.93 | I56: =EOMONTH(Fact_Sales[[#This Row],[Date]],-1)+1 -> 45292 | J56: =IFERROR(Fact_Sales[[#This Row],[Quantity]]*Fact_Sales[[#This Row],[ActualCost]],0) -> 125244.93
A57: 2024-01-17 | B57: CUST-010 | C57: PRD-010 | D57: 349025.4 | E57: 194 | F57: 0.1 | G57: {=IFERROR(--SUBSTITUTE(INDEX(Product_Costing!$I$2:$I$201,MATCH(1,(Product_Costing!$B$2:$B$201=Fact_Sales[[#This Row],[ProductID]])*(Product_Costing!$C$2:$C$201=DATE(YEAR(Fact_Sales[[#This Row],[Date]]),MONTH(Fact_Sales[[#This Row],[Date]]),1)),0))&""," USD",""),"")} -> 840.57 | H57: =IF(Fact_Sales[[#This Row],[Revenue]]="","",IFERROR(--SUBSTITUTE(Fact_Sales[[#This Row],[Revenue]]&""," USD",""),Fact_Sales[[#This Row],[Revenue]])-Fact_Sales[[#This Row],[Quantity]]*Fact_Sales[[#This Row],[ActualCost]]) -> 185954.82 | I57: =EOMONTH(Fact_Sales[[#This Row],[Date]],-1)+1 -> 45292 | J57: =IFERROR(Fact_Sales[[#This Row],[Quantity]]*Fact_Sales[[#This Row],[ActualCost]],0) -> 163070.58
A58: 2024-01-23 | B58: CUST-009 | C58: PRD-010 | D58: 55972 | E58: 28 | F58: 0 | G58: {=IFERROR(--SUBSTITUTE(INDEX(Product_Costing!$I$2:$I$201,MATCH(1,(Product_Costing!$B$2:$B$201=Fact_Sales[[#This Row],[ProductID]])*(Product_Costing!$C$2:$C$201=DATE(YEAR(Fact_Sales[[#This Row],[Date]]),MONTH(Fact_Sales[[#This Row],[Date]]),1)),0))&""," USD",""),"")} -> 840.57 | H58: =IF(Fact_Sales[[#This Row],[Revenue]]="","",IFERROR(--SUBSTITUTE(Fact_Sales[[#This Row],[Revenue]]&""," USD",""),Fact_Sales[[#This Row],[Revenue]])-Fact_Sales[[#This Row],[Quantity]]*Fact_Sales[[#This Row],[ActualCost]]) -> 32436.04 | I58: =EOMONTH(Fact_Sales[[#This Row],[Date]],-1)+1 -> 45292 | J58: =IFERROR(Fact_Sales[[#This Row],[Quantity]]*Fact_Sales[[#This Row],[ActualCost]],0) -> 23535.96
A59: 2024-01-21 | B59: CUST-015 | C59: PRD-010 | D59: 96851.55 | E59: 57 | F59: 0.15 | G59: {=IFERROR(--SUBSTITUTE(INDEX(Product_Costing!$I$2:$I$201,MATCH(1,(Product_Costing!$B$2:$B$201=Fact_Sales[[#This Row],[ProductID]])*(Product_Costing!$C$2:$C$201=DATE(YEAR(Fact_Sales[[#This Row],[Date]]),MONTH(Fact_Sales[[#This Row],[Date]]),1)),0))&""," USD",""),"")} -> 840.57 | H59: =IF(Fact_Sales[[#This Row],[Revenue]]="","",IFERROR(--SUBSTITUTE(Fact_Sales[[#This Row],[Revenue]]&""," USD",""),Fact_Sales[[#This Row],[Revenue]])-Fact_Sales[[#This Row],[Quantity]]*Fact_Sales[[#This Row],[ActualCost]]) -> 48939.06 | I59: =EOMONTH(Fact_Sales[[#This Row],[Date]],-1)+1 -> 45292 | J59: =IFERROR(Fact_Sales[[#This Row],[Quantity]]*Fact_Sales[[#This Row],[ActualCost]],0) -> 47912.49
A60: 2024-01-15 | B60: CUST-011 | C60: PRD-010 | D60: 298150.85 | E60: 157 | F60: 0.05 | G60: {=IFERROR(--SUBSTITUTE(INDEX(Product_Costing!$I$2:$I$201,MATCH(1,(Product_Costing!$B$2:$B$201=Fact_Sales[[#This Row],[ProductID]])*(Product_Costing!$C$2:$C$201=DATE(YEAR(Fact_Sales[[#This Row],[Date]]),MONTH(Fact_Sales[[#This Row],[Date]]),1)),0))&""," USD",""),"")} -> 840.57 | H60: =IF(Fact_Sales[[#This Row],[Revenue]]="","",IFERROR(--SUBSTITUTE(Fact_Sales[[#This Row],[Revenue]]&""," USD",""),Fact_Sales[[#This Row],[Revenue]])-Fact_Sales[[#This Row],[Quantity]]*Fact_Sales[[#This Row],[ActualCost]]) -> 166181.36 | I60: =EOMONTH(Fact_Sales[[#This Row],[Date]],-1)+1 -> 45292 | J60: =IFERROR(Fact_Sales[[#This Row],[Quantity]]*Fact_Sales[[#This Row],[ActualCost]],0) -> 131969.49
A61: 2024-01-27 | B61: CUST-014 | C61: PRD-010 | D61: 185907 | E61: 93 | F61: 0 | G61: {=IFERROR(--SUBSTITUTE(INDEX(Product_Costing!$I$2:$I$201,MATCH(1,(Product_Costing!$B$2:$B$201=Fact_Sales[[#This Row],[ProductID]])*(Product_Costing!$C$2:$C$201=DATE(YEAR(Fact_Sales[[#This Row],[Date]]),MONTH(Fact_Sales[[#This Row],[Date]]),1)),0))&""," USD",""),"")} -> 840.57 | H61: =IF(Fact_Sales[[#This Row],[Revenue]]="","",IFERROR(--SUBSTITUTE(Fact_Sales[[#This Row],[Revenue]]&""," USD",""),Fact_Sales[[#This Row],[Revenue]])-Fact_Sales[[#This Row],[Quantity]]*Fact_Sales[[#This Row],[ActualCost]]) -> 107733.99 | I61: =EOMONTH(Fact_Sales[[#This Row],[Date]],-1)+1 -> 45292 | J61: =IFERROR(Fact_Sales[[#This Row],[Quantity]]*Fact_Sales[[#This Row],[ActualCost]],0) -> 78173.01
A62: 2024-01-28 | B62: CUST-009 | C62: PRD-011 | E62: 59 | F62: 0 | G62: {=IFERROR(--SUBSTITUTE(INDEX(Product_Costing!$I$2:$I$201,MATCH(1,(Product_Costing!$B$2:$B$201=Fact_Sales[[#This Row],[ProductID]])*(Product_Costing!$C$2:$C$201=DATE(YEAR(Fact_Sales[[#This Row],[Date]]),MONTH(Fact_Sales[[#This Row],[Date]]),1)),0))&""," USD",""),"")} -> 75.56 | H62: =IF(Fact_Sales[[#This Row],[Revenue]]="","",IFERROR(--SUBSTITUTE(Fact_Sales[[#This Row],[Revenue]]&""," USD",""),Fact_Sales[[#This Row],[Revenue]])-Fact_Sales[[#This Row],[Quantity]]*Fact_Sales[[#This Row],[ActualCost]]) | I62: =EOMONTH(Fact_Sales[[#This Row],[Date]],-1)+1 -> 45292 | J62: =IFERROR(Fact_Sales[[#This Row],[Quantity]]*Fact_Sales[[#This Row],[ActualCost]],0) -> 4458.04
A63: 2024-01-23 | B63: CUST-009 | C63: PRD-011 | D63: 3206 | E63: 14 | F63: 0 | G63: {=IFERROR(--SUBSTITUTE(INDEX(Product_Costing!$I$2:$I$201,MATCH(1,(Product_Costing!$B$2:$B$201=Fact_Sales[[#This Row],[ProductID]])*(Product_Costing!$C$2:$C$201=DATE(YEAR(Fact_Sales[[#This Row],[Date]]),MONTH(Fact_Sales[[#This Row],[Date]]),1)),0))&""," USD",""),"")} -> 75.56 | H63: =IF(Fact_Sales[[#This Row],[Revenue]]="","",IFERROR(--SUBSTITUTE(Fact_Sales[[#This Row],[Revenue]]&""," USD",""),Fact_Sales[[#This Row],[Revenue]])-Fact_Sales[[#This Row],[Quantity]]*Fact_Sales[[#This Row],[ActualCost]]) -> 2148.16 | I63: =EOMONTH(Fact_Sales[[#This Row],[Date]],-1)+1 -> 45292 | J63: =IFERROR(Fact_Sales[[#This Row],[Quantity]]*Fact_Sales[[#This Row],[ActualCost]],0) -> 1057.84
A64: 2024-01-06 | B64: CUST-007 | C64: PRD-011 | D64: 16946 | E64: 74 | F64: 0 | G64: {=IFERROR(--SUBSTITUTE(INDEX(Product_Costing!$I$2:$I$201,MATCH(1,(Product_Costing!$B$2:$B$201=Fact_Sales[[#This Row],[ProductID]])*(Product_Costing!$C$2:$C$201=DATE(YEAR(Fact_Sales[[#This Row],[Date]]),MONTH(Fact_Sales[[#This Row],[Date]]),1)),0))&""," USD",""),"")} -> 75.56 | H64: =IF(Fact_Sales[[#This Row],[Revenue]]="","",IFERROR(--SUBSTITUTE(Fact_Sales[[#This Row],[Revenue]]&""," USD",""),Fact_Sales[[#This Row],[Revenue]])-Fact_Sales[[#This Row],[Quantity]]*Fact_Sales[[#This Row],[ActualCost]]) -> 11354.56 | I64: =EOMONTH(Fact_Sales[[#This Row],[Date]],-1)+1 -> 45292 | J64: =IFERROR(Fact_Sales[[#This Row],[Quantity]]*Fact_Sales[[#This Row],[ActualCost]],0) -> 5591.44
A65: 2024-01-08 | B65: CUST-002 | C65: PRD-011 | D65: 6183 | E65: 27 | F65: 0 | G65: {=IFERROR(--SUBSTITUTE(INDEX(Product_Costing!$I$2:$I$201,MATCH(1,(Product_Costing!$B$2:$B$201=Fact_Sales[[#This Row],[ProductID]])*(Product_Costing!$C$2:$C$201=DATE(YEAR(Fact_Sales[[#This Row],[Date]]),MONTH(Fact_Sales[[#This Row],[Date]]),1)),0))&""," USD",""),"")} -> 75.56 | H65: =IF(Fact_Sales[[#This Row],[Revenue]]="","",IFERROR(--SUBSTITUTE(Fact_Sales[[#This Row],[Revenue]]&""," USD",""),Fact_Sales[[#This Row],[Revenue]])-Fact_Sales[[#This Row],[Quantity]]*Fact_Sales[[#This Row],[ActualCost]]) -> 4142.88 | I65: =EOMONTH(Fact_Sales[[#This Row],[Date]],-1)+1 -> 45292 | J65: =IFERROR(Fact_Sales[[#This Row],[Quantity]]*Fact_Sales[[#This Row],[ActualCost]],0) -> 2040.12
A66: 2024-01-23 | B66: CUST-013 | C66: PRD-011 | D66: 7980.65 | E66: 41 | F66: 0.15 | G66: {=IFERROR(--SUBSTITUTE(INDEX(Product_Costing!$I$2:$I$201,MATCH(1,(Product_Costing!$B$2:$B$201=Fact_Sales[[#This Row],[ProductID]])*(Product_Costing!$C$2:$C$201=DATE(YEAR(Fact_Sales[[#This Row],[Date]]),MONTH(Fact_Sales[[#This Row],[Date]]),1)),0))&""," USD",""),"")} -> 75.56 | H66: =IF(Fact_Sales[[#This Row],[Revenue]]="","",IFERROR(--SUBSTITUTE(Fact_Sales[[#This Row],[Revenue]]&""," USD",""),Fact_Sales[[#This Row],[Revenue]])-Fact_Sales[[#This Row],[Quantity]]*Fact_Sales[[#This Row],[ActualCost]]) -> 4882.69 | I66: =EOMONTH(Fact_Sales[[#This Row],[Date]],-1)+1 -> 45292 | J66: =IFERROR(Fact_Sales[[#This Row],[Quantity]]*Fact_Sales[[#This Row],[ActualCost]],0) -> 3097.96
A67: 2024-01-25 | B67: CUST-008 | C67: PRD-011 | D67: 41552.05 | E67: 191 | F67: 0.05 | G67: {=IFERROR(--SUBSTITUTE(INDEX(Product_Costing!$I$2:$I$201,MATCH(1,(Product_Costing!$B$2:$B$201=Fact_Sales[[#This Row],[ProductID]])*(Product_Costing!$C$2:$C$201=DATE(YEAR(Fact_Sales[[#This Row],[Date]]),MONTH(Fact_Sales[[#This Row],[Date]]),1)),0))&""," USD",""),"")} -> 75.56 | H67: =IF(Fact_Sales[[#This Row],[Revenue]]="","",IFERROR(--SUBSTITUTE(Fact_Sales[[#This Row],[Revenue]]&""," USD",""),Fact_Sales[[#This Row],[Revenue]])-Fact_Sales[[#This Row],[Quantity]]*Fact_Sales[[#This Row],[ActualCost]]) -> 27120.09 | I67: =EOMONTH(Fact_Sales[[#This Row],[Date]],-1)+1 -> 45292 | J67: =IFERROR(Fact_Sales[[#This Row],[Quantity]]*Fact_Sales[[#This Row],[ActualCost]],0) -> 14431.96
A68: 2024-01-13 | B68: CUST-005 | C68: PRD-012 | D68: 29284.2 | E68: 108 | F68: 0.15 | G68: {=IFERROR(--SUBSTITUTE(INDEX(Product_Costing!$I$2:$I$201,MATCH(1,(Product_Costing!$B$2:$B$201=Fact_Sales[[#This Row],[ProductID]])*(Product_Costing!$C$2:$C$201=DATE(YEAR(Fact_Sales[[#This Row],[Date]]),MONTH(Fact_Sales[[#This Row],[Date]]),1)),0))&""," USD",""),"")} -> 113.68 | H68: =IF(Fact_Sales[[#This Row],[Revenue]]="","",IFERROR(--SUBSTITUTE(Fact_Sales[[#This Row],[Revenue]]&""," USD",""),Fact_Sales[[#This Row],[Revenue]])-Fact_Sales[[#This Row],[Quantity]]*Fact_Sales[[#This Row],[ActualCost]]) -> 17006.76 | I68: =EOMONTH(Fact_Sales[[#This Row],[Date]],-1)+1 -> 45292 | J68: =IFERROR(Fact_Sales[[#This Row],[Quantity]]*Fact_Sales[[#This Row],[ActualCost]],0) -> 12277.44
A69: 2024-01-21 | B69: CUST-002 | C69: PRD-012 | D69: 33176 | E69: 104 | F69: 0 | G69: {=IFERROR(--SUBSTITUTE(INDEX(Product_Costing!$I$2:$I$201,MATCH(1,(Product_Costing!$B$2:$B$201=Fact_Sales[[#This Row],[ProductID]])*(Product_Costing!$C$2:$C$201=DATE(YEAR(Fact_Sales[[#This Row],[Date]]),MONTH(Fact_Sales[[#This Row],[Date]]),1)),0))&""," USD",""),"")} -> 113.68 | H69: =IF(Fact_Sales[[#This Row],[Revenue]]="","",IFERROR(--SUBSTITUTE(Fact_Sales[[#This Row],[Revenue]]&""," USD",""),Fact_Sales[[#This Row],[Revenue]])-Fact_Sales[[#This Row],[Quantity]]*Fact_Sales[[#This Row],[ActualCost]]) -> 21353.28 | I69: =EOMONTH(Fact_Sales[[#This Row],[Date]],-1)+1 -> 45292 | J69: =IFERROR(Fact_Sales[[#This Row],[Quantity]]*Fact_Sales[[#This Row],[ActualCost]],0) -> 11822.72
A70: 2024-01-11 | B70: CUST-013 | C70: PRD-012 | D70: 56973.4 | E70: 188 | F70: 0.05 | G70: {=IFERROR(--SUBSTITUTE(INDEX(Product_Costing!$I$2:$I$201,MATCH(1,(Product_Costing!$B$2:$B$201=Fact_Sales[[#This Row],[ProductID]])*(Product_Costing!$C$2:$C$201=DATE(YEAR(Fact_Sales[[#This Row],[Date]]),MONTH(Fact_Sales[[#This Row],[Date]]),1)),0))&""," USD",""),"")} -> 113.68 | H70: =IF(Fact_Sales[[#This Row],[Revenue]]="","",IFERROR(--SUBSTITUTE(Fact_Sales[[#This Row],[Revenue]]&""," USD",""),Fact_Sales[[#This Row],[Revenue]])-Fact_Sales[[#This Row],[Quantity]]*Fact_Sales[[#This Row],[ActualCost]]) -> 35601.56 | I70: =EOMONTH(Fact_Sales[[#This Row],[Date]],-1)+1 -> 45292 | J70: =IFERROR(Fact_Sales[[#This Row],[Quantity]]*Fact_Sales[[#This Row],[ActualCost]],0) -> 21371.84
A71: 2024-01-17 | B71: CUST-001 | C71: PRD-012 | D71: -3732.3 | E71: 13 | F71: 0.1 | G71: {=IFERROR(--SUBSTITUTE(INDEX(Product_Costing!$I$2:$I$201,MATCH(1,(Product_Costing!$B$2:$B$201=Fact_Sales[[#This Row],[ProductID]])*(Product_Costing!$C$2:$C$201=DATE(YEAR(Fact_Sales[[#This Row],[Date]]),MONTH(Fact_Sales[[#This Row],[Date]]),1)),0))&""," USD",""),"")} -> 113.68 | H71: =IF(Fact_Sales[[#This Row],[Revenue]]="","",IFERROR(--SUBSTITUTE(Fact_Sales[[#This Row],[Revenue]]&""," USD",""),Fact_Sales[[#This Row],[Revenue]])-Fact_Sales[[#This Row],[Quantity]]*Fact_Sales[[#This Row],[ActualCost]]) -> -5210.14 | I71: =EOMONTH(Fact_Sales[[#This Row],[Date]],-1)+1 -> 45292 | J71: =IFERROR(Fact_Sales[[#This Row],[Quantity]]*Fact_Sales[[#This Row],[ActualCost]],0) -> 1477.84
A72: 2024-01-20 | B72: CUST-010 | C72: PRD-013 | D72: 38321.4 | E72: 156 | F72: 0.15 | G72: {=IFERROR(--SUBSTITUTE(INDEX(Product_Costing!$I$2:$I$201,MATCH(1,(Product_Costing!$B$2:$B$201=Fact_Sales[[#This Row],[ProductID]])*(Product_Costing!$C$2:$C$201=DATE(YEAR(Fact_Sales[[#This Row],[Date]]),MONTH(Fact_Sales[[#This Row],[Date]]),1)),0))&""," USD",""),"")} -> 109.61 | H72: =IF(Fact_Sales[[#This Row],[Revenue]]="","",IFERROR(--SUBSTITUTE(Fact_Sales[[#This Row],[Revenue]]&""," USD",""),Fact_Sales[[#This Row],[Revenue]])-Fact_Sales[[#This Row],[Quantity]]*Fact_Sales[[#This Row],[ActualCost]]) -> 21222.24 | I72: =EOMONTH(Fact_Sales[[#This Row],[Date]],-1)+1 -> 45292 | J72: =IFERROR(Fact_Sales[[#This Row],[Quantity]]*Fact_Sales[[#This Row],[ActualCost]],0) -> 17099.16
A73: 2024-01-23 | B73: CUST-007 | C73: PRD-013 | D73: 6502.5 | E73: 25 | F73: 0.1 | G73: {=IFERROR(--SUBSTITUTE(INDEX(Product_Costing!$I$2:$I$201,MATCH(1,(Product_Costing!$B$2:$B$201=Fact_Sales[[#This Row],[ProductID]])*(Product_Costing!$C$2:$C$201=DATE(YEAR(Fact_Sales[[#This Row],[Date]]),MONTH(Fact_Sales[[#This Row],[Date]]),1)),0))&""," USD",""),"")} -> 109.61 | H73: =IF(Fact_Sales[[#This Row],[Revenue]]="","",IFERROR(--SUBSTITUTE(Fact_Sales[[#This Row],[Revenue]]&""," USD",""),Fact_Sales[[#This Row],[Revenue]])-Fact_Sales[[#This Row],[Quantity]]*Fact_Sales[[#This Row],[ActualCost]]) -> 3762.25 | I73: =EOMONTH(Fact_Sales[[#This Row],[Date]],-1)+1 -> 45292 | J73: =IFERROR(Fact_Sales[[#This Row],[Quantity]]*Fact_Sales[[#This Row],[ActualCost]],0) -> 2740.25
A74: 2024-01-08 | B74: CUST-002 | C74: PRD-013 | D74: 35373.6 | E74: 136 | F74: 0.1 | G74: {=IFERROR(--SUBSTITUTE(INDEX(Product_Costing!$I$2:$I$201,MATCH(1,(Product_Costing!$B$2:$B$201=Fact_Sales[[#This Row],[ProductID]])*(Product_Costing!$C$2:$C$201=DATE(YEAR(Fact_Sales[[#This Row],[Date]]),MONTH(Fact_Sales[[#This Row],[Date]]),1)),0))&""," USD",""),"")} -> 109.61 | H74: =IF(Fact_Sales[[#This Row],[Revenue]]="","",IFERROR(--SUBSTITUTE(Fact_Sales[[#This Row],[Revenue]]&""," USD",""),Fact_Sales[[#This Row],[Revenue]])-Fact_Sales[[#This Row],[Quantity]]*Fact_Sales[[#This Row],[ActualCost]]) -> 20466.64 | I74: =EOMONTH(Fact_Sales[[#This Row],[Date]],-1)+1 -> 45292 | J74: =IFERROR(Fact_Sales[[#This Row],[Quantity]]*Fact_Sales[[#This Row],[ActualCost]],0) -> 14906.96
... A118: 2024-02-03 | B118: CUST-013 | C118: PRD-004 | D118: 131695.65 | E118: 73 | F118: 0.05 | G118: {=IFERROR(--SUBSTITUTE(INDEX(Product_Costing!$I$2:$I$201,MATCH(1,(Product_Costing!$B$2:$B$201=Fact_Sales[[#This Row],[ProductID]])*(Product_Costing!$C$2:$C$201=DATE(YEAR(Fact_Sales[[#This Row],[Date]]),MONTH(Fact_Sales[[#This Row],[Date]]),1)),0))&""," USD",""),"")} -> 811.22 | H118: =IF(Fact_Sales[[#This Row],[Revenue]]="","",IFERROR(--SUBSTITUTE(Fact_Sales[[#This Row],[Revenue]]&""," USD",""),Fact_Sales[[#This Row],[Revenue]])-Fact_Sales[[#This Row],[Quantity]]*Fact_Sales[[#This Row],[ActualCost]]) -> 72476.59 | I118: =EOMONTH(Fact_Sales[[#This Row],[Date]],-1)+1 -> 45323 | J118: =IFERROR(Fact_Sales[[#This Row],[Quantity]]*Fact_Sales[[#This Row],[ActualCost]],0) -> 59219.06
A119: 2024-02-24 | B119: CUST-004 | C119: PRD-004 | E119: 151 | F119: 0.1 | G119: {=IFERROR(--SUBSTITUTE(INDEX(Product_Costing!$I$2:$I$201,MATCH(1,(Product_Costing!$B$2:$B$201=Fact_Sales[[#This Row],[ProductID]])*(Product_Costing!$C$2:$C$201=DATE(YEAR(Fact_Sales[[#This Row],[Date]]),MONTH(Fact_Sales[[#This Row],[Date]]),1)),0))&""," USD",""),"")} -> 811.22 | H119: =IF(Fact_Sales[[#This Row],[Revenue]]="","",IFERROR(--SUBSTITUTE(Fact_Sales[[#This Row],[Revenue]]&""," USD",""),Fact_Sales[[#This Row],[Revenue]])-Fact_Sales[[#This Row],[Quantity]]*Fact_Sales[[#This Row],[ActualCost]]) | I119: =EOMONTH(Fact_Sales[[#This Row],[Date]],-1)+1 -> 45323 | J119: =IFERROR(Fact_Sales[[#This Row],[Quantity]]*Fact_Sales[[#This Row],[ActualCost]],0) -> 122494.22
A120: 2024-02-26 | B120: CUST-001 | C120: PRD-004 | D120: 112041 | E120: 59 | F120: 0 | G120: {=IFERROR(--SUBSTITUTE(INDEX(Product_Costing!$I$2:$I$201,MATCH(1,(Product_Costing!$B$2:$B$201=Fact_Sales[[#This Row],[ProductID]])*(Product_Costing!$C$2:$C$201=DATE(YEAR(Fact_Sales[[#This Row],[Date]]),MONTH(Fact_Sales[[#This Row],[Date]]),1)),0))&""," USD",""),"")} -> 811.22 | H120: =IF(Fact_Sales[[#This Row],[Revenue]]="","",IFERROR(--SUBSTITUTE(Fact_Sales[[#This Row],[Revenue]]&""," USD",""),Fact_Sales[[#This Row],[Revenue]])-Fact_Sales[[#This Row],[Quantity]]*Fact_Sales[[#This Row],[ActualCost]]) -> 64179.02 | I120: =EOMONTH(Fact_Sales[[#This Row],[Date]],-1)+1 -> 45323 | J120: =IFERROR(Fact_Sales[[#This Row],[Quantity]]*Fact_Sales[[#This Row],[ActualCost]],0) -> 47861.98
A121: 2024-02-24 | B121: CUST-014 | C121: PRD-005 | D121: 18500.3 | E121: 26 | F121: 0.05 | G121: {=IFERROR(--SUBSTITUTE(INDEX(Product_Costing!$I$2:$I$201,MATCH(1,(Product_Costing!$B$2:$B$201=Fact_Sales[[#This Row],[ProductID]])*(Product_Costing!$C$2:$C$201=DATE(YEAR(Fact_Sales[[#This Row],[Date]]),MONTH(Fact_Sales[[#This Row],[Date]]),1)),0))&""," USD",""),"")} -> 295.58 | H121: =IF(Fact_Sales[[#This Row],[Revenue]]="","",IFERROR(--SUBSTITUTE(Fact_Sales[[#This Row],[Revenue]]&""," USD",""),Fact_Sales[[#This Row],[Revenue]])-Fact_Sales[[#This Row],[Quantity]]*Fact_Sales[[#This Row],[ActualCost]]) -> 10815.22 | I121: =EOMONTH(Fact_Sales[[#This Row],[Date]],-1)+1 -> 45323 | J121: =IFERROR(Fact_Sales[[#This Row],[Quantity]]*Fact_Sales[[#This Row],[ActualCost]],0) -> 7685.08
A122: 2024-02-15 | B122: CUST-015 | C122: PRD-005 | D122: 25466 | E122: 34 | F122: 0 | G122: {=IFERROR(--SUBSTITUTE(INDEX(Product_Costing!$I$2:$I$201,MATCH(1,(Product_Costing!$B$2:$B$201=Fact_Sales[[#This Row],[ProductID]])*(Product_Costing!$C$2:$C$201=DATE(YEAR(Fact_Sales[[#This Row],[Date]]),MONTH(Fact_Sales[[#This Row],[Date]]),1)),0))&""," USD",""),"")} -> 295.58 | H122: =IF(Fact_Sales[[#This Row],[Revenue]]="","",IFERROR(--SUBSTITUTE(Fact_Sales[[#This Row],[Revenue]]&""," USD",""),Fact_Sales[[#This Row],[Revenue]])-Fact_Sales[[#This Row],[Quantity]]*Fact_Sales[[#This Row],[ActualCost]]) -> 15416.28 | I122: =EOMONTH(Fact_Sales[[#This Row],[Date]],-1)+1 -> 45323 | J122: =IFERROR(Fact_Sales[[#This Row],[Quantity]]*Fact_Sales[[#This Row],[ActualCost]],0) -> 10049.72
A123: 2024-02-13 | B123: CUST-014 | C123: PRD-005 | D123: 143808 | E123: 192 | F123: 0 | G123: {=IFERROR(--SUBSTITUTE(INDEX(Product_Costing!$I$2:$I$201,MATCH(1,(Product_Costing!$B$2:$B$201=Fact_Sales[[#This Row],[ProductID]])*(Product_Costing!$C$2:$C$201=DATE(YEAR(Fact_Sales[[#This Row],[Date]]),MONTH(Fact_Sales[[#This Row],[Date]]),1)),0))&""," USD",""),"")} -> 295.58 | H123: =IF(Fact_Sales[[#This Row],[Revenue]]="","",IFERROR(--SUBSTITUTE(Fact_Sales[[#This Row],[Revenue]]&""," USD",""),Fact_Sales[[#This Row],[Revenue]])-Fact_Sales[[#This Row],[Quantity]]*Fact_Sales[[#This Row],[ActualCost]]) -> 87056.64 | I123: =EOMONTH(Fact_Sales[[#This Row],[Date]],-1)+1 -> 45323 | J123: =IFERROR(Fact_Sales[[#This Row],[Quantity]]*Fact_Sales[[#This Row],[ActualCost]],0) -> 56751.36
A124: 2024-02-21 | B124: CUST-003 | C124: PRD-005 | D124: 106358 | E124: 142 | F124: 0 | G124: {=IFERROR(--SUBSTITUTE(INDEX(Product_Costing!$I$2:$I$201,MATCH(1,(Product_Costing!$B$2:$B$201=Fact_Sales[[#This Row],[ProductID]])*(Product_Costing!$C$2:$C$201=DATE(YEAR(Fact_Sales[[#This Row],[Date]]),MONTH(Fact_Sales[[#This Row],[Date]]),1)),0))&""," USD",""),"")} -> 295.58 | H124: =IF(Fact_Sales[[#This Row],[Revenue]]="","",IFERROR(--SUBSTITUTE(Fact_Sales[[#This Row],[Revenue]]&""," USD",""),Fact_Sales[[#This Row],[Revenue]])-Fact_Sales[[#This Row],[Quantity]]*Fact_Sales[[#This Row],[ActualCost]]) -> 64385.64 | I124: =EOMONTH(Fact_Sales[[#This Row],[Date]],-1)+1 -> 45323 | J124: =IFERROR(Fact_Sales[[#This Row],[Quantity]]*Fact_Sales[[#This Row],[ActualCost]],0) -> 41972.36
A125: 2024-02-12 | B125: CUST-004 | C125: PRD-005 | D125: 67410 | E125: 90 | F125: 0 | G125: {=IFERROR(--SUBSTITUTE(INDEX(Product_Costing!$I$2:$I$201,MATCH(1,(Product_Costing!$B$2:$B$201=Fact_Sales[[#This Row],[ProductID]])*(Product_Costing!$C$2:$C$201=DATE(YEAR(Fact_Sales[[#This Row],[Date]]),MONTH(Fact_Sales[[#This Row],[Date]]),1)),0))&""," USD",""),"")} -> 295.58 | H125: =IF(Fact_Sales[[#This Row],[Revenue]]="","",IFERROR(--SUBSTITUTE(Fact_Sales[[#This Row],[Revenue]]&""," USD",""),Fact_Sales[[#This Row],[Revenue]])-Fact_Sales[[#This Row],[Quantity]]*Fact_Sales[[#This Row],[ActualCost]]) -> 40807.8 | I125: =EOMONTH(Fact_Sales[[#This Row],[Date]],-1)+1 -> 45323 | J125: =IFERROR(Fact_Sales[[#This Row],[Quantity]]*Fact_Sales[[#This Row],[ActualCost]],0) -> 26602.2
A126: 2024-02-01 | B126: CUST-010 | C126: PRD-005 | D126: 35577.5 | E126: 50 | F126: 0.05 | G126: {=IFERROR(--SUBSTITUTE(INDEX(Product_Costing!$I$2:$I$201,MATCH(1,(Product_Costing!$B$2:$B$201=Fact_Sales[[#This Row],[ProductID]])*(Product_Costing!$C$2:$C$201=DATE(YEAR(Fact_Sales[[#This Row],[Date]]),MONTH(Fact_Sales[[#This Row],[Date]]),1)),0))&""," USD",""),"")} -> 295.58 | H126: =IF(Fact_Sales[[#This Row],[Revenue]]="","",IFERROR(--SUBSTITUTE(Fact_Sales[[#This Row],[Revenue]]&""," USD",""),Fact_Sales[[#This Row],[Revenue]])-Fact_Sales[[#This Row],[Quantity]]*Fact_Sales[[#This Row],[ActualCost]]) -> 20798.5 | I126: =EOMONTH(Fact_Sales[[#This Row],[Date]],-1)+1 -> 45323 | J126: =IFERROR(Fact_Sales[[#This Row],[Quantity]]*Fact_Sales[[#This Row],[ActualCost]],0) -> 14779
A127: 2024-02-14 | B127: CUST-006 | C127: PRD-005 | D127: 7415.1 | E127: 11 | F127: 0.1 | G127: {=IFERROR(--SUBSTITUTE(INDEX(Product_Costing!$I$2:$I$201,MATCH(1,(Product_Costing!$B$2:$B$201=Fact_Sales[[#This Row],[ProductID]])*(Product_Costing!$C$2:$C$201=DATE(YEAR(Fact_Sales[[#This Row],[Date]]),MONTH(Fact_Sales[[#This Row],[Date]]),1)),0))&""," USD",""),"")} -> 295.58 | H127: =IF(Fact_Sales[[#This Row],[Revenue]]="","",IFERROR(--SUBSTITUTE(Fact_Sales[[#This Row],[Revenue]]&""," USD",""),Fact_Sales[[#This Row],[Revenue]])-Fact_Sales[[#This Row],[Quantity]]*Fact_Sales[[#This Row],[ActualCost]]) -> 4163.72 | I127: =EOMONTH(Fact_Sales[[#This Row],[Date]],-1)+1 -> 45323 | J127: =IFERROR(Fact_Sales[[#This Row],[Quantity]]*Fact_Sales[[#This Row],[ActualCost]],0) -> 3251.38
A128: 2024-02-20 | B128: CUST-007 | C128: PRD-006 | D128: 74338 | E128: 62 | F128: 0 | G128: {=IFERROR(--SUBSTITUTE(INDEX(Product_Costing!$I$2:$I$201,MATCH(1,(Product_Costing!$B$2:$B$201=Fact_Sales[[#This Row],[ProductID]])*(Product_Costing!$C$2:$C$201=DATE(YEAR(Fact_Sales[[#This Row],[Date]]),MONTH(Fact_Sales[[#This Row],[Date]]),1)),0))&""," USD",""),"")} -> 494.5 | H128: =IF(Fact_Sales[[#This Row],[Revenue]]="","",IFERROR(--SUBSTITUTE(Fact_Sales[[#This Row],[Revenue]]&""," USD",""),Fact_Sales[[#This Row],[Revenue]])-Fact_Sales[[#This Row],[Quantity]]*Fact_Sales[[#This Row],[ActualCost]]) -> 43679 | I128: =EOMONTH(Fact_Sales[[#This Row],[Date]],-1)+1 -> 45323 | J128: =IFERROR(Fact_Sales[[#This Row],[Quantity]]*Fact_Sales[[#This Row],[ActualCost]],0) -> 30659
A129: 2024-02-20 | B129: CUST-013 | C129: PRD-006 | D129: 209825 | E129: 175 | F129: 0 | G129: {=IFERROR(--SUBSTITUTE(INDEX(Product_Costing!$I$2:$I$201,MATCH(1,(Product_Costing!$B$2:$B$201=Fact_Sales[[#This Row],[ProductID]])*(Product_Costing!$C$2:$C$201=DATE(YEAR(Fact_Sales[[#This Row],[Date]]),MONTH(Fact_Sales[[#This Row],[Date]]),1)),0))&""," USD",""),"")} -> 494.5 | H129: =IF(Fact_Sales[[#This Row],[Revenue]]="","",IFERROR(--SUBSTITUTE(Fact_Sales[[#This Row],[Revenue]]&""," USD",""),Fact_Sales[[#This Row],[Revenue]])-Fact_Sales[[#This Row],[Quantity]]*Fact_Sales[[#This Row],[ActualCost]]) -> 123287.5 | I129: =EOMONTH(Fact_Sales[[#This Row],[Date]],-1)+1 -> 45323 | J129: =IFERROR(Fact_Sales[[#This Row],[Quantity]]*Fact_Sales[[#This Row],[ActualCost]],0) -> 86537.5
A130: 2024-02-02 | B130: CUST-005 | C130: PRD-006 | D130: 45562 | E130: 38 | F130: 0 | G130: {=IFERROR(--SUBSTITUTE(INDEX(Product_Costing!$I$2:$I$201,MATCH(1,(Product_Costing!$B$2:$B$201=Fact_Sales[[#This Row],[ProductID]])*(Product_Costing!$C$2:$C$201=DATE(YEAR(Fact_Sales[[#This Row],[Date]]),MONTH(Fact_Sales[[#This Row],[Date]]),1)),0))&""," USD",""),"")} -> 494.5 | H130: =IF(Fact_Sales[[#This Row],[Revenue]]="","",IFERROR(--SUBSTITUTE(Fact_Sales[[#This Row],[Revenue]]&""," USD",""),Fact_Sales[[#This Row],[Revenue]])-Fact_Sales[[#This Row],[Quantity]]*Fact_Sales[[#This Row],[ActualCost]]) -> 26771 | I130: =EOMONTH(Fact_Sales[[#This Row],[Date]],-1)+1 -> 45323 | J130: =IFERROR(Fact_Sales[[#This Row],[Quantity]]*Fact_Sales[[#This Row],[ActualCost]],0) -> 18791
A131: 2024-02-08 | B131: CUST-001 | C131: PRD-007 | D131: 57096 | E131: 104 | F131: 0 | G131: {=IFERROR(--SUBSTITUTE(INDEX(Product_Costing!$I$2:$I$201,MATCH(1,(Product_Costing!$B$2:$B$201=Fact_Sales[[#This Row],[ProductID]])*(Product_Costing!$C$2:$C$201=DATE(YEAR(Fact_Sales[[#This Row],[Date]]),MONTH(Fact_Sales[[#This Row],[Date]]),1)),0))&""," USD",""),"")} -> 215.7 | H131: =IF(Fact_Sales[[#This Row],[Revenue]]="","",IFERROR(--SUBSTITUTE(Fact_Sales[[#This Row],[Revenue]]&""," USD",""),Fact_Sales[[#This Row],[Revenue]])-Fact_Sales[[#This Row],[Quantity]]*Fact_Sales[[#This Row],[ActualCost]]) -> 34663.2 | I131: =EOMONTH(Fact_Sales[[#This Row],[Date]],-1)+1 -> 45323 | J131: =IFERROR(Fact_Sales[[#This Row],[Quantity]]*Fact_Sales[[#This Row],[ActualCost]],0) -> 22432.8
... A181: 2024-03-27 | B181: CUST-011 | C181: PRD-001 | D181: 61406.1 | E181: 162 | F181: 0.05 | G181: {=IFERROR(--SUBSTITUTE(INDEX(Product_Costing!$I$2:$I$201,MATCH(1,(Product_Costing!$B$2:$B$201=Fact_Sales[[#This Row],[ProductID]])*(Product_Costing!$C$2:$C$201=DATE(YEAR(Fact_Sales[[#This Row],[Date]]),MONTH(Fact_Sales[[#This Row],[Date]]),1)),0))&""," USD",""),"")} -> 182.76 | H181: =IF(Fact_Sales[[#This Row],[Revenue]]="","",IFERROR(--SUBSTITUTE(Fact_Sales[[#This Row],[Revenue]]&""," USD",""),Fact_Sales[[#This Row],[Revenue]])-Fact_Sales[[#This Row],[Quantity]]*Fact_Sales[[#This Row],[ActualCost]]) -> 31798.98 | I181: =EOMONTH(Fact_Sales[[#This Row],[Date]],-1)+1 -> 45352 | J181: =IFERROR(Fact_Sales[[#This Row],[Quantity]]*Fact_Sales[[#This Row],[ActualCost]],0) -> 29607.12
A182: 2024-03-28 | B182: CUST-006 | C182: PRD-001 | E182: 118 | F182: 0.1 | G182: {=IFERROR(--SUBSTITUTE(INDEX(Product_Costing!$I$2:$I$201,MATCH(1,(Product_Costing!$B$2:$B$201=Fact_Sales[[#This Row],[ProductID]])*(Product_Costing!$C$2:$C$201=DATE(YEAR(Fact_Sales[[#This Row],[Date]]),MONTH(Fact_Sales[[#This Row],[Date]]),1)),0))&""," USD",""),"")} -> 182.76 | H182: =IF(Fact_Sales[[#This Row],[Revenue]]="","",IFERROR(--SUBSTITUTE(Fact_Sales[[#This Row],[Revenue]]&""," USD",""),Fact_Sales[[#This Row],[Revenue]])-Fact_Sales[[#This Row],[Quantity]]*Fact_Sales[[#This Row],[ActualCost]]) | I182: =EOMONTH(Fact_Sales[[#This Row],[Date]],-1)+1 -> 45352 | J182: =IFERROR(Fact_Sales[[#This Row],[Quantity]]*Fact_Sales[[#This Row],[ActualCost]],0) -> 21565.68
A183: 2024-03-09 | B183: CUST-013 | C183: PRD-001 | D183: 36269.1 | E183: 101 | F183: 0.1 | G183: {=IFERROR(--SUBSTITUTE(INDEX(Product_Costing!$I$2:$I$201,MATCH(1,(Product_Costing!$B$2:$B$201=Fact_Sales[[#This Row],[ProductID]])*(Product_Costing!$C$2:$C$201=DATE(YEAR(Fact_Sales[[#This Row],[Date]]),MONTH(Fact_Sales[[#This Row],[Date]]),1)),0))&""," USD",""),"")} -> 182.76 | H183: =IF(Fact_Sales[[#This Row],[Revenue]]="","",IFERROR(--SUBSTITUTE(Fact_Sales[[#This Row],[Revenue]]&""," USD",""),Fact_Sales[[#This Row],[Revenue]])-Fact_Sales[[#This Row],[Quantity]]*Fact_Sales[[#This Row],[ActualCost]]) -> 17810.34 | I183: =EOMONTH(Fact_Sales[[#This Row],[Date]],-1)+1 -> 45352 | J183: =IFERROR(Fact_Sales[[#This Row],[Quantity]]*Fact_Sales[[#This Row],[ActualCost]],0) -> 18458.76
A184: 2024-03-16 | B184: CUST-009 | C184: PRD-001 | D184: 47760.3 | E184: 133 | F184: 0.1 | G184: {=IFERROR(--SUBSTITUTE(INDEX(Product_Costing!$I$2:$I$201,MATCH(1,(Product_Costing!$B$2:$B$201=Fact_Sales[[#This Row],[ProductID]])*(Product_Costing!$C$2:$C$201=DATE(YEAR(Fact_Sales[[#This Row],[Date]]),MONTH(Fact_Sales[[#This Row],[Date]]),1)),0))&""," USD",""),"")} -> 182.76 | H184: =IF(Fact_Sales[[#This Row],[Revenue]]="","",IFERROR(--SUBSTITUTE(Fact_Sales[[#This Row],[Revenue]]&""," USD",""),Fact_Sales[[#This Row],[Revenue]])-Fact_Sales[[#This Row],[Quantity]]*Fact_Sales[[#This Row],[ActualCost]]) -> 23453.22 | I184: =EOMONTH(Fact_Sales[[#This Row],[Date]],-1)+1 -> 45352 | J184: =IFERROR(Fact_Sales[[#This Row],[Quantity]]*Fact_Sales[[#This Row],[ActualCost]],0) -> 24307.08
A185: 2024-03-09 | B185: CUST-012 | C185: PRD-001 | D185: 44428.65 | E185: 131 | F185: 0.15 | G185: {=IFERROR(--SUBSTITUTE(INDEX(Product_Costing!$I$2:$I$201,MATCH(1,(Product_Costing!$B$2:$B$201=Fact_Sales[[#This Row],[ProductID]])*(Product_Costing!$C$2:$C$201=DATE(YEAR(Fact_Sales[[#This Row],[Date]]),MONTH(Fact_Sales[[#This Row],[Date]]),1)),0))&""," USD",""),"")} -> 182.76 | H185: =IF(Fact_Sales[[#This Row],[Revenue]]="","",IFERROR(--SUBSTITUTE(Fact_Sales[[#This Row],[Revenue]]&""," USD",""),Fact_Sales[[#This Row],[Revenue]])-Fact_Sales[[#This Row],[Quantity]]*Fact_Sales[[#This Row],[ActualCost]]) -> 20487.09 | I185: =EOMONTH(Fact_Sales[[#This Row],[Date]],-1)+1 -> 45352 | J185: =IFERROR(Fact_Sales[[#This Row],[Quantity]]*Fact_Sales[[#This Row],[ActualCost]],0) -> 23941.56
A186: 2024-03-02 | B186: CUST-006 | C186: PRD-001 | D186: 47760.3 | E186: 126 | F186: 0.05 | G186: {=IFERROR(--SUBSTITUTE(INDEX(Product_Costing!$I$2:$I$201,MATCH(1,(Product_Costing!$B$2:$B$201=Fact_Sales[[#This Row],[ProductID]])*(Product_Costing!$C$2:$C$201=DATE(YEAR(Fact_Sales[[#This Row],[Date]]),MONTH(Fact_Sales[[#This Row],[Date]]),1)),0))&""," USD",""),"")} -> 182.76 | H186: =IF(Fact_Sales[[#This Row],[Revenue]]="","",IFERROR(--SUBSTITUTE(Fact_Sales[[#This Row],[Revenue]]&""," USD",""),Fact_Sales[[#This Row],[Revenue]])-Fact_Sales[[#This Row],[Quantity]]*Fact_Sales[[#This Row],[ActualCost]]) -> 24732.54 | I186: =EOMONTH(Fact_Sales[[#This Row],[Date]],-1)+1 -> 45352 | J186: =IFERROR(Fact_Sales[[#This Row],[Quantity]]*Fact_Sales[[#This Row],[ActualCost]],0) -> 23027.76
A187: 2024-03-21 | B187: CUST-014 | C187: PRD-002 | D187: 52292.7 | E187: 97 | F187: 0.1 | G187: {=IFERROR(--SUBSTITUTE(INDEX(Product_Costing!$I$2:$I$201,MATCH(1,(Product_Costing!$B$2:$B$201=Fact_Sales[[#This Row],[ProductID]])*(Product_Costing!$C$2:$C$201=DATE(YEAR(Fact_Sales[[#This Row],[Date]]),MONTH(Fact_Sales[[#This Row],[Date]]),1)),0))&""," USD",""),"")} -> 267.29 | H187: =IF(Fact_Sales[[#This Row],[Revenue]]="","",IFERROR(--SUBSTITUTE(Fact_Sales[[#This Row],[Revenue]]&""," USD",""),Fact_Sales[[#This Row],[Revenue]])-Fact_Sales[[#This Row],[Quantity]]*Fact_Sales[[#This Row],[ActualCost]]) -> 26365.57 | I187: =EOMONTH(Fact_Sales[[#This Row],[Date]],-1)+1 -> 45352 | J187: =IFERROR(Fact_Sales[[#This Row],[Quantity]]*Fact_Sales[[#This Row],[ActualCost]],0) -> 25927.13
A188: 2024-03-17 | B188: CUST-002 | C188: PRD-002 | D188: -19767 | E188: 33 | F188: 0 | G188: {=IFERROR(--SUBSTITUTE(INDEX(Product_Costing!$I$2:$I$201,MATCH(1,(Product_Costing!$B$2:$B$201=Fact_Sales[[#This Row],[ProductID]])*(Product_Costing!$C$2:$C$201=DATE(YEAR(Fact_Sales[[#This Row],[Date]]),MONTH(Fact_Sales[[#This Row],[Date]]),1)),0))&""," USD",""),"")} -> 267.29 | H188: =IF(Fact_Sales[[#This Row],[Revenue]]="","",IFERROR(--SUBSTITUTE(Fact_Sales[[#This Row],[Revenue]]&""," USD",""),Fact_Sales[[#This Row],[Revenue]])-Fact_Sales[[#This Row],[Quantity]]*Fact_Sales[[#This Row],[ActualCost]]) -> -28587.57 | I188: =EOMONTH(Fact_Sales[[#This Row],[Date]],-1)+1 -> 45352 | J188: =IFERROR(Fact_Sales[[#This Row],[Quantity]]*Fact_Sales[[#This Row],[ActualCost]],0) -> 8820.57
A189: 2024-03-16 | B189: CUST-011 | C189: PRD-002 | D189: 19347.7 | E189: 38 | F189: 0.15 | G189: {=IFERROR(--SUBSTITUTE(INDEX(Product_Costing!$I$2:$I$201,MATCH(1,(Product_Costing!$B$2:$B$201=Fact_Sales[[#This Row],[ProductID]])*(Product_Costing!$C$2:$C$201=DATE(YEAR(Fact_Sales[[#This Row],[Date]]),MONTH(Fact_Sales[[#This Row],[Date]]),1)),0))&""," USD",""),"")} -> 267.29 | H189: =IF(Fact_Sales[[#This Row],[Revenue]]="","",IFERROR(--SUBSTITUTE(Fact_Sales[[#This Row],[Revenue]]&""," USD",""),Fact_Sales[[#This Row],[Revenue]])-Fact_Sales[[#This Row],[Quantity]]*Fact_Sales[[#This Row],[ActualCost]]) -> 9190.68 | I189: =EOMONTH(Fact_Sales[[#This Row],[Date]],-1)+1 -> 45352 | J189: =IFERROR(Fact_Sales[[#This Row],[Quantity]]*Fact_Sales[[#This Row],[ActualCost]],0) -> 10157.02
A190: 2024-03-06 | B190: CUST-008 | C190: PRD-002 | D190: 30189.6 | E190: 56 | F190: 0.1 | G190: {=IFERROR(--SUBSTITUTE(INDEX(Product_Costing!$I$2:$I$201,MATCH(1,(Product_Costing!$B$2:$B$201=Fact_Sales[[#This Row],[ProductID]])*(Product_Costing!$C$2:$C$201=DATE(YEAR(Fact_Sales[[#This Row],[Date]]),MONTH(Fact_Sales[[#This Row],[Date]]),1)),0))&""," USD",""),"")} -> 267.29 | H190: =IF(Fact_Sales[[#This Row],[Revenue]]="","",IFERROR(--SUBSTITUTE(Fact_Sales[[#This Row],[Revenue]]&""," USD",""),Fact_Sales[[#This Row],[Revenue]])-Fact_Sales[[#This Row],[Quantity]]*Fact_Sales[[#This Row],[ActualCost]]) -> 15221.36 | I190: =EOMONTH(Fact_Sales[[#This Row],[Date]],-1)+1 -> 45352 | J190: =IFERROR(Fact_Sales[[#This Row],[Quantity]]*Fact_Sales[[#This Row],[ActualCost]],0) -> 14968.24
A191: 2024-03-24 | B191: CUST-014 | C191: PRD-002 | D191: 25757 | E191: 43 | F191: 0 | G191: {=IFERROR(--SUBSTITUTE(INDEX(Product_Costing!$I$2:$I$201,MATCH(1,(Product_Costing!$B$2:$B$201=Fact_Sales[[#This Row],[ProductID]])*(Product_Costing!$C$2:$C$201=DATE(YEAR(Fact_Sales[[#This Row],[Date]]),MONTH(Fact_Sales[[#This Row],[Date]]),1)),0))&""," USD",""),"")} -> 267.29 | H191: =IF(Fact_Sales[[#This Row],[Revenue]]="","",IFERROR(--SUBSTITUTE(Fact_Sales[[#This Row],[Revenue]]&""," USD",""),Fact_Sales[[#This Row],[Revenue]])-Fact_Sales[[#This Row],[Quantity]]*Fact_Sales[[#This Row],[ActualCost]]) -> 14263.53 | I191: =EOMONTH(Fact_Sales[[#This Row],[Date]],-1)+1 -> 45352 | J191: =IFERROR(Fact_Sales[[#This Row],[Quantity]]*Fact_Sales[[#This Row],[ActualCost]],0) -> 11493.47
A192: 2024-03-09 | B192: CUST-012 | C192: PRD-002 | D192: 61457.4 | E192: 114 | F192: 0.1 | G192: {=IFERROR(--SUBSTITUTE(INDEX(Product_Costing!$I$2:$I$201,MATCH(1,(Product_Costing!$B$2:$B$201=Fact_Sales[[#This Row],[ProductID]])*(Product_Costing!$C$2:$C$201=DATE(YEAR(Fact_Sales[[#This Row],[Date]]),MONTH(Fact_Sales[[#This Row],[Date]]),1)),0))&""," USD",""),"")} -> 267.29 | H192: =IF(Fact_Sales[[#This Row],[Revenue]]="","",IFERROR(--SUBSTITUTE(Fact_Sales[[#This Row],[Revenue]]&""," USD",""),Fact_Sales[[#This Row],[Revenue]])-Fact_Sales[[#This Row],[Quantity]]*Fact_Sales[[#This Row],[ActualCost]]) -> 30986.34 | I192: =EOMONTH(Fact_Sales[[#This Row],[Date]],-1)+1 -> 45352 | J192: =IFERROR(Fact_Sales[[#This Row],[Quantity]]*Fact_Sales[[#This Row],[ActualCost]],0) -> 30471.06
A193: 2024-03-22 | B193: CUST-013 | C193: PRD-003 | E193: 39 | F193: 0.1 | G193: {=IFERROR(--SUBSTITUTE(INDEX(Product_Costing!$I$2:$I$201,MATCH(1,(Product_Costing!$B$2:$B$201=Fact_Sales[[#This Row],[ProductID]])*(Product_Costing!$C$2:$C$201=DATE(YEAR(Fact_Sales[[#This Row],[Date]]),MONTH(Fact_Sales[[#This Row],[Date]]),1)),0))&""," USD",""),"")} -> 568 | H193: =IF(Fact_Sales[[#This Row],[Revenue]]="","",IFERROR(--SUBSTITUTE(Fact_Sales[[#This Row],[Revenue]]&""," USD",""),Fact_Sales[[#This Row],[Revenue]])-Fact_Sales[[#This Row],[Quantity]]*Fact_Sales[[#This Row],[ActualCost]]) | I193: =EOMONTH(Fact_Sales[[#This Row],[Date]],-1)+1 -> 45352 | J193: =IFERROR(Fact_Sales[[#This Row],[Quantity]]*Fact_Sales[[#This Row],[ActualCost]],0) -> 22152
A194: 2024-03-15 | B194: CUST-013 | C194: PRD-003 | D194: 176664 | E194: 136 | F194: 0 | G194: {=IFERROR(--SUBSTITUTE(INDEX(Product_Costing!$I$2:$I$201,MATCH(1,(Product_Costing!$B$2:$B$201=Fact_Sales[[#This Row],[ProductID]])*(Product_Costing!$C$2:$C$201=DATE(YEAR(Fact_Sales[[#This Row],[Date]]),MONTH(Fact_Sales[[#This Row],[Date]]),1)),0))&""," USD",""),"")} -> 568 | H194: =IF(Fact_Sales[[#This Row],[Revenue]]="","",IFERROR(--SUBSTITUTE(Fact_Sales[[#This Row],[Revenue]]&""," USD",""),Fact_Sales[[#This Row],[Revenue]])-Fact_Sales[[#This Row],[Quantity]]*Fact_Sales[[#This Row],[ActualCost]]) -> 99416 | I194: =EOMONTH(Fact_Sales[[#This Row],[Date]],-1)+1 -> 45352 | J194: =IFERROR(Fact_Sales[[#This Row],[Quantity]]*Fact_Sales[[#This Row],[ActualCost]],0) -> 77248
A195: 2024-03-23 | B195: CUST-014 | C195: PRD-003 | D195: 14289 | E195: 11 | F195: 0 | G195: {=IFERROR(--SUBSTITUTE(INDEX(Product_Costing!$I$2:$I$201,MATCH(1,(Product_Costing!$B$2:$B$201=Fact_Sales[[#This Row],[ProductID]])*(Product_Costing!$C$2:$C$201=DATE(YEAR(Fact_Sales[[#This Row],[Date]]),MONTH(Fact_Sales[[#This Row],[Date]]),1)),0))&""," USD",""),"")} -> 568 | H195: =IF(Fact_Sales[[#This Row],[Revenue]]="","",IFERROR(--SUBSTITUTE(Fact_Sales[[#This Row],[Revenue]]&""," USD",""),Fact_Sales[[#This Row],[Revenue]])-Fact_Sales[[#This Row],[Quantity]]*Fact_Sales[[#This Row],[ActualCost]]) -> 8041 | I195: =EOMONTH(Fact_Sales[[#This Row],[Date]],-1)+1 -> 45352 | J195: =IFERROR(Fact_Sales[[#This Row],[Quantity]]*Fact_Sales[[#This Row],[ActualCost]],0) -> 6248
A196: 2024-03-14 | B196: CUST-001 | C196: PRD-003 | D196: -258501 | E196: 199 | F196: 0 | G196: {=IFERROR(--SUBSTITUTE(INDEX(Product_Costing!$I$2:$I$201,MATCH(1,(Product_Costing!$B$2:$B$201=Fact_Sales[[#This Row],[ProductID]])*(Product_Costing!$C$2:$C$201=DATE(YEAR(Fact_Sales[[#This Row],[Date]]),MONTH(Fact_Sales[[#This Row],[Date]]),1)),0))&""," USD",""),"")} -> 568 | H196: =IF(Fact_Sales[[#This Row],[Revenue]]="","",IFERROR(--SUBSTITUTE(Fact_Sales[[#This Row],[Revenue]]&""," USD",""),Fact_Sales[[#This Row],[Revenue]])-Fact_Sales[[#This Row],[Quantity]]*Fact_Sales[[#This Row],[ActualCost]]) -> -371533 | I196: =EOMONTH(Fact_Sales[[#This Row],[Date]],-1)+1 -> 45352 | J196: =IFERROR(Fact_Sales[[#This Row],[Quantity]]*Fact_Sales[[#This Row],[ActualCost]],0) -> 113032
A197: 2024-03-12 | B197: CUST-013 | C197: PRD-003 | D197: 177963 | E197: 137 | F197: 0 | G197: {=IFERROR(--SUBSTITUTE(INDEX(Product_Costing!$I$2:$I$201,MATCH(1,(Product_Costing!$B$2:$B$201=Fact_Sales[[#This Row],[ProductID]])*(Product_Costing!$C$2:$C$201=DATE(YEAR(Fact_Sales[[#This Row],[Date]]),MONTH(Fact_Sales[[#This Row],[Date]]),1)),0))&""," USD",""),"")} -> 568 | H197: =IF(Fact_Sales[[#This Row],[Revenue]]="","",IFERROR(--SUBSTITUTE(Fact_Sales[[#This Row],[Revenue]]&""," USD",""),Fact_Sales[[#This Row],[Revenue]])-Fact_Sales[[#This Row],[Quantity]]*Fact_Sales[[#This Row],[ActualCost]]) -> 100147 | I197: =EOMONTH(Fact_Sales[[#This Row],[Date]],-1)+1 -> 45352 | J197: =IFERROR(Fact_Sales[[#This Row],[Quantity]]*Fact_Sales[[#This Row],[ActualCost]],0) -> 77816
A198: 2024-03-18 | B198: CUST-008 | C198: PRD-003 | D198: 82811.25 | E198: 75 | F198: 0.15 | G198: {=IFERROR(--SUBSTITUTE(INDEX(Product_Costing!$I$2:$I$201,MATCH(1,(Product_Costing!$B$2:$B$201=Fact_Sales[[#This Row],[ProductID]])*(Product_Costing!$C$2:$C$201=DATE(YEAR(Fact_Sales[[#This Row],[Date]]),MONTH(Fact_Sales[[#This Row],[Date]]),1)),0))&""," USD",""),"")} -> 568 | H198: =IF(Fact_Sales[[#This Row],[Revenue]]="","",IFERROR(--SUBSTITUTE(Fact_Sales[[#This Row],[Revenue]]&""," USD",""),Fact_Sales[[#This Row],[Revenue]])-Fact_Sales[[#This Row],[Quantity]]*Fact_Sales[[#This Row],[ActualCost]]) -> 40211.25 | I198: =EOMONTH(Fact_Sales[[#This Row],[Date]],-1)+1 -> 45352 | J198: =IFERROR(Fact_Sales[[#This Row],[Quantity]]*Fact_Sales[[#This Row],[ActualCost]],0) -> 42600
A199: 2024-03-17 | B199: CUST-014 | C199: PRD-003 | D199: 215634 | E199: 166 | F199: 0 | G199: {=IFERROR(--SUBSTITUTE(INDEX(Product_Costing!$I$2:$I$201,MATCH(1,(Product_Costing!$B$2:$B$201=Fact_Sales[[#This Row],[ProductID]])*(Product_Costing!$C$2:$C$201=DATE(YEAR(Fact_Sales[[#This Row],[Date]]),MONTH(Fact_Sales[[#This Row],[Date]]),1)),0))&""," USD",""),"")} -> 568 | H199: =IF(Fact_Sales[[#This Row],[Revenue]]="","",IFERROR(--SUBSTITUTE(Fact_Sales[[#This Row],[Revenue]]&""," USD",""),Fact_Sales[[#This Row],[Revenue]])-Fact_Sales[[#This Row],[Quantity]]*Fact_Sales[[#This Row],[ActualCost]]) -> 121346 | I199: =EOMONTH(Fact_Sales[[#This Row],[Date]],-1)+1 -> 45352 | J199: =IFERROR(Fact_Sales[[#This Row],[Quantity]]*Fact_Sales[[#This Row],[ActualCost]],0) -> 94288
A200: 2024-03-20 | B200: CUST-010 | C200: PRD-004 | D200: 110142 | E200: 58 | F200: 0 | G200: {=IFERROR(--SUBSTITUTE(INDEX(Product_Costing!$I$2:$I$201,MATCH(1,(Product_Costing!$B$2:$B$201=Fact_Sales[[#This Row],[ProductID]])*(Product_Costing!$C$2:$C$201=DATE(YEAR(Fact_Sales[[#This Row],[Date]]),MONTH(Fact_Sales[[#This Row],[Date]]),1)),0))&""," USD",""),"")} -> 786.32 | H200: =IF(Fact_Sales[[#This Row],[Revenue]]="","",IFERROR(--SUBSTITUTE(Fact_Sales[[#This Row],[Revenue]]&""," USD",""),Fact_Sales[[#This Row],[Revenue]])-Fact_Sales[[#This Row],[Quantity]]*Fact_Sales[[#This Row],[ActualCost]]) -> 64535.44 | I200: =EOMONTH(Fact_Sales[[#This Row],[Date]],-1)+1 -> 45352 | J200: =IFERROR(Fact_Sales[[#This Row],[Quantity]]*Fact_Sales[[#This Row],[ActualCost]],0) -> 45606.56
A201: 2024-03-06 | B201: CUST-004 | C201: PRD-004 | D201: 176796.9 | E201: 98 | F201: 0.05 | G201: {=IFERROR(--SUBSTITUTE(INDEX(Product_Costing!$I$2:$I$201,MATCH(1,(Product_Costing!$B$2:$B$201=Fact_Sales[[#This Row],[ProductID]])*(Product_Costing!$C$2:$C$201=DATE(YEAR(Fact_Sales[[#This Row],[Date]]),MONTH(Fact_Sales[[#This Row],[Date]]),1)),0))&""," USD",""),"")} -> 786.32 | H201: =IF(Fact_Sales[[#This Row],[Revenue]]="","",IFERROR(--SUBSTITUTE(Fact_Sales[[#This Row],[Revenue]]&""," USD",""),Fact_Sales[[#This Row],[Revenue]])-Fact_Sales[[#This Row],[Quantity]]*Fact_Sales[[#This Row],[ActualCost]]) -> 99737.54 | I201: =EOMONTH(Fact_Sales[[#This Row],[Date]],-1)+1 -> 45352 | J201: =IFERROR(Fact_Sales[[#This Row],[Quantity]]*Fact_Sales[[#This Row],[ActualCost]],0) -> 77059.36
A202: 2024-03-06 | B202: CUST-007 | C202: PRD-004 | D202: 234146.7 | E202: 137 | F202: 0.1 | G202: {=IFERROR(--SUBSTITUTE(INDEX(Product_Costing!$I$2:$I$201,MATCH(1,(Product_Costing!$B$2:$B$201=Fact_Sales[[#This Row],[ProductID]])*(Product_Costing!$C$2:$C$201=DATE(YEAR(Fact_Sales[[#This Row],[Date]]),MONTH(Fact_Sales[[#This Row],[Date]]),1)),0))&""," USD",""),"")} -> 786.32 | H202: =IF(Fact_Sales[[#This Row],[Revenue]]="","",IFERROR(--SUBSTITUTE(Fact_Sales[[#This Row],[Revenue]]&""," USD",""),Fact_Sales[[#This Row],[Revenue]])-Fact_Sales[[#This Row],[Quantity]]*Fact_Sales[[#This Row],[ActualCost]]) -> 126420.86 | I202: =EOMONTH(Fact_Sales[[#This Row],[Date]],-1)+1 -> 45352 | J202: =IFERROR(Fact_Sales[[#This Row],[Quantity]]*Fact_Sales[[#This Row],[ActualCost]],0) -> 107725.84
A203: 2024-03-21 | B203: CUST-013 | C203: PRD-004 | E203: 142 | F203: 0.05 | G203: {=IFERROR(--SUBSTITUTE(INDEX(Product_Costing!$I$2:$I$201,MATCH(1,(Product_Costing!$B$2:$B$201=Fact_Sales[[#This Row],[ProductID]])*(Product_Costing!$C$2:$C$201=DATE(YEAR(Fact_Sales[[#This Row],[Date]]),MONTH(Fact_Sales[[#This Row],[Date]]),1)),0))&""," USD",""),"")} -> 786.32 | H203: =IF(Fact_Sales[[#This Row],[Revenue]]="","",IFERROR(--SUBSTITUTE(Fact_Sales[[#This Row],[Revenue]]&""," USD",""),Fact_Sales[[#This Row],[Revenue]])-Fact_Sales[[#This Row],[Quantity]]*Fact_Sales[[#This Row],[ActualCost]]) | I203: =EOMONTH(Fact_Sales[[#This Row],[Date]],-1)+1 -> 45352 | J203: =IFERROR(Fact_Sales[[#This Row],[Quantity]]*Fact_Sales[[#This Row],[ActualCost]],0) -> 111657.44
A204: 2024-03-13 | B204: CUST-011 | C204: PRD-004 | D204: 117832.95 | E204: 73 | F204: 0.15 | G204: {=IFERROR(--SUBSTITUTE(INDEX(Product_Costing!$I$2:$I$201,MATCH(1,(Product_Costing!$B$2:$B$201=Fact_Sales[[#This Row],[ProductID]])*(Product_Costing!$C$2:$C$201=DATE(YEAR(Fact_Sales[[#This Row],[Date]]),MONTH(Fact_Sales[[#This Row],[Date]]),1)),0))&""," USD",""),"")} -> 786.32 | H204: =IF(Fact_Sales[[#This Row],[Revenue]]="","",IFERROR(--SUBSTITUTE(Fact_Sales[[#This Row],[Revenue]]&""," USD",""),Fact_Sales[[#This Row],[Revenue]])-Fact_Sales[[#This Row],[Quantity]]*Fact_Sales[[#This Row],[ActualCost]]) -> 60431.59 | I204: =EOMONTH(Fact_Sales[[#This Row],[Date]],-1)+1 -> 45352 | J204: =IFERROR(Fact_Sales[[#This Row],[Quantity]]*Fact_Sales[[#This Row],[ActualCost]],0) -> 57401.36
A205: 2024-03-20 | B205: CUST-001 | C205: PRD-004 | E205: 57 | F205: 0 | G205: {=IFERROR(--SUBSTITUTE(INDEX(Product_Costing!$I$2:$I$201,MATCH(1,(Product_Costing!$B$2:$B$201=Fact_Sales[[#This Row],[ProductID]])*(Product_Costing!$C$2:$C$201=DATE(YEAR(Fact_Sales[[#This Row],[Date]]),MONTH(Fact_Sales[[#This Row],[Date]]),1)),0))&""," USD",""),"")} -> 786.32 | H205: =IF(Fact_Sales[[#This Row],[Revenue]]="","",IFERROR(--SUBSTITUTE(Fact_Sales[[#This Row],[Revenue]]&""," USD",""),Fact_Sales[[#This Row],[Revenue]])-Fact_Sales[[#This Row],[Quantity]]*Fact_Sales[[#This Row],[ActualCost]]) | I205: =EOMONTH(Fact_Sales[[#This Row],[Date]],-1)+1 -> 45352 | J205: =IFERROR(Fact_Sales[[#This Row],[Quantity]]*Fact_Sales[[#This Row],[ActualCost]],0) -> 44820.24
A206: 2024-03-20 | B206: CUST-010 | C206: PRD-004 | D206: 89253 | E206: 47 | F206: 0 | G206: {=IFERROR(--SUBSTITUTE(INDEX(Product_Costing!$I$2:$I$201,MATCH(1,(Product_Costing!$B$2:$B$201=Fact_Sales[[#This Row],[ProductID]])*(Product_Costing!$C$2:$C$201=DATE(YEAR(Fact_Sales[[#This Row],[Date]]),MONTH(Fact_Sales[[#This Row],[Date]]),1)),0))&""," USD",""),"")} -> 786.32 | H206: =IF(Fact_Sales[[#This Row],[Revenue]]="","",IFERROR(--SUBSTITUTE(Fact_Sales[[#This Row],[Revenue]]&""," USD",""),Fact_Sales[[#This Row],[Revenue]])-Fact_Sales[[#This Row],[Quantity]]*Fact_Sales[[#This Row],[ActualCost]]) -> 52295.96 | I206: =EOMONTH(Fact_Sales[[#This Row],[Date]],-1)+1 -> 45352 | J206: =IFERROR(Fact_Sales[[#This Row],[Quantity]]*Fact_Sales[[#This Row],[ActualCost]],0) -> 36957.04
A207: 2024-03-23 | B207: CUST-012 | C207: PRD-005 | D207: 105833.7 | E207: 157 | F207: 0.1 | G207: {=IFERROR(--SUBSTITUTE(INDEX(Product_Costing!$I$2:$I$201,MATCH(1,(Product_Costing!$B$2:$B$201=Fact_Sales[[#This Row],[ProductID]])*(Product_Costing!$C$2:$C$201=DATE(YEAR(Fact_Sales[[#This Row],[Date]]),MONTH(Fact_Sales[[#This Row],[Date]]),1)),0))&""," USD",""),"")} -> 286.64 | H207: =IF(Fact_Sales[[#This Row],[Revenue]]="","",IFERROR(--SUBSTITUTE(Fact_Sales[[#This Row],[Revenue]]&""," USD",""),Fact_Sales[[#This Row],[Revenue]])-Fact_Sales[[#This Row],[Quantity]]*Fact_Sales[[#This Row],[ActualCost]]) -> 60831.22 | I207: =EOMONTH(Fact_Sales[[#This Row],[Date]],-1)+1 -> 45352 | J207: =IFERROR(Fact_Sales[[#This Row],[Quantity]]*Fact_Sales[[#This Row],[ActualCost]],0) -> 45002.48
A208: 2024-03-23 | B208: CUST-012 | C208: PRD-005 | D208: 66735.9 | E208: 99 | F208: 0.1 | G208: {=IFERROR(--SUBSTITUTE(INDEX(Product_Costing!$I$2:$I$201,MATCH(1,(Product_Costing!$B$2:$B$201=Fact_Sales[[#This Row],[ProductID]])*(Product_Costing!$C$2:$C$201=DATE(YEAR(Fact_Sales[[#This Row],[Date]]),MONTH(Fact_Sales[[#This Row],[Date]]),1)),0))&""," USD",""),"")} -> 286.64 | H208: =IF(Fact_Sales[[#This Row],[Revenue]]="","",IFERROR(--SUBSTITUTE(Fact_Sales[[#This Row],[Revenue]]&""," USD",""),Fact_Sales[[#This Row],[Revenue]])-Fact_Sales[[#This Row],[Quantity]]*Fact_Sales[[#This Row],[ActualCost]]) -> 38358.54 | I208: =EOMONTH(Fact_Sales[[#This Row],[Date]],-1)+1 -> 45352 | J208: =IFERROR(Fact_Sales[[#This Row],[Quantity]]*Fact_Sales[[#This Row],[ActualCost]],0) -> 28377.36
A209: 2024-03-05 | B209: CUST-002 | C209: PRD-005 | D209: 10785.6 | E209: 16 | F209: 0.1 | G209: {=IFERROR(--SUBSTITUTE(INDEX(Product_Costing!$I$2:$I$201,MATCH(1,(Product_Costing!$B$2:$B$201=Fact_Sales[[#This Row],[ProductID]])*(Product_Costing!$C$2:$C$201=DATE(YEAR(Fact_Sales[[#This Row],[Date]]),MONTH(Fact_Sales[[#This Row],[Date]]),1)),0))&""," USD",""),"")} -> 286.64 | H209: =IF(Fact_Sales[[#This Row],[Revenue]]="","",IFERROR(--SUBSTITUTE(Fact_Sales[[#This Row],[Revenue]]&""," USD",""),Fact_Sales[[#This Row],[Revenue]])-Fact_Sales[[#This Row],[Quantity]]*Fact_Sales[[#This Row],[ActualCost]]) -> 6199.36 | I209: =EOMONTH(Fact_Sales[[#This Row],[Date]],-1)+1 -> 45352 | J209: =IFERROR(Fact_Sales[[#This Row],[Quantity]]*Fact_Sales[[#This Row],[ActualCost]],0) -> 4586.24
A210: 2024-03-27 | B210: CUST-009 | C210: PRD-005 | D210: 99317.4 | E210: 156 | F210: 0.15 | G210: {=IFERROR(--SUBSTITUTE(INDEX(Product_Costing!$I$2:$I$201,MATCH(1,(Product_Costing!$B$2:$B$201=Fact_Sales[[#This Row],[ProductID]])*(Product_Costing!$C$2:$C$201=DATE(YEAR(Fact_Sales[[#This Row],[Date]]),MONTH(Fact_Sales[[#This Row],[Date]]),1)),0))&""," USD",""),"")} -> 286.64 | H210: =IF(Fact_Sales[[#This Row],[Revenue]]="","",IFERROR(--SUBSTITUTE(Fact_Sales[[#This Row],[Revenue]]&""," USD",""),Fact_Sales[[#This Row],[Revenue]])-Fact_Sales[[#This Row],[Quantity]]*Fact_Sales[[#This Row],[ActualCost]]) -> 54601.56 | I210: =EOMONTH(Fact_Sales[[#This Row],[Date]],-1)+1 -> 45352 | J210: =IFERROR(Fact_Sales[[#This Row],[Quantity]]*Fact_Sales[[#This Row],[ActualCost]],0) -> 44715.84
A211: 2024-03-16 | B211: CUST-014 | C211: PRD-006 | D211: 44363 | E211: 37 | F211: 0 | G211: {=IFERROR(--SUBSTITUTE(INDEX(Product_Costing!$I$2:$I$201,MATCH(1,(Product_Costing!$B$2:$B$201=Fact_Sales[[#This Row],[ProductID]])*(Product_Costing!$C$2:$C$201=DATE(YEAR(Fact_Sales[[#This Row],[Date]]),MONTH(Fact_Sales[[#This Row],[Date]]),1)),0))&""," USD",""),"")} -> 507.69 | H211: =IF(Fact_Sales[[#This Row],[Revenue]]="","",IFERROR(--SUBSTITUTE(Fact_Sales[[#This Row],[Revenue]]&""," USD",""),Fact_Sales[[#This Row],[Revenue]])-Fact_Sales[[#This Row],[Quantity]]*Fact_Sales[[#This Row],[ActualCost]]) -> 25578.47 | I211: =EOMONTH(Fact_Sales[[#This Row],[Date]],-1)+1 -> 45352 | J211: =IFERROR(Fact_Sales[[#This Row],[Quantity]]*Fact_Sales[[#This Row],[ActualCost]],0) -> 18784.53
A212: 2024-03-04 | B212: CUST-003 | C212: PRD-006 | D212: 51557 | E212: 43 | F212: 0 | G212: {=IFERROR(--SUBSTITUTE(INDEX(Product_Costing!$I$2:$I$201,MATCH(1,(Product_Costing!$B$2:$B$201=Fact_Sales[[#This Row],[ProductID]])*(Product_Costing!$C$2:$C$201=DATE(YEAR(Fact_Sales[[#This Row],[Date]]),MONTH(Fact_Sales[[#This Row],[Date]]),1)),0))&""," USD",""),"")} -> 507.69 | H212: =IF(Fact_Sales[[#This Row],[Revenue]]="","",IFERROR(--SUBSTITUTE(Fact_Sales[[#This Row],[Revenue]]&""," USD",""),Fact_Sales[[#This Row],[Revenue]])-Fact_Sales[[#This Row],[Quantity]]*Fact_Sales[[#This Row],[ActualCost]]) -> 29726.33 | I212: =EOMONTH(Fact_Sales[[#This Row],[Date]],-1)+1 -> 45352 | J212: =IFERROR(Fact_Sales[[#This Row],[Quantity]]*Fact_Sales[[#This Row],[ActualCost]],0) -> 21830.67
A213: 2024-03-15 | B213: CUST-008 | C213: PRD-006 | D213: 117502 | E213: 98 | F213: 0 | G213: {=IFERROR(--SUBSTITUTE(INDEX(Product_Costing!$I$2:$I$201,MATCH(1,(Product_Costing!$B$2:$B$201=Fact_Sales[[#This Row],[ProductID]])*(Product_Costing!$C$2:$C$201=DATE(YEAR(Fact_Sales[[#This Row],[Date]]),MONTH(Fact_Sales[[#This Row],[Date]]),1)),0))&""," USD",""),"")} -> 507.69 | H213: =IF(Fact_Sales[[#This Row],[Revenue]]="","",IFERROR(--SUBSTITUTE(Fact_Sales[[#This Row],[Revenue]]&""," USD",""),Fact_Sales[[#This Row],[Revenue]])-Fact_Sales[[#This Row],[Quantity]]*Fact_Sales[[#This Row],[ActualCost]]) -> 67748.38 | I213: =EOMONTH(Fact_Sales[[#This Row],[Date]],-1)+1 -> 45352 | J213: =IFERROR(Fact_Sales[[#This Row],[Quantity]]*Fact_Sales[[#This Row],[ActualCost]],0) -> 49753.62
A214: 2024-03-12 | B214: CUST-004 | C214: PRD-006 | D214: 179850 | E214: 150 | F214: 0 | G214: {=IFERROR(--SUBSTITUTE(INDEX(Product_Costing!$I$2:$I$201,MATCH(1,(Product_Costing!$B$2:$B$201=Fact_Sales[[#This Row],[ProductID]])*(Product_Costing!$C$2:$C$201=DATE(YEAR(Fact_Sales[[#This Row],[Date]]),MONTH(Fact_Sales[[#This Row],[Date]]),1)),0))&""," USD",""),"")} -> 507.69 | H214: =IF(Fact_Sales[[#This Row],[Revenue]]="","",IFERROR(--SUBSTITUTE(Fact_Sales[[#This Row],[Revenue]]&""," USD",""),Fact_Sales[[#This Row],[Revenue]])-Fact_Sales[[#This Row],[Quantity]]*Fact_Sales[[#This Row],[ActualCost]]) -> 103696.5 | I214: =EOMONTH(Fact_Sales[[#This Row],[Date]],-1)+1 -> 45352 | J214: =IFERROR(Fact_Sales[[#This Row],[Quantity]]*Fact_Sales[[#This Row],[ActualCost]],0) -> 76153.5
A215: 2024-03-28 | B215: CUST-014 | C215: PRD-006 | D215: 53535.35 | E215: 47 | F215: 0.05 | G215: {=IFERROR(--SUBSTITUTE(INDEX(Product_Costing!$I$2:$I$201,MATCH(1,(Product_Costing!$B$2:$B$201=Fact_Sales[[#This Row],[ProductID]])*(Product_Costing!$C$2:$C$201=DATE(YEAR(Fact_Sales[[#This Row],[Date]]),MONTH(Fact_Sales[[#This Row],[Date]]),1)),0))&""," USD",""),"")} -> 507.69 | H215: =IF(Fact_Sales[[#This Row],[Revenue]]="","",IFERROR(--SUBSTITUTE(Fact_Sales[[#This Row],[Revenue]]&""," USD",""),Fact_Sales[[#This Row],[Revenue]])-Fact_Sales[[#This Row],[Quantity]]*Fact_Sales[[#This Row],[ActualCost]]) -> 29673.92 | I215: =EOMONTH(Fact_Sales[[#This Row],[Date]],-1)+1 -> 45352 | J215: =IFERROR(Fact_Sales[[#This Row],[Quantity]]*Fact_Sales[[#This Row],[ActualCost]],0) -> 23861.43
A216: 2024-03-13 | B216: CUST-003 | C216: PRD-006 | D216: 93881.7 | E216: 87 | F216: 0.1 | G216: {=IFERROR(--SUBSTITUTE(INDEX(Product_Costing!$I$2:$I$201,MATCH(1,(Product_Costing!$B$2:$B$201=Fact_Sales[[#This Row],[ProductID]])*(Product_Costing!$C$2:$C$201=DATE(YEAR(Fact_Sales[[#This Row],[Date]]),MONTH(Fact_Sales[[#This Row],[Date]]),1)),0))&""," USD",""),"")} -> 507.69 | H216: =IF(Fact_Sales[[#This Row],[Revenue]]="","",IFERROR(--SUBSTITUTE(Fact_Sales[[#This Row],[Revenue]]&""," USD",""),Fact_Sales[[#This Row],[Revenue]])-Fact_Sales[[#This Row],[Quantity]]*Fact_Sales[[#This Row],[ActualCost]]) -> 49712.67 | I216: =EOMONTH(Fact_Sales[[#This Row],[Date]],-1)+1 -> 45352 | J216: =IFERROR(Fact_Sales[[#This Row],[Quantity]]*Fact_Sales[[#This Row],[ActualCost]],0) -> 44169.03
A217: 2024-03-14 | B217: CUST-011 | C217: PRD-006 | D217: 146757.6 | E217: 144 | F217: 0.15 | G217: {=IFERROR(--SUBSTITUTE(INDEX(Product_Costing!$I$2:$I$201,MATCH(1,(Product_Costing!$B$2:$B$201=Fact_Sales[[#This Row],[ProductID]])*(Product_Costing!$C$2:$C$201=DATE(YEAR(Fact_Sales[[#This Row],[Date]]),MONTH(Fact_Sales[[#This Row],[Date]]),1)),0))&""," USD",""),"")} -> 507.69 | H217: =IF(Fact_Sales[[#This Row],[Revenue]]="","",IFERROR(--SUBSTITUTE(Fact_Sales[[#This Row],[Revenue]]&""," USD",""),Fact_Sales[[#This Row],[Revenue]])-Fact_Sales[[#This Row],[Quantity]]*Fact_Sales[[#This Row],[ActualCost]]) -> 73650.24 | I217: =EOMONTH(Fact_Sales[[#This Row],[Date]],-1)+1 -> 45352 | J217: =IFERROR(Fact_Sales[[#This Row],[Quantity]]*Fact_Sales[[#This Row],[ActualCost]],0) -> 73107.36
... A222: 2024-03-17 | B222: CUST-007 | C222: PRD-007 | D222: 14823 | E222: 27 | F222: 0 | G222: {=IFERROR(--SUBSTITUTE(INDEX(Product_Costing!$I$2:$I$201,MATCH(1,(Product_Costing!$B$2:$B$201=Fact_Sales[[#This Row],[ProductID]])*(Product_Costing!$C$2:$C$201=DATE(YEAR(Fact_Sales[[#This Row],[Date]]),MONTH(Fact_Sales[[#This Row],[Date]]),1)),0))&""," USD",""),"")} -> 225.01 | H222: =IF(Fact_Sales[[#This Row],[Revenue]]="","",IFERROR(--SUBSTITUTE(Fact_Sales[[#This Row],[Revenue]]&""," USD",""),Fact_Sales[[#This Row],[Revenue]])-Fact_Sales[[#This Row],[Quantity]]*Fact_Sales[[#This Row],[ActualCost]]) -> 8747.73 | I222: =EOMONTH(Fact_Sales[[#This Row],[Date]],-1)+1 -> 45352 | J222: =IFERROR(Fact_Sales[[#This Row],[Quantity]]*Fact_Sales[[#This Row],[ActualCost]],0) -> 6075.27
A223: 2024-03-20 | B223: CUST-005 | C223: PRD-008 | E223: 160 | F223: 0 | G223: {=IFERROR(--SUBSTITUTE(INDEX(Product_Costing!$I$2:$I$201,MATCH(1,(Product_Costing!$B$2:$B$201=Fact_Sales[[#This Row],[ProductID]])*(Product_Costing!$C$2:$C$201=DATE(YEAR(Fact_Sales[[#This Row],[Date]]),MONTH(Fact_Sales[[#This Row],[Date]]),1)),0))&""," USD",""),"")} -> 338.53 | H223: =IF(Fact_Sales[[#This Row],[Revenue]]="","",IFERROR(--SUBSTITUTE(Fact_Sales[[#This Row],[Revenue]]&""," USD",""),Fact_Sales[[#This Row],[Revenue]])-Fact_Sales[[#This Row],[Quantity]]*Fact_Sales[[#This Row],[ActualCost]]) | I223: =EOMONTH(Fact_Sales[[#This Row],[Date]],-1)+1 -> 45352 | J223: =IFERROR(Fact_Sales[[#This Row],[Quantity]]*Fact_Sales[[#This Row],[ActualCost]],0) -> 54164.8
A224: 2024-03-27 | B224: CUST-005 | C224: PRD-008 | D224: 78781.4 | E224: 116 | F224: 0.15 | G224: {=IFERROR(--SUBSTITUTE(INDEX(Product_Costing!$I$2:$I$201,MATCH(1,(Product_Costing!$B$2:$B$201=Fact_Sales[[#This Row],[ProductID]])*(Product_Costing!$C$2:$C$201=DATE(YEAR(Fact_Sales[[#This Row],[Date]]),MONTH(Fact_Sales[[#This Row],[Date]]),1)),0))&""," USD",""),"")} -> 338.53 | H224: =IF(Fact_Sales[[#This Row],[Revenue]]="","",IFERROR(--SUBSTITUTE(Fact_Sales[[#This Row],[Revenue]]&""," USD",""),Fact_Sales[[#This Row],[Revenue]])-Fact_Sales[[#This Row],[Quantity]]*Fact_Sales[[#This Row],[ActualCost]]) -> 39511.92 | I224: =EOMONTH(Fact_Sales[[#This Row],[Date]],-1)+1 -> 45352 | J224: =IFERROR(Fact_Sales[[#This Row],[Quantity]]*Fact_Sales[[#This Row],[ActualCost]],0) -> 39269.48
A225: 2024-03-22 | B225: CUST-003 | C225: PRD-008 | D225: 64719 | E225: 90 | F225: 0.1 | G225: {=IFERROR(--SUBSTITUTE(INDEX(Product_Costing!$I$2:$I$201,MATCH(1,(Product_Costing!$B$2:$B$201=Fact_Sales[[#This Row],[ProductID]])*(Product_Costing!$C$2:$C$201=DATE(YEAR(Fact_Sales[[#This Row],[Date]]),MONTH(Fact_Sales[[#This Row],[Date]]),1)),0))&""," USD",""),"")} -> 338.53 | H225: =IF(Fact_Sales[[#This Row],[Revenue]]="","",IFERROR(--SUBSTITUTE(Fact_Sales[[#This Row],[Revenue]]&""," USD",""),Fact_Sales[[#This Row],[Revenue]])-Fact_Sales[[#This Row],[Quantity]]*Fact_Sales[[#This Row],[ActualCost]]) -> 34251.3 | I225: =EOMONTH(Fact_Sales[[#This Row],[Date]],-1)+1 -> 45352 | J225: =IFERROR(Fact_Sales[[#This Row],[Quantity]]*Fact_Sales[[#This Row],[ActualCost]],0) -> 30467.7
A226: 2024-03-18 | B226: CUST-005 | C226: PRD-008 | D226: 50337 | E226: 63 | F226: 0 | G226: {=IFERROR(--SUBSTITUTE(INDEX(Product_Costing!$I$2:$I$201,MATCH(1,(Product_Costing!$B$2:$B$201=Fact_Sales[[#This Row],[ProductID]])*(Product_Costing!$C$2:$C$201=DATE(YEAR(Fact_Sales[[#This Row],[Date]]),MONTH(Fact_Sales[[#This Row],[Date]]),1)),0))&""," USD",""),"")} -> 338.53 | H226: =IF(Fact_Sales[[#This Row],[Revenue]]="","",IFERROR(--SUBSTITUTE(Fact_Sales[[#This Row],[Revenue]]&""," USD",""),Fact_Sales[[#This Row],[Revenue]])-Fact_Sales[[#This Row],[Quantity]]*Fact_Sales[[#This Row],[ActualCost]]) -> 29009.61 | I226: =EOMONTH(Fact_Sales[[#This Row],[Date]],-1)+1 -> 45352 | J226: =IFERROR(Fact_Sales[[#This Row],[Quantity]]*Fact_Sales[[#This Row],[ActualCost]],0) -> 21327.39
A227: 2024-03-12 | B227: CUST-012 | C227: PRD-008 | D227: 108664 | E227: 160 | F227: 0.15 | G227: {=IFERROR(--SUBSTITUTE(INDEX(Product_Costing!$I$2:$I$201,MATCH(1,(Product_Costing!$B$2:$B$201=Fact_Sales[[#This Row],[ProductID]])*(Product_Costing!$C$2:$C$201=DATE(YEAR(Fact_Sales[[#This Row],[Date]]),MONTH(Fact_Sales[[#This Row],[Date]]),1)),0))&""," USD",""),"")} -> 338.53 | H227: =IF(Fact_Sales[[#This Row],[Revenue]]="","",IFERROR(--SUBSTITUTE(Fact_Sales[[#This Row],[Revenue]]&""," USD",""),Fact_Sales[[#This Row],[Revenue]])-Fact_Sales[[#This Row],[Quantity]]*Fact_Sales[[#This Row],[ActualCost]]) -> 54499.2 | I227: =EOMONTH(Fact_Sales[[#This Row],[Date]],-1)+1 -> 45352 | J227: =IFERROR(Fact_Sales[[#This Row],[Quantity]]*Fact_Sales[[#This Row],[ActualCost]],0) -> 54164.8
A228: 2024-03-18 | B228: CUST-009 | C228: PRD-009 | D228: 149234 | E228: 166 | F228: 0 | G228: {=IFERROR(--SUBSTITUTE(INDEX(Product_Costing!$I$2:$I$201,MATCH(1,(Product_Costing!$B$2:$B$201=Fact_Sales[[#This Row],[ProductID]])*(Product_Costing!$C$2:$C$201=DATE(YEAR(Fact_Sales[[#This Row],[Date]]),MONTH(Fact_Sales[[#This Row],[Date]]),1)),0))&""," USD",""),"")} -> 384.07 | H228: =IF(Fact_Sales[[#This Row],[Revenue]]="","",IFERROR(--SUBSTITUTE(Fact_Sales[[#This Row],[Revenue]]&""," USD",""),Fact_Sales[[#This Row],[Revenue]])-Fact_Sales[[#This Row],[Quantity]]*Fact_Sales[[#This Row],[ActualCost]]) -> 85478.38 | I228: =EOMONTH(Fact_Sales[[#This Row],[Date]],-1)+1 -> 45352 | J228: =IFERROR(Fact_Sales[[#This Row],[Quantity]]*Fact_Sales[[#This Row],[ActualCost]],0) -> 63755.62
A229: 2024-03-17 | B229: CUST-005 | C229: PRD-009 | D229: 84506 | E229: 94 | F229: 0 | G229: {=IFERROR(--SUBSTITUTE(INDEX(Product_Costing!$I$2:$I$201,MATCH(1,(Product_Costing!$B$2:$B$201=Fact_Sales[[#This Row],[ProductID]])*(Product_Costing!$C$2:$C$201=DATE(YEAR(Fact_Sales[[#This Row],[Date]]),MONTH(Fact_Sales[[#This Row],[Date]]),1)),0))&""," USD",""),"")} -> 384.07 | H229: =IF(Fact_Sales[[#This Row],[Revenue]]="","",IFERROR(--SUBSTITUTE(Fact_Sales[[#This Row],[Revenue]]&""," USD",""),Fact_Sales[[#This Row],[Revenue]])-Fact_Sales[[#This Row],[Quantity]]*Fact_Sales[[#This Row],[ActualCost]]) -> 48403.42 | I229: =EOMONTH(Fact_Sales[[#This Row],[Date]],-1)+1 -> 45352 | J229: =IFERROR(Fact_Sales[[#This Row],[Quantity]]*Fact_Sales[[#This Row],[ActualCost]],0) -> 36102.58
A230: 2024-03-16 | B230: CUST-012 | C230: PRD-009 | D230: 134850 | E230: 150 | F230: 0 | G230: {=IFERROR(--SUBSTITUTE(INDEX(Product_Costing!$I$2:$I$201,MATCH(1,(Product_Costing!$B$2:$B$201=Fact_Sales[[#This Row],[ProductID]])*(Product_Costing!$C$2:$C$201=DATE(YEAR(Fact_Sales[[#This Row],[Date]]),MONTH(Fact_Sales[[#This Row],[Date]]),1)),0))&""," USD",""),"")} -> 384.07 | H230: =IF(Fact_Sales[[#This Row],[Revenue]]="","",IFERROR(--SUBSTITUTE(Fact_Sales[[#This Row],[Revenue]]&""," USD",""),Fact_Sales[[#This Row],[Revenue]])-Fact_Sales[[#This Row],[Quantity]]*Fact_Sales[[#This Row],[ActualCost]]) -> 77239.5 | I230: =EOMONTH(Fact_Sales[[#This Row],[Date]],-1)+1 -> 45352 | J230: =IFERROR(Fact_Sales[[#This Row],[Quantity]]*Fact_Sales[[#This Row],[ActualCost]],0) -> 57610.5
A231: 2024-03-04 | B231: CUST-012 | C231: PRD-009 | D231: 162719 | E231: 181 | F231: 0 | G231: {=IFERROR(--SUBSTITUTE(INDEX(Product_Costing!$I$2:$I$201,MATCH(1,(Product_Costing!$B$2:$B$201=Fact_Sales[[#This Row],[ProductID]])*(Product_Costing!$C$2:$C$201=DATE(YEAR(Fact_Sales[[#This Row],[Date]]),MONTH(Fact_Sales[[#This Row],[Date]]),1)),0))&""," USD",""),"")} -> 384.07 | H231: =IF(Fact_Sales[[#This Row],[Revenue]]="","",IFERROR(--SUBSTITUTE(Fact_Sales[[#This Row],[Revenue]]&""," USD",""),Fact_Sales[[#This Row],[Revenue]])-Fact_Sales[[#This Row],[Quantity]]*Fact_Sales[[#This Row],[ActualCost]]) -> 93202.33 | I231: =EOMONTH(Fact_Sales[[#This Row],[Date]],-1)+1 -> 45352 | J231: =IFERROR(Fact_Sales[[#This Row],[Quantity]]*Fact_Sales[[#This Row],[ActualCost]],0) -> 69516.67
A232: 2024-03-24 | B232: CUST-007 | C232: PRD-009 | D232: 68009.35 | E232: 89 | F232: 0.15 | G232: {=IFERROR(--SUBSTITUTE(INDEX(Product_Costing!$I$2:$I$201,MATCH(1,(Product_Costing!$B$2:$B$201=Fact_Sales[[#This Row],[ProductID]])*(Product_Costing!$C$2:$C$201=DATE(YEAR(Fact_Sales[[#This Row],[Date]]),MONTH(Fact_Sales[[#This Row],[Date]]),1)),0))&""," USD",""),"")} -> 384.07 | H232: =IF(Fact_Sales[[#This Row],[Revenue]]="","",IFERROR(--SUBSTITUTE(Fact_Sales[[#This Row],[Revenue]]&""," USD",""),Fact_Sales[[#This Row],[Revenue]])-Fact_Sales[[#This Row],[Quantity]]*Fact_Sales[[#This Row],[ActualCost]]) -> 33827.12 | I232: =EOMONTH(Fact_Sales[[#This Row],[Date]],-1)+1 -> 45352 | J232: =IFERROR(Fact_Sales[[#This Row],[Quantity]]*Fact_Sales[[#This Row],[ActualCost]],0) -> 34182.23
A233: 2024-03-02 | B233: CUST-015 | C233: PRD-010 | D233: 241079.4 | E233: 134 | F233: 0.1 | G233: {=IFERROR(--SUBSTITUTE(INDEX(Product_Costing!$I$2:$I$201,MATCH(1,(Product_Costing!$B$2:$B$201=Fact_Sales[[#This Row],[ProductID]])*(Product_Costing!$C$2:$C$201=DATE(YEAR(Fact_Sales[[#This Row],[Date]]),MONTH(Fact_Sales[[#This Row],[Date]]),1)),0))&""," USD",""),"")} -> 822.15 | H233: =IF(Fact_Sales[[#This Row],[Revenue]]="","",IFERROR(--SUBSTITUTE(Fact_Sales[[#This Row],[Revenue]]&""," USD",""),Fact_Sales[[#This Row],[Revenue]])-Fact_Sales[[#This Row],[Quantity]]*Fact_Sales[[#This Row],[ActualCost]]) -> 130911.3 | I233: =EOMONTH(Fact_Sales[[#This Row],[Date]],-1)+1 -> 45352 | J233: =IFERROR(Fact_Sales[[#This Row],[Quantity]]*Fact_Sales[[#This Row],[ActualCost]],0) -> 110168.1
A234: 2024-03-21 | B234: CUST-005 | C234: PRD-010 | D234: 78160.9 | E234: 46 | F234: 0.15 | G234: {=IFERROR(--SUBSTITUTE(INDEX(Product_Costing!$I$2:$I$201,MATCH(1,(Product_Costing!$B$2:$B$201=Fact_Sales[[#This Row],[ProductID]])*(Product_Costing!$C$2:$C$201=DATE(YEAR(Fact_Sales[[#This Row],[Date]]),MONTH(Fact_Sales[[#This Row],[Date]]),1)),0))&""," USD",""),"")} -> 822.15 | H234: =IF(Fact_Sales[[#This Row],[Revenue]]="","",IFERROR(--SUBSTITUTE(Fact_Sales[[#This Row],[Revenue]]&""," USD",""),Fact_Sales[[#This Row],[Revenue]])-Fact_Sales[[#This Row],[Quantity]]*Fact_Sales[[#This Row],[ActualCost]]) -> 40342 | I234: =EOMONTH(Fact_Sales[[#This Row],[Date]],-1)+1 -> 45352 | J234: =IFERROR(Fact_Sales[[#This Row],[Quantity]]*Fact_Sales[[#This Row],[ActualCost]],0) -> 37818.9
A235: 2024-03-09 | B235: CUST-014 | C235: PRD-010 | D235: 223088.4 | E235: 124 | F235: 0.1 | G235: {=IFERROR(--SUBSTITUTE(INDEX(Product_Costing!$I$2:$I$201,MATCH(1,(Product_Costing!$B$2:$B$201=Fact_Sales[[#This Row],[ProductID]])*(Product_Costing!$C$2:$C$201=DATE(YEAR(Fact_Sales[[#This Row],[Date]]),MONTH(Fact_Sales[[#This Row],[Date]]),1)),0))&""," USD",""),"")} -> 822.15 | H235: =IF(Fact_Sales[[#This Row],[Revenue]]="","",IFERROR(--SUBSTITUTE(Fact_Sales[[#This Row],[Revenue]]&""," USD",""),Fact_Sales[[#This Row],[Revenue]])-Fact_Sales[[#This Row],[Quantity]]*Fact_Sales[[#This Row],[ActualCost]]) -> 121141.8 | I235: =EOMONTH(Fact_Sales[[#This Row],[Date]],-1)+1 -> 45352 | J235: =IFERROR(Fact_Sales[[#This Row],[Quantity]]*Fact_Sales[[#This Row],[ActualCost]],0) -> 101946.6
...

Sheet Sales_Order
A1: SalesOrderID | B1: CustomerID | C1: OrderDate | D1: DeliveryDate | E1: Status | F1: TotalAmount
A2: SO-1000 | B2: CUST-011 | C2: 27-02-2024 | D2: 01-03-2024 | E2: delivered | F2: 157096
A3: SO-1001 | B3: CUST-002 | C3: 2024-07-13 | D3: July 19, 2024 | E3: Cancelled | F3: 149739.9
A4: SO-1002 | B4: CUST-012 | C4: 15-12-2024 | D4: 07/01/2025 | E4: Delivered | F4: 70321.35
A5: SO-1003 | B5: CUST-004 | C5: 17/01/2024 | D5: 14/02/2024 | E5: Pending | F5: 49630.65
A6: SO-1004 | B6: CUST-011 | C6: August 04, 2024 | D6: 2024-08-26 | E6: Pending
A7: SO-1005 | B7: CUST-011 | C7: June 23, 2024 | D7: June 29, 2024 | E7: Shipped | F7: 94114.45
A8: SO-1006 | B8: CUST-002 | C8: 2024-02-13 | D8: 10/03/2024 | E8: Delivered | F8: 172455.3
A9: SO-1007 | B9: CUST-003 | C9: 10/19/2024 | D9: 11/09/2024 | E9: Delivered | F9: 72284.35
A10: SO-1008 | B10: CUST-003 | C10: 27/07/2024 | D10: 14-08-2024 | E10: Cancelled
A11: SO-1009 | B11: CUST-010 | C11: 10/31/2024 | D11: 04/11/2024 | E11: Delivered | F11: 196626.15
A12: SO-1010 | B12: CUST-012 | C12: 10/10/2024 | D12: 10/17/2024 | E12: Shipped
A13: SO-1011 | B13: CUST-006 | C13: 25-10-2024 | D13: 14-11-2024 | E13: Shipped | F13: 97336
A14: SO-1012 | B14: CUST-007 | C14: 13/01/2024 | D14: 2024-01-21 | E14: Delivered | F14: 58853.7
A15: SO-1013 | B15: CUST-005 | C15: 04/01/2024 | D15: 22/04/2024 | E15: Cancelled
A16: SO-1014 | B16: CUST-002 | C16: 02-06-2024 | D16: June 21, 2024 | E16: Pending | F16: 175068.2
A17: SO-1015 | B17: CUST-005 | C17: 20-09-2024 | D17: 14/10/2024 | E17: Cancelled | F17: 180389.05
A18: SO-1016 | B18: CUST-009 | C18: 06-08-2024 | D18: 2024-09-04 | E18: Shipped | F18: 55394.75
A19: SO-1017 | B19: CUST-014 | C19: 02/08/2024 | D19: August 22, 2024 | E19: delivered | F19: 178081.9
A20: SO-1018 | B20: CUST-004 | C20: 04/12/2024 | D20: May 11, 2024 | E20: Pending | F20: 23219
A21: SO-1019 | B21: CUST-013 | C21: 24/03/2024 | E21: Pending | F21: 14364
A22: SO-1020 | B22: CUST-002 | C22: 10/16/2024 | D22: November 13, 2024 | E22: shipped | F22: 20910.45
A23: SO-1021 | B23: CUST-008 | C23: 2024-12-28 | D23: 04/01/2025 | E23: Delivered | F23: 179592.95
A24: SO-1022 | B24: CUST-013 | C24: 2024-05-03 | D24: 28/05/2024 | E24: Cancelled | F24: 85925.1
A25: SO-1023 | B25: CUST-005 | C25: April 26, 2024 | D25: 2024-05-10 | E25: DELIVERED | F25: 30362.3
A26: SO-1024 | B26: CUST-008 | C26: 02/28/2024 | D26: 28-03-2024 | E26: Cancelled | F26: 18207
A27: SO-1025 | B27: CUST-013 | C27: 2024-11-12 | D27: 11/22/2024 | E27: Delivered | F27: 375390.9
A28: SO-1026 | B28: CUST-003 | C28: June 06, 2024 | E28: Shipped | F28: 179391.25
A29: SO-1027 | B29: CUST-003 | C29: June 17, 2024 | D29: 03/07/2024 | E29: Delivered | F29: 225324.4
A30: SO-1028 | B30: CUST-014 | C30: February 28, 2024 | D30: 2024-03-16 | E30: Shipped | F30: 40745.6
A31: SO-1029 | B31: CUST-012 | C31: 2024-03-10 | D31: 04/09/2024 | E31: Cancelled | F31: 48546
A32: SO-1030 | B32: CUST-006 | C32: 19/06/2024 | D32: 07/09/2024 | E32: Delivered | F32: 69346.7
A33: SO-1031 | B33: CUST-008 | C33: 10/04/2024 | D33: 2024-10-08 | E33: Shipped | F33: 274186.15
A34: SO-1032 | B34: CUST-005 | C34: November 23, 2024 | D34: 2024-12-09 | E34: Shipped | F34: 74564.9
A35: SO-1033 | B35: CUST-006 | C35: 04/22/2024 | D35: May 15, 2024 | E35: Pending | F35: 25148.7
A36: SO-1034 | B36: CUST-003 | C36: 2024-05-11 | D36: June 09, 2024 | E36: Delivered | F36: 133756.7
A37: SO-1035 | B37: CUST-001 | C37: 20/01/2024 | D37: February 01, 2024 | E37: Delivered
A38: SO-1036 | B38: CUST-010 | C38: 2024-01-11 | D38: 15-01-2024 | E38: Delivered | F38: 58395.6
A39: SO-1037 | B39: CUST-005 | C39: 2024-01-27 | D39: 03/02/2024 | E39: cancelled | F39: 201707.95
A40: SO-1038 | B40: CUST-007 | C40: 20/02/2024 | D40: 2024-03-19 | E40: Delivered | F40: 29206.8
A41: SO-1039 | B41: CUST-011 | C41: 2024-08-30 | D41: 04-09-2024 | E41: Delivered | F41: 14808.6
A42: SO-1040 | B42: CUST-013 | C42: 08/04/2024 | D42: September 03, 2024 | E42: Shipped | F42: 153923
A43: SO-1041 | B43: CUST-005 | C43: October 20, 2024 | E43: Delivered | F43: 66328.7
A44: SO-1042 | B44: CUST-010 | C44: 2024-08-14 | D44: 08/30/2024 | E44: Cancelled
A45: SO-1043 | B45: CUST-011 | C45: 06/30/2024 | D45: 2024-07-05 | E45: Pending | F45: 60585.7
A46: SO-1044 | B46: CUST-006 | C46: 26-11-2024 | D46: 12/25/2024 | E46: Cancelled | F46: 34560
A47: SO-1045 | B47: CUST-011 | C47: 06/10/2024 | D47: 06/17/2024 | E47: Pending | F47: 214205.25
A48: SO-1046 | B48: CUST-014 | C48: 24/06/2024 | D48: July 19, 2024 | E48: Pending | F48: 7194
A49: SO-1047 | B49: CUST-013 | C49: 19-11-2024 | D49: 2024-12-12 | E49: Cancelled | F49: 98757
A50: SO-1048 | B50: CUST-011 | C50: 04-08-2024 | D50: 08/23/2024 | E50: Delivered | F50: 56550
A51: SO-1049 | B51: CUST-012 | C51: 12/08/2024 | D51: 16/08/2024 | E51: Cancelled | F51: 178097.75
A52: SO-1050 | B52: CUST-014 | C52: 2024-08-11 | D52: 16-08-2024 | E52: CANCELLED | F52: 26028.35
A53: SO-1051 | B53: CUST-014 | C53: 2024-03-12 | E53: Delivered | F53: 60135
A54: SO-1052 | B54: CUST-009 | C54: 05-10-2024 | D54: 10/24/2024 | E54: Shipped | F54: 231115.75
A55: SO-1053 | B55: CUST-014 | C55: 25/01/2024 | D55: 24/02/2024 | E55: Delivered | F55: 50629.8
A56: SO-1054 | B56: CUST-008 | C56: 06/28/2024 | D56: 07/15/2024 | E56: Shipped | F56: 23940.95
A57: SO-1055 | B57: CUST-014 | C57: 07/11/2024 | D57: 12/01/2024 | E57: Shipped | F57: 112275
A58: SO-1056 | B58: CUST-008 | C58: 03/29/2024 | D58: 23-04-2024 | E58: Delivered | F58: 176532.75
A59: SO-1057 | B59: CUST-008 | C59: 2024-12-14 | D59: 02-01-2025 | E59: Delivered | F59: 73191.6
A60: SO-1058 | B60: CUST-010 | C60: 2024-03-19 | D60: 2024-03-27 | E60: Cancelled | F60: 78189.3
A61: SO-1059 | B61: CUST-005 | C61: 07/15/2024 | D61: 14/08/2024 | E61: Delivered | F61: 43515.4
A62: SO-1060 | B62: CUST-005 | C62: 15/11/2024 | D62: December 09, 2024 | E62: Shipped | F62: 73996
A63: SO-1061 | B63: CUST-008 | C63: 2024-05-15 | D63: 07/06/2024 | E63: Pending | F63: 64117.75
A64: SO-1062 | B64: CUST-004 | C64: May 06, 2024 | D64: 17/05/2024 | E64: Cancelled | F64: 163216.4
A65: SO-1063 | B65: CUST-002 | C65: 07/30/2024 | D65: 08/12/2024 | E65: Shipped | F65: 117416.25
... A77: SO-1075 | B77: CUST-002 | C77: 02/19/2024 | D77: 2024-03-09 | E77: Pending | F77: 59331.5
A78: SO-1076 | B78: CUST-007 | C78: 13/07/2024 | E78: cancelled | F78: 52658.6
A79: SO-1077 | B79: CUST-012 | C79: 10/02/2024 | D79: 29/02/2024 | E79: Shipped | F79: 27525.65
A80: SO-1078 | B80: CUST-006 | C80: 02/24/2024 | E80: Shipped | F80: 113943
A81: SO-1079 | B81: CUST-010 | C81: 02/11/2024 | D81: 30-11-2024 | E81: Delivered | F81: 63741.4
A82: SO-1080 | B82: CUST-007 | C82: 19/06/2024 | D82: July 18, 2024 | E82: Shipped | F82: 147104.05
A83: SO-1081 | B83: CUST-003 | C83: 08/04/2024 | D83: 01-09-2024 | E83: Delivered | F83: 113588.95
A84: SO-1082 | B84: CUST-010 | C84: 12/19/2024 | D84: 07-01-2025 | E84: Delivered | F84: 69766.1
A85: SO-1083 | B85: CUST-001 | C85: June 24, 2024 | D85: 17-07-2024 | E85: Delivered | F85: 34531.2
A86: SO-1084 | B86: CUST-007 | C86: 15/01/2024 | D86: 02/10/2024 | E86: Delivered | F86: 205909.8
A87: SO-1085 | B87: CUST-007 | C87: 04-08-2024 | D87: 12-08-2024 | E87: Pending | F87: 166836.05
A88: SO-1086 | B88: CUST-009 | C88: 2024-09-18 | D88: 2024-09-24 | E88: PENDING | F88: 154107.6
A89: SO-1087 | B89: CUST-009 | C89: 13-12-2024 | D89: 11-01-2025 | E89: Shipped | F89: 39697
A90: SO-1088 | B90: CUST-005 | C90: 11/17/2024 | D90: 03/12/2024 | E90: Delivered | F90: 112842.3
A91: SO-1089 | B91: CUST-001 | C91: 2024-03-04 | D91: 03-04-2024 | E91: Delivered | F91: 36788.9
A92: SO-1090 | B92: CUST-007 | C92: 01-12-2024 | D92: December 06, 2024 | E92: Delivered
A93: SO-1091 | B93: CUST-003 | C93: 2024-09-01 | D93: 06-09-2024 | E93: Shipped | F93: 29533.8
A94: SO-1092 | B94: CUST-012 | C94: March 18, 2024 | D94: April 03, 2024 | E94: Cancelled | F94: 75919.75
A95: SO-1093 | B95: CUST-014 | C95: 10/18/2024 | D95: 03/11/2024 | E95: Delivered | F95: 117029
A96: SO-1094 | B96: CUST-011 | C96: 11/28/2024 | E96: Delivered | F96: 95152.4
A97: SO-1095 | B97: CUST-002 | C97: 07-01-2024 | D97: 2024-02-01 | E97: Shipped | F97: 27195.75
A98: SO-1096 | B98: CUST-010 | C98: 17-11-2024 | E98: Delivered
A99: SO-1097 | B99: CUST-011 | C99: 01/27/2024 | D99: February 04, 2024 | E99: Shipped | F99: 51461
A100: SO-1098 | B100: CUST-009 | C100: 2024-05-05 | D100: 05/12/2024 | E100: cancelled | F100: 796
A101: SO-1099 | B101: CUST-004 | C101: 02-08-2024 | D101: August 20, 2024 | E101: Delivered | F101: 26964
A102: SO-1100 | B102: CUST-007 | C102: 08-02-2024 | D102: February 29, 2024 | E102: DELIVERED | F102: 122637
A103: SO-1101 | B103: CUST-014 | C103: 30-03-2024 | D103: 02/04/2024 | E103: Delivered | F103: 80840.45
A104: SO-1102 | B104: CUST-007 | C104: 11-09-2024 | D104: 2024-09-14 | E104: Cancelled | F104: 112483.9
A105: SO-1103 | B105: CUST-005 | C105: 04/02/2024 | D105: 05-04-2024 | E105: Delivered | F105: 60006.1
A106: SO-1104 | B106: CUST-012 | C106: July 02, 2024 | D106: 23-07-2024 | E106: Delivered | F106: 20958.3
A107: SO-1105 | B107: CUST-001 | C107: 29-04-2024 | D107: 2024-05-21 | E107: Delivered | F107: 41216.7
A108: SO-1106 | B108: CUST-006 | C108: December 26, 2024 | D108: 2025-01-19 | E108: Cancelled | F108: 102811.4
A109: SO-1107 | B109: CUST-003 | C109: 06/18/2024 | D109: 2024-07-14 | E109: Delivered | F109: 35955
A110: SO-1108 | B110: CUST-007 | C110: 08/12/2024 | E110: Delivered | F110: 91583.35
A111: SO-1109 | B111: CUST-004 | C111: 2024-07-28 | D111: August 22, 2024 | E111: DELIVERED | F111: 66580.45
...

Sheet Sales_Order_Items
A1: SO_Item_ID | B1: SalesOrderID | C1: ProductID | D1: ProductName | E1: Quantity | F1: UnitPrice | G1: Discount
A2: SOI-5000 | B2: SO-1000 | C2: PRD-008 | D2: Range Hood 90cm | E2: 29 | F2: 799.0 | G2: 0
A3: SOI-5001 | B3: SO-1000 | C3: PRD-004 | E3: 70 | F3: 1899.0 | G3: 0
A4: SOI-5002 | B4: SO-1000 | C4: PRD-014 | D4: Coffee Maker Filter | E4: 5 | F4: 199.0 | G4: 0
A5: SOI-5003 | B5: SO-1001 | C5: PRD-012 | D5: toaster 4-slot | E5: 78 | F5: 319.0 | G5: 0
A6: SOI-5004 | B6: SO-1001 | C6: PRD-002 | D6: Stand Mixer 7L Professional | E6: 59 | F6: 539.1 | G6: 0.1
A7: SOI-5005 | B7: SO-1001 | C7: PRD-004 | D7: Electric Oven 90cm Built-in | E7: 49 | F7: 1899.0 | G7: 0
A8: SOI-5006 | B8: SO-1002 | C8: PRD-006 | D8: Cooktop 90cm Induction | E8: 69 | F8: 1019.15 | G8: 0.15
A9: SOI-5007 | B9: SO-1003 | C9: PRD-013 | D9: Blender Professional | E9: 35 | F9: 289.0 | G9: 0
A10: SOI-5008 | B10: SO-1003 | C10: PRD-007 | D10: Range Hood 60cm | E10: 73 | F10: 466.65 | G10: 0.15
A11: SOI-5009 | B11: SO-1003 | C11: PRD-011 | D11: Toaster 2-Slot | E11: 28 | F11: 194.65 | G11: 0.15
A12: SOI-5010 | B12: SO-1004 | C12: PRD-013 | D12: Blender Professional | E12: 49 | F12: 260.1 | G12: 0.1
A13: SOI-5011 | B13: SO-1005 | C13: PRD-014 | D13: Coffee Maker Filter | E13: 21 | F13: 189.05 | G13: 0.05
A14: SOI-5012 | B14: SO-1005 | C14: PRD-001 | D14: Stand Mixer 5L | E14: 34 | F14: 359.1 | G14: 0.1
A15: SOI-5013 | B15: SO-1005 | C15: PRD-006 | D15: Cooktop 90cm Induction | E15: 65 | F15: 1199.0 | G15: 0
... A64: SOI-5062 | B64: SO-1020 | C64: PRD-012 | D64: Toaster 4-Slot | E64: 69 | F64: 303.05 | G64: 0.05
A65: SOI-5063 | B65: SO-1021 | C65: PRD-006 | E65: 67 | F65: 1019.15 | G65: 0.15
A66: SOI-5064 | B66: SO-1021 | C66: PRD-009 | D66: Dishwasher-60cm | E66: 79 | F66: 809.1 | G66: 0.1
A67: SOI-5065 | B67: SO-1021 | C67: PRD-016 | D67: Food Processor 3L | E67: 60 | F67: 160.55 USD | G67: 0.05
A68: SOI-5066 | B68: SO-1021 | C68: PRD-009 | D68: Dishwasher 60cm | E68: 42 | F68: 899.0 | G68: 0
A69: SOI-5067 | B69: SO-1022 | C69: PRD-016 | D69: Food Processor 3L | E69: 58 | F69: 169.0 | G69: 0
A70: SOI-5068 | B70: SO-1022 | C70: PRD-003 | D70: Electric_Oven_60cm | E70: 38 | F70: 1299.0 | G70: 0
A71: SOI-5069 | B71: SO-1022 | C71: PRD-013 | D71: BLENDER PROFESSIONAL | E71: 32 | F71: 289.0 | G71: 0
A72: SOI-5070 | B72: SO-1022 | C72: PRD-012 | D72: Toaster 4-Slot | E72: 61 | F72: 287.1 | G72: 0.1
A73: SOI-5071 | B73: SO-1023 | C73: PRD-010 | D73: Refrigerator French Door | E73: 2 | F73: 1699.15 | G73: 0.15
A74: SOI-5072 | B74: SO-1023 | C74: PRD-005 | D74: Cooktop 60cm Gas | E74: 36 | F74: 749.0 | G74: 0
A75: SOI-5073 | B75: SO-1024 | C75: PRD-013 | D75: Blender Professional | E75: 63 | F75: 289.0 | G75: 0
A76: SOI-5074 | B76: SO-1025 | C76: PRD-013 | D76: blender professional | E76: 58 | F76: 274.55 | G76: 0.05
A77: SOI-5075 | B77: SO-1025 | C77: PRD-010 | D77: Refrigerator-French-Door | E77: 76 | F77: 1899.05 | G77: 0.05
... A102: SOI-5100 | B102: SO-1032 | C102: PRD-015 | D102: Coffee Maker Espresso | E102: 39 | F102: 549.0 | G102: 0
A103: SOI-5101 | B103: SO-1032 | C103: PRD-013 | E103: 62 | F103: 289.0 | G103: 0
A104: SOI-5102 | B104: SO-1032 | C104: PRD-008 | D104: Range Hood 90cm | E104: 49 | F104: 719.1 | G104: 0.1
A105: SOI-5103 | B105: SO-1033 | C105: PRD-009 | D105: Dishwasher 60cm | E105: 18 | F105: 764.15 | G105: 0.15
A106: SOI-5104 | B106: SO-1033 | C106: PRD-004 | D106: Electric Oven 90cm Built-in | E106: 6 | F106: 1899.0 | G106: 0
A107: SOI-5105 | B107: SO-1034 | C107: PRD-010 | D107: Refrigerator-French-Door | E107: 44 | F107: 1999.0 | G107: 0
A108: SOI-5106 | B108: SO-1034 | C108: PRD-015 | D108: Coffee Maker Espresso | E108: 10 | F108: 549.0 | G108: 0
A109: SOI-5107 | B109: SO-1034 | C109: PRD-008 | D109: Range Hood 90cm | E109: 51 | F109: 719.1 | G109: 0.1
A110: SOI-5108 | B110: SO-1034 | C110: PRD-012 | D110: Toaster 4-Slot | E110: 12 | F110: 303.05 | G110: 0.05
A111: SOI-5109 | B111: SO-1035 | C111: PRD-004 | D111: Electric Oven 90cm Built-in | E111: 13 | F111: 1899.0 | G111: 0
A112: SOI-5110 | B112: SO-1035 | C112: PRD-005 | D112: cooktop 60cm gas | E112: 50 | F112: 711.55 | G112: 0.05
A113: SOI-5111 | B113: SO-1035 | C113: PRD-012 | D113: Toaster 4-Slot | E113: 70 | F113: 303.05 | G113: 0.05
A114: SOI-5112 | B114: SO-1035 | C114: PRD-005 | D114: Cooktop 60cm Gas | E114: 54 | F114: 636.65 | G114: 0.15
A115: SOI-5113 | B115: SO-1036 | C115: PRD-008 | D115: Range Hood 90cm | E115: 17 | F115: 719.1 | G115: 0.1
... A153: SOI-5151 | B153: SO-1050 | C153: PRD-015 | D153: Coffee_Maker_Espresso | E153: 45 | F153: 549.0 | G153: 0
A154: SOI-5152 | B154: SO-1050 | C154: PRD-014 | E154: 7 | F154: 189.05 | G154: 0.05
A155: SOI-5153 | B155: SO-1051 | C155: PRD-015 | D155: Coffee Maker Espresso | E155: 79 | F155: 549.0 | G155: 0
A156: SOI-5154 | B156: SO-1051 | C156: PRD-003 | D156: electric oven 60cm | E156: 3 | F156: 1299.0 | G156: 0
A157: SOI-5155 | B157: SO-1051 | C157: PRD-007 | D157: Range Hood 60cm | E157: 20 | F157: 494.1 | G157: 0.1
A158: SOI-5156 | B158: SO-1051 | C158: PRD-014 | D158: Coffee Maker Filter | E158: 15 | F158: 199.0 | G158: 0
A159: SOI-5157 | B159: SO-1052 | C159: PRD-001 | D159: Stand Mixer 5L | E159: 50 | F159: 379.05 | G159: 0.05
A160: SOI-5158 | B160: SO-1052 | C160: PRD-002 | D160: STAND MIXER 7L PROFESSIONAL | E160: 50 | F160: 599.0 | G160: 0
A161: SOI-5159 | B161: SO-1052 | C161: PRD-009 | D161: dishwasher 60cm | E161: 3 | F161: 899.0 | G161: 0
A162: SOI-5160 | B162: SO-1052 | C162: PRD-003 | D162: Electric_Oven_60cm | E162: 45 | F162: 1299.0 | G162: 0
A163: SOI-5161 | B163: SO-1052 | C163: PRD-004 | E163: 75 | F163: 1614.15 | G163: 0.15
A164: SOI-5162 | B164: SO-1053 | C164: PRD-009 | D164: dishwasher 60cm | E164: 16 | F164: 899.0 | G164: 0
A165: SOI-5163 | B165: SO-1053 | C165: PRD-014 | D165: COFFEE MAKER FILTER | E165: 52 | F165: 169.15 | G165: 0.15
A166: SOI-5164 | B166: SO-1053 | C166: PRD-015 | D166: Coffee_Maker_Espresso | E166: 50 | F166: 549.0 | G166: 0
A167: SOI-5165 | B167: SO-1054 | C167: PRD-012 | D167: Toaster 4-Slot | E167: 79 | F167: 303.05 USD | G167: 0.05
A168: SOI-5166 | B168: SO-1055 | C168: PRD-002 | D168: Stand Mixer 7L Professional | E168: 17 | F168: 599.0 | G168: 0
A169: SOI-5167 | B169: SO-1055 | C169: PRD-008 | D169: Range Hood 90cm | E169: 47 | F169: 799.0 | G169: 0
A170: SOI-5168 | B170: SO-1055 | C170: PRD-013 | D170: Blender-Professional | E170: 73 | F170: 289.0 | G170: 0
A171: SOI-5169 | B171: SO-1055 | C171: PRD-005 | D171: Cooktop 60cm Gas | E171: 58 | F171: 749.0 | G171: 0
A172: SOI-5170 | B172: SO-1056 | C172: PRD-003 | D172: Electric Oven 60cm | E172: 41 | F172: 1104.15 | G172: 0.15
A173: SOI-5171 | B173: SO-1056 | C173: PRD-012 | D173: TOASTER 4-SLOT | E173: 9 | F173: 287.1 | G173: 0.1
A174: SOI-5172 | B174: SO-1056 | C174: PRD-010 | D174: Refrigerator French Door | E174: 39 | F174: 1999.0 | G174: 0
A175: SOI-5173 | B175: SO-1056 | C175: PRD-006 | D175: Cooktop 90cm Induction | E175: 47 | F175: 1079.1 | G175: 0.1
... A203: SOI-5201 | B203: SO-1062 | C203: PRD-009 | D203: dishwasher 60cm | E203: 37 | F203: 899.0 | G203: 0
A204: SOI-5202 | B204: SO-1063 | C204: PRD-004 | E204: 18 | F204: 1899.0 | G204: 0
A205: SOI-5203 | B205: SO-1063 | C205: PRD-006 | D205: Cooktop 90cm Induction | E205: 53 | F205: 1019.15 USD | G205: 0.15
A206: SOI-5204 | B206: SO-1063 | C206: PRD-016 | D206: Food Processor 3L | E206: 62 | F206: 143.65 | G206: 0.15
A207: SOI-5205 | B207: SO-1063 | C207: PRD-007 | D207: Range Hood 60cm | E207: 37 | F207: 549.0 USD | G207: 0
A208: SOI-5206 | B208: SO-1064 | C208: PRD-011 | D208: Toaster_2-Slot | E208: 37 | F208: 217.55 | G208: 0.05
A209: SOI-5207 | B209: SO-1065 | C209: PRD-001 | D209: Stand Mixer 5L | E209: 44 | F209: -399.0 | G209: 0
A210: SOI-5208 | B210: SO-1065 | C210: PRD-007 | D210: Range Hood 60cm | E210: 23 | F210: 494.1 | G210: 0.1
A211: SOI-5209 | B211: SO-1066 | C211: PRD-012 | D211: Toaster-4-Slot | E211: 31 | F211: 319.0 | G211: 0
A212: SOI-5210 | B212: SO-1066 | C212: PRD-004 | D212: Electric Oven 90cm Built-in | E212: 60 | F212: 1899.0 | G212: 0
A213: SOI-5211 | B213: SO-1066 | C213: PRD-006 | D213: Cooktop 90cm Induction | E213: 52 | F213: 1019.15 | G213: 0.15
A214: SOI-5212 | B214: SO-1067 | C214: PRD-015 | D214: Coffee-Maker-Espresso | E214: 68 | F214: 466.65 | G214: 0.15
A215: SOI-5213 | B215: SO-1068 | C215: PRD-016 | D215: Food Processor 3L | E215: 12 | F215: 152.1 | G215: 0.1
A216: SOI-5214 | B216: SO-1068 | C216: PRD-015 | D216: Coffee Maker Espresso | E216: 8 | F216: 521.55 | G216: 0.05
A217: SOI-5215 | B217: SO-1069 | C217: PRD-016 | D217: Food Processor 3L | E217: 5 | F217: 169.0 | G217: 0
A218: SOI-5216 | B218: SO-1070 | C218: PRD-005 | E218: 45 | F218: 749.0 | G218: 0
A219: SOI-5217 | B219: SO-1071 | C219: PRD-008 | E219: 32 | F219: 759.05 | G219: 0.05
A220: SOI-5218 | B220: SO-1071 | C220: PRD-012 | D220: Toaster-4-Slot | E220: 20 | F220: 319.0 | G220: 0
A221: SOI-5219 | B221: SO-1071 | C221: PRD-007 | D221: Range Hood 60cm | E221: 15 | F221: 549.0 | G221: 0
A222: SOI-5220 | B222: SO-1071 | C222: PRD-014 | D222: Coffee_Maker_Filter | E222: 79 | F222: 199.0 | G222: 0
A223: SOI-5221 | B223: SO-1072 | C223: PRD-008 | D223: Range-Hood-90cm | E223: 53 | F223: 799.0 | G223: 0
A224: SOI-5222 | B224: SO-1072 | C224: PRD-009 | D224: Dishwasher 60cm | E224: 8 | F224: 809.1 | G224: 0.1
A225: SOI-5223 | B225: SO-1072 | C225: PRD-006 | D225: Cooktop 90cm Induction | E225: 55 | F225: 1079.1 | G225: 0.1
A226: SOI-5224 | B226: SO-1072 | C226: PRD-016 | D226: food processor 3l | E226: 7 | F226: 169.0 | G226: 0
A227: SOI-5225 | B227: SO-1072 | C227: PRD-013 | D227: Blender Professional | E227: 68 | F227: 289.0 | G227: 0
A228: SOI-5226 | B228: SO-1073 | C228: PRD-007 | D228: Range-Hood-60cm | E228: 62 | F228: 549.0 | G228: 0
A229: SOI-5227 | B229: SO-1073 | C229: PRD-011 | D229: Toaster 2-Slot | E229: 39 | F229: 229.0 | G229: 0
A230: SOI-5228 | B230: SO-1073 | C230: PRD-007 | D230: Range Hood 60cm | E230: 25 | F230: 466.65 | G230: 0.15
A231: SOI-5229 | B231: SO-1073 | C231: PRD-004 | D231: ELECTRIC OVEN 90CM BUILT-IN | E231: 62 | F231: 1899.0 | G231: 0
A232: SOI-5230 | B232: SO-1073 | C232: PRD-007 | D232: Range Hood 60cm | E232: 51 | F232: 549.0 | G232: 0
A233: SOI-5231 | B233: SO-1074 | C233: PRD-011 | E233: 33 | F233: 217.55 | G233: 0.05
A234: SOI-5232 | B234: SO-1074 | C234: PRD-016 | D234: Food Processor 3L | E234: 59 | F234: 169.0 | G234: 0
A235: SOI-5233 | B235: SO-1074 | C235: PRD-012 | E235: 22 | F235: -319.0 | G235: 0
A236: SOI-5234 | B236: SO-1074 | C236: PRD-016 | D236: Food Processor 3L | E236: 24 | F236: -152.1 | G236: 0.1
...

Sheet GL_Transactions
A1: Column1 | B1: Column2 | C1: Column3 | D1: Column4 | E1: Column5 | F1: Column6 | G1: Column7 | H1: Column8 | I1: Column9
A2: TransactionID | B2: AccountID | C2: AccountName | D2: Amount | E2: Currency | F2: PostingDate | G2: ReferenceDocument | H2: Description | I2: =EOMONTH(GL_Transactions[[#This Row],[Column6]],-1)+1 -> #VALUE!
A3: GL-10000 | B3: ACC-4001 | C3: Utilities | D3: 66432.65 | E3: GBP | F3: January 26, 2024 | G3: REF-6493 | H3: Payroll posting | I3: =EOMONTH(GL_Transactions[[#This Row],[Column6]],-1)+1 -> 45292
A4: GL-10001 | B4: ACC-6001 | C4: Warranty Expense | D4: -28569.93 | E4: GBP | F4: 03/01/2024 | G4: REF-3255 | H4: Depreciation run | I4: =EOMONTH(GL_Transactions[[#This Row],[Column6]],-1)+1 -> 45352
A5: GL-10002 | B5: ACC-5001 | C5: Raw Material Purchases | D5: 32531.66 | E5: GBP | F5: January 10, 2024 | G5: REF-2407 | H5: Utility bill | I5: =EOMONTH(GL_Transactions[[#This Row],[Column6]],-1)+1 -> 45292
A6: GL-10003 | B6: ACC-3001 | C6: Labor Cost | D6: 68952.67 | E6: EUR | F6: 01/01/2024 | G6: REF-2596 | H6: Payroll posting | I6: =EOMONTH(GL_Transactions[[#This Row],[Column6]],-1)+1 -> 45292
A7: GL-10004 | B7: ACC-4003 | C7: Marketing | D7: -56929.51 | E7: EUR | F7: 2024-01-13 | G7: REF-2764 | H7: Freight charges | I7: =EOMONTH(GL_Transactions[[#This Row],[Column6]],-1)+1 -> 45292
A8: GL-10005 | B8: ACC-1001 | C8: Revenue | D8: 48247.77 | E8: EUR | F8: 01/15/2024 | H8: Intercompany transfer | I8: =EOMONTH(GL_Transactions[[#This Row],[Column6]],-1)+1 -> 45292
A9: GL-10006 | B9: ACC-4002 | C9: Depreciation | D9: 44004.35 | E9: EUR | F9: 2024-01-06 | G9: REF-7456 | H9: Payroll posting | I9: =EOMONTH(GL_Transactions[[#This Row],[Column6]],-1)+1 -> 45292
A10: GL-10007 | B10: ACC-4005 | C10: Admin Expenses | D10: -17262.68 | E10: EUR | F10: 2024-01-12 | G10: REF-2047 | H10: Depreciation run | I10: =EOMONTH(GL_Transactions[[#This Row],[Column6]],-1)+1 -> 45292
A11: GL-10008 | B11: ACC-4001 | C11: Utilities | D11: 17879.28 | E11: EUR | F11: 11/01/2024 | G11: REF-9154 | H11: Intercompany transfer | I11: =EOMONTH(GL_Transactions[[#This Row],[Column6]],-1)+1 -> 45597
A12: GL-10009 | B12: ACC-3001 | C12: Labor Cost | D12: 33286.23 | E12: USD | F12: 2024-01-18 | G12: REF-8169 | I12: =EOMONTH(GL_Transactions[[#This Row],[Column6]],-1)+1 -> 45292
A13: GL-10010 | B13: ACC-4004 | D13: 6838.53 | E13: GBP | F13: January 28, 2024 | G13: REF-1577 | H13: Intercompany transfer | I13: =EOMONTH(GL_Transactions[[#This Row],[Column6]],-1)+1 -> 45292
A14: GL-10011 | B14: ACC-4003 | C14: Marketing | D14: 75484.42 | E14: USD | F14: 01/20/2024 | H14: Payroll posting | I14: =EOMONTH(GL_Transactions[[#This Row],[Column6]],-1)+1 -> 45292
A15: GL-10012 | B15: ACC-3002 | C15: Overhead Cost | D15: 31617.32 | E15: EUR | F15: 2024-01-17 | G15: REF-4231 | H15: Freight charges | I15: =EOMONTH(GL_Transactions[[#This Row],[Column6]],-1)+1 -> 45292
A16: GL-10013 | B16: ACC-3001 | C16: Labor Cost | D16: 75162.27 | E16: USD | F16: 2024-01-18 | G16: REF-1172 | H16: Utility bill | I16: =EOMONTH(GL_Transactions[[#This Row],[Column6]],-1)+1 -> 45292
A17: GL-10014 | B17: ACC-1001 | C17: Revenue | D17: 56370.25 | E17: EUR | F17: 17/01/2024 | G17: REF-5391 | H17: Inventory write-off | I17: =EOMONTH(GL_Transactions[[#This Row],[Column6]],-1)+1 -> #VALUE!
A18: GL-10015 | B18: ACC-2001 | C18: Cost of Goods Sold | D18: 15998.48 | E18: EUR | F18: 03/01/2024 | H18: Freight charges | I18: =EOMONTH(GL_Transactions[[#This Row],[Column6]],-1)+1 -> 45352
A19: GL-10016 | B19: ACC-4004 | C19: Logistics | D19: 28701.52 | E19: EUR | F19: 01/09/2024 | G19: REF-6519 | H19: Inventory write-off | I19: =EOMONTH(GL_Transactions[[#This Row],[Column6]],-1)+1 -> 45292
A20: GL-10017 | B20: ACC-1001 | C20: Revenue | D20: 5710.63 | E20: USD | F20: 01/07/2024 | G20: REF-6876 | H20: Inventory write-off | I20: =EOMONTH(GL_Transactions[[#This Row],[Column6]],-1)+1 -> 45292
A21: GL-10018 | B21: ACC-4004 | C21: Logistics | D21: -43630.29 | E21: EUR | F21: 2024-01-28 | G21: REF-4201 | H21: Bonus provision | I21: =EOMONTH(GL_Transactions[[#This Row],[Column6]],-1)+1 -> 45292
A22: GL-10019 | B22: ACC-6001 | C22: Warranty Expense | D22: 53819.35 | E22: EUR | F22: January 12, 2024 | G22: REF-6192 | H22: Utility bill | I22: =EOMONTH(GL_Transactions[[#This Row],[Column6]],-1)+1 -> 45292
A23: GL-10020 | B23: ACC-4004 | C23: Logistics | D23: -40114.72 | E23: EUR | F23: 01/11/2024 | H23: Payroll posting | I23: =EOMONTH(GL_Transactions[[#This Row],[Column6]],-1)+1 -> 45292
A24: GL-10021 | B24: ACC-5001 | C24: Raw Material Purchases | D24: -32963.26 | E24: EUR | F24: 11/01/2024 | H24: Payroll posting | I24: =EOMONTH(GL_Transactions[[#This Row],[Column6]],-1)+1 -> 45597
A25: GL-10022 | B25: ACC-3002 | C25: Overhead Cost | D25: -66066.11 | E25: EUR | F25: 2024-01-07 | H25: Supplier invoice | I25: =EOMONTH(GL_Transactions[[#This Row],[Column6]],-1)+1 -> 45292
A26: GL-10023 | B26: ACC-4005 | C26: Admin Expenses | D26: 71843.89 | E26: EUR | F26: January 03, 2024 | G26: REF-2104 | H26: Payroll posting | I26: =EOMONTH(GL_Transactions[[#This Row],[Column6]],-1)+1 -> 45292
A27: GL-10024 | B27: ACC-6001 | C27: Warranty Expense | D27: 32137.65 | E27: USD | F27: 2024-01-26 | G27: REF-6504 | H27: Payroll posting | I27: =EOMONTH(GL_Transactions[[#This Row],[Column6]],-1)+1 -> 45292
A28: GL-10025 | B28: ACC-4002 | C28: Depreciation | D28: 31049.38 | E28: GBP | F28: 23/01/2024 | H28: Payroll posting | I28: =EOMONTH(GL_Transactions[[#This Row],[Column6]],-1)+1 -> #VALUE!
A29: GL-10026 | B29: ACC-4005 | C29: Admin Expenses | D29: 66262.24 | E29: EUR | F29: 20/01/2024 | G29: REF-9636 | H29: Supplier invoice | I29: =EOMONTH(GL_Transactions[[#This Row],[Column6]],-1)+1 -> #VALUE!
A30: GL-10027 | B30: ACC-3002 | C30: Overhead Cost | D30: 30138.36 | E30: USD | F30: 10/01/2024 | G30: REF-5359 | H30: Manual adjustment | I30: =EOMONTH(GL_Transactions[[#This Row],[Column6]],-1)+1 -> 45566
A31: GL-10028 | B31: ACC-4004 | C31: Logistics | D31: 58335.89 | E31: EUR | F31: 2024-01-04 | G31: REF-1807 | H31: Monthly accrual | I31: =EOMONTH(GL_Transactions[[#This Row],[Column6]],-1)+1 -> 45292
A32: GL-10029 | B32: ACC-4004 | C32: Logistics | D32: 27209.77 | E32: EUR | F32: 01/27/2024 | G32: REF-1196 | I32: =EOMONTH(GL_Transactions[[#This Row],[Column6]],-1)+1 -> 45292
A33: GL-10030 | B33: ACC-4005 | C33: Admin Expenses | D33: 76928.55 | E33: GBP | F33: 16/01/2024 | G33: REF-2300 | H33: Bonus provision | I33: =EOMONTH(GL_Transactions[[#This Row],[Column6]],-1)+1 -> #VALUE!
A34: GL-10031 | B34: ACC-4005 | C34: Admin Expenses | D34: 81178.91 | E34: USD | F34: 07-01-2024 | G34: REF-4592 | H34: Bonus provision | I34: =EOMONTH(GL_Transactions[[#This Row],[Column6]],-1)+1 -> 45474
A35: GL-10032 | B35: ACC-5001 | C35: Raw Material Purchases | D35: 35011.82 | E35: USD | F35: 07/01/2024 | G35: REF-3789 | H35: Freight charges | I35: =EOMONTH(GL_Transactions[[#This Row],[Column6]],-1)+1 -> 45474
A36: GL-10033 | B36: ACC-4002 | C36: Depreciation | D36: 543.82 | E36: EUR | F36: 2024-01-16 | I36: =EOMONTH(GL_Transactions[[#This Row],[Column6]],-1)+1 -> 45292
A37: GL-10034 | B37: ACC-4001 | C37: Utilities | D37: -1232.88 | E37: USD | F37: January 09, 2024 | G37: REF-7997 | H37: Supplier invoice | I37: =EOMONTH(GL_Transactions[[#This Row],[Column6]],-1)+1 -> 45292
A38: GL-10035 | B38: ACC-5001 | D38: 41635.61 | E38: USD | F38: 2024-01-14 | G38: REF-2881 | H38: Supplier invoice | I38: =EOMONTH(GL_Transactions[[#This Row],[Column6]],-1)+1 -> 45292
A39: GL-10036 | B39: ACC-4001 | C39: Utilities | D39: 41456.25 | E39: USD | F39: January 13, 2024 | G39: REF-6735 | H39: Intercompany transfer | I39: =EOMONTH(GL_Transactions[[#This Row],[Column6]],-1)+1 -> 45292
A40: GL-10037 | B40: ACC-5001 | C40: Raw Material Purchases | D40: 58215.2 | E40: EUR | F40: January 21, 2024 | G40: REF-9769 | H40: Intercompany transfer | I40: =EOMONTH(GL_Transactions[[#This Row],[Column6]],-1)+1 -> 45292
A41: GL-10038 | B41: ACC-5001 | C41: Raw Material Purchases | D41: -79313.65 | E41: EUR | F41: 2024-01-14 | G41: REF-8822 | H41: Intercompany transfer | I41: =EOMONTH(GL_Transactions[[#This Row],[Column6]],-1)+1 -> 45292
A42: GL-10039 | B42: ACC-6001 | C42: Warranty Expense | D42: 13835.02 | E42: GBP | F42: 01/08/2024 | G42: REF-2333 | H42: Freight charges | I42: =EOMONTH(GL_Transactions[[#This Row],[Column6]],-1)+1 -> 45292
A43: GL-10040 | B43: ACC-4004 | C43: Logistics | D43: 28563.31 | E43: GBP | F43: January 19, 2024 | G43: REF-1663 | H43: Monthly accrual | I43: =EOMONTH(GL_Transactions[[#This Row],[Column6]],-1)+1 -> 45292
A44: GL-10041 | B44: ACC-4002 | C44: Depreciation | D44: 50286.93 | E44: EUR | F44: January 10, 2024 | G44: REF-6969 | H44: Manual adjustment | I44: =EOMONTH(GL_Transactions[[#This Row],[Column6]],-1)+1 -> 45292
A45: GL-10042 | B45: ACC-2001 | C45: Cost of Goods Sold | D45: 48804.64 | E45: EUR | F45: 10/01/2024 | G45: REF-2689 | H45: Depreciation run | I45: =EOMONTH(GL_Transactions[[#This Row],[Column6]],-1)+1 -> 45566
A46: GL-10043 | B46: ACC-3002 | C46: Overhead Cost | D46: -79738.73 | E46: USD | F46: 25-01-2024 | G46: REF-7036 | H46: Bonus provision | I46: =EOMONTH(GL_Transactions[[#This Row],[Column6]],-1)+1 -> #VALUE!
A47: GL-10044 | B47: ACC-5001 | C47: Raw Material Purchases | D47: -57161.15 | E47: USD | F47: 01/19/2024 | G47: REF-7608 | H47: Utility bill | I47: =EOMONTH(GL_Transactions[[#This Row],[Column6]],-1)+1 -> 45292
A48: GL-10045 | B48: ACC-4004 | C48: Logistics | D48: 65050.15 | E48: USD | F48: 21/01/2024 | G48: REF-4118 | H48: Inventory write-off | I48: =EOMONTH(GL_Transactions[[#This Row],[Column6]],-1)+1 -> #VALUE!
A49: GL-10046 | B49: ACC-5001 | C49: Raw Material Purchases | D49: 79251.24 | E49: GBP | F49: 08/01/2024 | G49: REF-7304 | H49: Freight charges | I49: =EOMONTH(GL_Transactions[[#This Row],[Column6]],-1)+1 -> 45505
A50: GL-10047 | B50: ACC-5001 | C50: Raw Material Purchases | D50: 84642.42 | E50: EUR | F50: 2024-01-11 | G50: REF-5545 | H50: Monthly accrual | I50: =EOMONTH(GL_Transactions[[#This Row],[Column6]],-1)+1 -> 45292
A51: GL-10048 | B51: ACC-3001 | C51: Labor Cost | D51: 51250.82 USD | E51: EUR | F51: 20/01/2024 | G51: REF-4789 | H51: Payroll posting | I51: =EOMONTH(GL_Transactions[[#This Row],[Column6]],-1)+1 -> #VALUE!
A52: GL-10049 | B52: ACC-3001 | C52: Labor Cost | D52: 38410.0 USD | E52: EUR | F52: January 12, 2024 | G52: REF-5985 | H52: Manual adjustment | I52: =EOMONTH(GL_Transactions[[#This Row],[Column6]],-1)+1 -> 45292
A53: GL-10050 | B53: ACC-2001 | C53: Cost of Goods Sold | D53: 6219.62 | E53: EUR | F53: 11/01/2024 | G53: REF-3696 | H53: Manual adjustment | I53: =EOMONTH(GL_Transactions[[#This Row],[Column6]],-1)+1 -> 45597
A54: GL-10051 | B54: ACC-5001 | C54: Raw Material Purchases | D54: 66961.3 | E54: EUR | F54: 22/01/2024 | G54: REF-6395 | H54: Depreciation run | I54: =EOMONTH(GL_Transactions[[#This Row],[Column6]],-1)+1 -> #VALUE!
A55: GL-10052 | B55: ACC-1001 | C55: Revenue | D55: 31305.85 | E55: GBP | F55: January 11, 2024 | H55: Bonus provision | I55: =EOMONTH(GL_Transactions[[#This Row],[Column6]],-1)+1 -> 45292
A56: GL-10053 | B56: ACC-1001 | C56: Revenue | D56: 30007.46 | E56: EUR | F56: 28-01-2024 | H56: Inventory write-off | I56: =EOMONTH(GL_Transactions[[#This Row],[Column6]],-1)+1 -> #VALUE!
A57: GL-10054 | B57: ACC-4005 | C57: Admin Expenses | D57: -38516.75 | E57: EUR | F57: 27-01-2024 | G57: REF-8369 | H57: Utility bill | I57: =EOMONTH(GL_Transactions[[#This Row],[Column6]],-1)+1 -> #VALUE!
A58: GL-10055 | B58: ACC-2001 | C58: Cost of Goods Sold | D58: 24902.37 | E58: EUR | F58: 10/01/2024 | G58: REF-4149 | H58: Utility bill | I58: =EOMONTH(GL_Transactions[[#This Row],[Column6]],-1)+1 -> 45566
A59: GL-10056 | B59: ACC-3002 | C59: Overhead Cost | D59: 3317.16 | E59: GBP | F59: January 22, 2024 | G59: REF-3025 | H59: Payroll posting | I59: =EOMONTH(GL_Transactions[[#This Row],[Column6]],-1)+1 -> 45292
A60: GL-10057 | B60: ACC-4003 | C60: Marketing | D60: 36460.39 | E60: USD | F60: January 02, 2024 | G60: REF-6828 | H60: Depreciation run | I60: =EOMONTH(GL_Transactions[[#This Row],[Column6]],-1)+1 -> 45292
A61: GL-10058 | B61: ACC-4002 | C61: Depreciation | D61: -25056.6 | E61: USD | F61: 01/11/2024 | H61: Manual adjustment | I61: =EOMONTH(GL_Transactions[[#This Row],[Column6]],-1)+1 -> 45292
A62: GL-10059 | B62: ACC-4005 | C62: Admin Expenses | D62: -55508.35 | E62: GBP | F62: 01-01-2024 | G62: REF-4460 | H62: Utility bill | I62: =EOMONTH(GL_Transactions[[#This Row],[Column6]],-1)+1 -> 45292
A63: GL-10060 | B63: ACC-4002 | D63: 66763.78 | E63: GBP | F63: 2024-01-02 | G63: REF-2403 | H63: Bonus provision | I63: =EOMONTH(GL_Transactions[[#This Row],[Column6]],-1)+1 -> 45292
A64: GL-10061 | B64: ACC-4001 | D64: -49497.63 | E64: USD | F64: 01/13/2024 | G64: REF-2408 | H64: Manual adjustment | I64: =EOMONTH(GL_Transactions[[#This Row],[Column6]],-1)+1 -> 45292
A65: GL-10062 | B65: ACC-4003 | C65: Marketing | D65: 8048.6 | E65: EUR | F65: 01/01/2024 | G65: REF-6109 | I65: =EOMONTH(GL_Transactions[[#This Row],[Column6]],-1)+1 -> 45292
A66: GL-10063 | B66: ACC-6001 | D66: 47290.25 | E66: USD | F66: 01/05/2024 | G66: REF-7298 | H66: Intercompany transfer | I66: =EOMONTH(GL_Transactions[[#This Row],[Column6]],-1)+1 -> 45292
A67: GL-10064 | B67: ACC-4002 | C67: Depreciation | D67: 37434.51 | E67: GBP | F67: 24/01/2024 | G67: REF-4459 | H67: Inventory write-off | I67: =EOMONTH(GL_Transactions[[#This Row],[Column6]],-1)+1 -> #VALUE!
A68: GL-10065 | B68: ACC-3001 | C68: Labor Cost | D68: 74084.94 | E68: EUR | F68: 01/12/2024 | G68: REF-9584 | H68: Depreciation run | I68: =EOMONTH(GL_Transactions[[#This Row],[Column6]],-1)+1 -> 45292
A69: GL-10066 | B69: ACC-4001 | C69: Utilities | D69: 74114.54 | E69: EUR | F69: 09/01/2024 | G69: REF-7576 | I69: =EOMONTH(GL_Transactions[[#This Row],[Column6]],-1)+1 -> 45536
A70: GL-10067 | B70: ACC-1001 | C70: Revenue | D70: 62153.84 | E70: EUR | F70: 2024-01-12 | G70: REF-9908 | H70: Inventory write-off | I70: =EOMONTH(GL_Transactions[[#This Row],[Column6]],-1)+1 -> 45292
A71: GL-10068 | B71: ACC-3001 | C71: Labor Cost | D71: -71663.27 | E71: EUR | F71: 01/10/2024 | G71: REF-9224 | I71: =EOMONTH(GL_Transactions[[#This Row],[Column6]],-1)+1 -> 45292
A72: GL-10069 | B72: ACC-1001 | C72: Revenue | D72: -80978.5 | E72: USD | F72: 01/13/2024 | G72: REF-4765 | H72: Utility bill | I72: =EOMONTH(GL_Transactions[[#This Row],[Column6]],-1)+1 -> 45292
A73: GL-10070 | B73: ACC-5001 | C73: Raw Material Purchases | D73: 9675.17 | E73: EUR | F73: 2024-01-18 | G73: REF-7698 | H73: Payroll posting | I73: =EOMONTH(GL_Transactions[[#This Row],[Column6]],-1)+1 -> 45292
A74: GL-10071 | B74: ACC-3002 | C74: Overhead Cost | D74: 9938.88 | E74: USD | F74: 08/01/2024 | G74: REF-7466 | H74: Payroll posting | I74: =EOMONTH(GL_Transactions[[#This Row],[Column6]],-1)+1 -> 45505
A75: GL-10072 | B75: ACC-5001 | C75: Raw Material Purchases | D75: 30468.38 | E75: GBP | F75: January 26, 2024 | G75: REF-1981 | H75: Utility bill | I75: =EOMONTH(GL_Transactions[[#This Row],[Column6]],-1)+1 -> 45292
A76: GL-10073 | B76: ACC-4004 | D76: 10617.44 | E76: EUR | F76: 21/01/2024 | G76: REF-1603 | H76: Payroll posting | I76: =EOMONTH(GL_Transactions[[#This Row],[Column6]],-1)+1 -> #VALUE!
A77: GL-10074 | B77: ACC-2001 | C77: Cost of Goods Sold | D77: 22897.21 | E77: EUR | F77: 2024-01-15 | G77: REF-2716 | H77: Inventory write-off | I77: =EOMONTH(GL_Transactions[[#This Row],[Column6]],-1)+1 -> 45292
A78: GL-10075 | B78: ACC-4002 | C78: Depreciation | D78: 58144.81 | E78: USD | F78: 2024-01-20 | G78: REF-2414 | H78: Freight charges | I78: =EOMONTH(GL_Transactions[[#This Row],[Column6]],-1)+1 -> 45292
A79: GL-10076 | B79: ACC-2001 | C79: Cost of Goods Sold | D79: 71076.44 | E79: EUR | F79: 18-01-2024 | G79: REF-1342 | H79: Utility bill | I79: =EOMONTH(GL_Transactions[[#This Row],[Column6]],-1)+1 -> #VALUE!
A80: GL-10077 | B80: ACC-4004 | C80: Logistics | D80: 21331.83 | E80: EUR | F80: 11/01/2024 | G80: REF-1039 | H80: Bonus provision | I80: =EOMONTH(GL_Transactions[[#This Row],[Column6]],-1)+1 -> 45597
A81: GL-10078 | B81: ACC-6001 | D81: 10730.01 | E81: EUR | F81: 09-01-2024 | G81: REF-6772 | H81: Payroll posting | I81: =EOMONTH(GL_Transactions[[#This Row],[Column6]],-1)+1 -> 45536
A82: GL-10079 | B82: ACC-4002 | C82: Depreciation | D82: 33065.23 | E82: USD | F82: 2024-01-05 | G82: REF-3013 | H82: Manual adjustment | I82: =EOMONTH(GL_Transactions[[#This Row],[Column6]],-1)+1 -> 45292
A83: GL-10080 | B83: ACC-1001 | C83: Revenue | D83: 49141.54 | E83: EUR | F83: 09/01/2024 | H83: Inventory write-off | I83: =EOMONTH(GL_Transactions[[#This Row],[Column6]],-1)+1 -> 45536
A84: GL-10081 | B84: ACC-4005 | C84: Admin Expenses | D84: 54462.77 | E84: GBP | F84: 21/01/2024 | G84: REF-2176 | H84: Depreciation run | I84: =EOMONTH(GL_Transactions[[#This Row],[Column6]],-1)+1 -> #VALUE!
A85: GL-10082 | B85: ACC-1001 | C85: Revenue | D85: 58996.51 | E85: GBP | F85: 22-01-2024 | G85: REF-3481 | H85: Payroll posting | I85: =EOMONTH(GL_Transactions[[#This Row],[Column6]],-1)+1 -> #VALUE!
A86: GL-10083 | B86: ACC-3002 | C86: Overhead Cost | D86: 13568.01 | E86: USD | F86: 05/01/2024 | G86: REF-6500 | H86: Utility bill | I86: =EOMONTH(GL_Transactions[[#This Row],[Column6]],-1)+1 -> 45413
A87: GL-10084 | B87: ACC-5001 | C87: Raw Material Purchases | D87: 54120.22 | E87: USD | F87: 2024-01-25 | G87: REF-3474 | H87: Intercompany transfer | I87: =EOMONTH(GL_Transactions[[#This Row],[Column6]],-1)+1 -> 45292
A88: GL-10085 | B88: ACC-5001 | C88: Raw Material Purchases | D88: -16883.07 | E88: USD | F88: 07/01/2024 | G88: REF-7698 | H88: Freight charges | I88: =EOMONTH(GL_Transactions[[#This Row],[Column6]],-1)+1 -> 45474
A89: GL-10086 | B89: ACC-1001 | C89: Revenue | D89: 77380.2 | E89: USD | F89: 08-01-2024 | H89: Supplier invoice | I89: =EOMONTH(GL_Transactions[[#This Row],[Column6]],-1)+1 -> 45505
A90: GL-10087 | B90: ACC-3002 | D90: 74377.95 | E90: GBP | F90: 15-01-2024 | G90: REF-9749 | I90: =EOMONTH(GL_Transactions[[#This Row],[Column6]],-1)+1 -> #VALUE!
A91: GL-10088 | B91: ACC-4002 | C91: Depreciation | D91: -67718.81 | E91: EUR | F91: 01/17/2024 | G91: REF-3580 | H91: Payroll posting | I91: =EOMONTH(GL_Transactions[[#This Row],[Column6]],-1)+1 -> 45292
A92: GL-10089 | B92: ACC-2001 | C92: Cost of Goods Sold | D92: 74125.19 | E92: GBP | F92: 2024-01-17 | H92: Manual adjustment | I92: =EOMONTH(GL_Transactions[[#This Row],[Column6]],-1)+1 -> 45292
A93: GL-10090 | B93: ACC-6001 | C93: Warranty Expense | D93: 76050.95 | E93: EUR | F93: 2024-01-18 | H93: Inventory write-off | I93: =EOMONTH(GL_Transactions[[#This Row],[Column6]],-1)+1 -> 45292
A94: GL-10091 | B94: ACC-1001 | C94: Revenue | D94: 42759.13 | E94: USD | F94: 08-01-2024 | G94: REF-7723 | H94: Payroll posting | I94: =EOMONTH(GL_Transactions[[#This Row],[Column6]],-1)+1 -> 45505
A95: GL-10092 | B95: ACC-4001 | C95: Utilities | D95: 73408.64 | E95: GBP | F95: 01/18/2024 | G95: REF-3398 | H95: Inventory write-off | I95: =EOMONTH(GL_Transactions[[#This Row],[Column6]],-1)+1 -> 45292
A96: GL-10093 | B96: ACC-2001 | C96: Cost of Goods Sold | D96: 80163.62 | E96: EUR | F96: 2024-01-11 | H96: Bonus provision | I96: =EOMONTH(GL_Transactions[[#This Row],[Column6]],-1)+1 -> 45292
A97: GL-10094 | B97: ACC-5001 | C97: Raw Material Purchases | D97: -42447.44 | E97: EUR | F97: January 13, 2024 | G97: REF-8825 | H97: Payroll posting | I97: =EOMONTH(GL_Transactions[[#This Row],[Column6]],-1)+1 -> 45292
A98: GL-10095 | B98: ACC-4003 | C98: Marketing | D98: 45367.37 | E98: EUR | F98: 12/01/2024 | H98: Monthly accrual | I98: =EOMONTH(GL_Transactions[[#This Row],[Column6]],-1)+1 -> 45627
A99: GL-10096 | B99: ACC-3002 | C99: Overhead Cost | D99: 40303.24 | E99: GBP | F99: 02-01-2024 | G99: REF-1293 | H99: Monthly accrual | I99: =EOMONTH(GL_Transactions[[#This Row],[Column6]],-1)+1 -> 45323
A100: GL-10097 | B100: ACC-3001 | C100: Labor Cost | D100: -2711.04 | E100: USD | F100: 11-01-2024 | G100: REF-5661 | H100: Utility bill | I100: =EOMONTH(GL_Transactions[[#This Row],[Column6]],-1)+1 -> 45597
...

Sheet Inventory_Balance
A1: InventoryID | B1: MaterialID | C1: WarehouseID | D1: QuantityOnHand | E1: QuantityReserved | F1: QuantityAvailable | G1: LastUpdated
A2: INV-4000 | B2: MAT-001 | C2: WH-001 | D2: 1112 | E2: 12 | F2: 1100 | G2: 26-01-2024
A3: INV-4001 | B3: MAT-001 | C3: WH-001 | D3: 1343 | E3: 377 | F3: 966 | G3: February 25, 2024
A4: INV-4002 | B4: MAT-001 | C4: WH-001 | D4: 3656 | E4: 65 | G4: 26-03-2024
A5: INV-4003 | B5: MAT-001 | C5: WH-001 | D5: 4339 | E5: 1232 | G5: April 26, 2024
A6: INV-4004 | B6: MAT-001 | C6: WH-001 | D6: 3636 | E6: 451 | F6: 3185 | G6: 05/27/2024
A7: INV-4005 | B7: MAT-001 | C7: WH-001 | D7: 1507 | E7: 357 | F7: 1150 | G7: 27-06-2024
A8: INV-4006 | B8: MAT-001 | C8: WH-001 | D8: 1963 | E8: 344 | F8: 1619 | G8: 07/28/2024
A9: INV-4007 | B9: MAT-001 | C9: WH-001 | D9: 3140 | E9: 867 | F9: 2273 | G9: 08/27/2024
A10: INV-4008 | B10: MAT-001 | C10: WH-001 | D10: 3963 | E10: 1098 | F10: 2865 | G10: 09/28/2024
A11: INV-4009 | B11: MAT-001 | C11: WH-001 | D11: 4722 | E11: 600 | F11: 4122 | G11: October 27, 2024
A12: INV-4010 | B12: MAT-001 | C12: WH-001 | D12: 1775 | E12: 71 | G12: 2024-11-26
A13: INV-4011 | B13: MAT-001 | C13: WH-001 | D13: 853 | E13: 119 | F13: 734 | G13: 2024-12-28
A14: INV-4012 | B14: MAT-001 | C14: WH-002 | D14: 3914 | E14: 747 | F14: 3167 | G14: 27-01-2024
A15: INV-4013 | B15: MAT-001 | C15: WH-002 | D15: 2387 | E15: 699 | F15: 1688 | G15: February 26, 2024
A16: INV-4014 | B16: MAT-001 | C16: WH-002 | D16: 2205 | E16: 167 | F16: 2038 | G16: March 27, 2024
A17: INV-4015 | B17: MAT-001 | C17: WH-002 | D17: 1999 | E17: 332 | F17: 1667 | G17: 25-04-2024
A18: INV-4016 | B18: MAT-001 | C18: WH-002 | D18: 462 | E18: 80 | F18: 382 | G18: 25-05-2024
A19: INV-4017 | B19: MAT-001 | C19: WH-002 | D19: 4846 | E19: 644 | F19: 4202 | G19: 28/06/2024
A20: INV-4018 | B20: MAT-001 | C20: WH-002 | D20: 3958 | E20: 292 | F20: 3666 | G20: July 26, 2024
A21: INV-4019 | B21: MAT-001 | C21: WH-002 | D21: 4615 | E21: 538 | F21: 4077 | G21: August 28, 2024
A22: INV-4020 | B22: MAT-001 | C22: WH-002 | D22: 3471 | E22: 741 | F22: 2730 | G22: September 26, 2024
A23: INV-4021 | B23: MAT-001 | C23: WH-002 | D23: 4242 | E23: 186 | F23: 4056 | G23: 25-10-2024
A24: INV-4022 | B24: MAT-001 | C24: WH-002 | D24: 1510 | E24: 405 | F24: 1105 | G24: 25/11/2024
... A36: INV-4034 | B36: MAT-001 | C36: WH-003 | D36: 3788 | E36: 1059 | F36: 2729 | G36: 26-11-2024
A37: INV-4035 | B37: MAT-001 | C37: WH-003 | D37: 724 | E37: 86 | G37: December 26, 2024
A38: INV-4036 | B38: MAT-002 | C38: WH-001 | D38: 2004 | E38: 7 | G38: 25-01-2024
A39: INV-4037 | B39: MAT-002 | C39: WH-001 | D39: 752 | E39: 8 | F39: 744 | G39: February 25, 2024
A40: INV-4038 | B40: MAT-002 | C40: WH-001 | D40: 2149 | E40: 285 | F40: 1864 | G40: March 26, 2024
A41: INV-4039 | B41: MAT-002 | C41: WH-001 | D41: 1283 | E41: 370 | F41: 913 | G41: 28-04-2024
A42: INV-4040 | B42: MAT-002 | C42: WH-001 | D42: 4074 | E42: 833 | F42: 3241 | G42: 25/05/2024
A43: INV-4041 | B43: MAT-002 | C43: WH-001 | D43: 3102 | E43: 433 | F43: 2669 | G43: 06/25/2024
A44: INV-4042 | B44: MAT-002 | C44: WH-001 | D44: 696 | E44: 103 | F44: 593 | G44: 25-07-2024
A45: INV-4043 | B45: MAT-002 | C45: WH-001 | D45: 1769 | E45: 194 | F45: 1575 | G45: 26/08/2024
A46: INV-4044 | B46: MAT-002 | C46: WH-001 | D46: 1703 | E46: 142 | F46: 1561 | G46: 25/09/2024
A47: INV-4045 | B47: MAT-002 | C47: WH-001 | D47: 4708 | E47: 200 | G47: 10/25/2024
A48: INV-4046 | B48: MAT-002 | C48: WH-001 | D48: 2136 | E48: 170 | F48: 1966 | G48: 28-11-2024
A49: INV-4047 | B49: MAT-002 | C49: WH-001 | D49: 3485 | E49: 120 | F49: 3365 | G49: 25/12/2024
A50: INV-4048 | B50: MAT-002 | C50: WH-002 | D50: 2372 | E50: 465 | F50: 1907 | G50: 28-01-2024
A51: INV-4049 | B51: MAT-002 | C51: WH-002 | D51: 1755 | E51: 303 | F51: 1452 | G51: February 25, 2024
A52: INV-4050 | B52: MAT-002 | C52: WH-002 | D52: 4641 | E52: 124 | F52: 4517 | G52: 03/25/2024
A53: INV-4051 | B53: MAT-002 | C53: WH-002 | D53: 4985 | E53: 976 | F53: 4009 | G53: 04/26/2024
A54: INV-4052 | B54: MAT-002 | C54: WH-002 | D54: 4360 | E54: 164 | F54: 4196 | G54: May 25, 2024
A55: INV-4053 | B55: MAT-002 | C55: WH-002 | D55: 756 | E55: 172 | F55: 584 | G55: 06/28/2024
A56: INV-4054 | B56: MAT-002 | C56: WH-002 | D56: 4866 | E56: 504 | F56: 4362 | G56: July 25, 2024
A57: INV-4055 | B57: MAT-002 | C57: WH-002 | D57: 871 | E57: 214 | F57: 657 | G57: 2024-08-27
A58: INV-4056 | B58: MAT-002 | C58: WH-002 | D58: 1873 | E58: 321 | F58: 1552 | G58: 28-09-2024
A59: INV-4057 | B59: MAT-002 | C59: WH-002 | D59: 2657 | E59: 468 | F59: 2189 | G59: 10/25/2024
... A67: INV-4065 | B67: MAT-002 | C67: WH-003 | D67: 2362 | E67: 517 | F67: 1845 | G67: 06/25/2024
A68: INV-4066 | B68: MAT-002 | C68: WH-003 | D68: 3669 | E68: 566 | G68: 27-07-2024
A69: INV-4067 | B69: MAT-002 | C69: WH-003 | D69: 2345 | E69: 165 | F69: 2180 | G69: August 28, 2024
A70: INV-4068 | B70: MAT-002 | C70: WH-003 | D70: 279 | E70: 14 | G70: September 26, 2024
A71: INV-4069 | B71: MAT-002 | C71: WH-003 | D71: 495 | E71: 94 | F71: 401 | G71: 26/10/2024
A72: INV-4070 | B72: MAT-002 | C72: WH-003 | D72: 1244 | E72: 21 | F72: 1223 | G72: 2024-11-25
A73: INV-4071 | B73: MAT-002 | C73: WH-003 | D73: 1920 | E73: 255 | F73: 1665 | G73: December 27, 2024
A74: INV-4072 | B74: MAT-003 | C74: WH-001 | D74: 3529 | E74: 316 | F74: 3213 | G74: 26-01-2024
A75: INV-4073 | B75: MAT-003 | C75: WH-001 | D75: 1650 | E75: 451 | F75: 1199 | G75: 2024-02-26
A76: INV-4074 | B76: MAT-003 | C76: WH-001 | D76: 3572 | E76: 508 | F76: 3064 | G76: 25/03/2024
A77: INV-4075 | B77: MAT-003 | C77: WH-001 | D77: 517 | E77: 120 | F77: 397 | G77: 2024-04-28
A78: INV-4076 | B78: MAT-003 | C78: WH-001 | D78: 2700 | E78: 233 | F78: 2467 | G78: 26/05/2024
A79: INV-4077 | B79: MAT-003 | C79: WH-001 | D79: 2889 | E79: 285 | F79: 2604 | G79: 2024-06-27
A80: INV-4078 | B80: MAT-003 | C80: WH-001 | D80: 4373 | E80: 818 | F80: 3555 | G80: 07/27/2024
A81: INV-4079 | B81: MAT-003 | C81: WH-001 | D81: 1144 | E81: 133 | F81: 1011 | G81: 08/27/2024
A82: INV-4080 | B82: MAT-003 | C82: WH-001 | D82: 1088 | E82: 305 | F82: 783 | G82: 27/09/2024
A83: INV-4081 | B83: MAT-003 | C83: WH-001 | D83: 4389 | E83: 236 | F83: 4153 | G83: 2024-10-26
A84: INV-4082 | B84: MAT-003 | C84: WH-001 | D84: 563 | E84: 111 | G84: 2024-11-26
A85: INV-4083 | B85: MAT-003 | C85: WH-001 | D85: 3733 | E85: 143 | F85: 3590 | G85: December 27, 2024
A86: INV-4084 | B86: MAT-003 | C86: WH-002 | D86: 2771 | E86: 679 | F86: 2092 | G86: January 27, 2024
A87: INV-4085 | B87: MAT-003 | C87: WH-002 | D87: 2733 | E87: 682 | F87: 2051 | G87: 2024-02-28
A88: INV-4086 | B88: MAT-003 | C88: WH-002 | D88: 4741 | E88: 260 | F88: 4481 | G88: 28-03-2024
A89: INV-4087 | B89: MAT-003 | C89: WH-002 | D89: 4862 | E89: 616 | F89: 4246 | G89: 2024-04-25
A90: INV-4088 | B90: MAT-003 | C90: WH-002 | D90: 2550 | E90: 215 | F90: 2335 | G90: 27/05/2024
A91: INV-4089 | B91: MAT-003 | C91: WH-002 | D91: 3819 | E91: 905 | F91: 2914 | G91: 28-06-2024
A92: INV-4090 | B92: MAT-003 | C92: WH-002 | D92: 894 | E92: 145 | F92: 749 | G92: 07/27/2024
A93: INV-4091 | B93: MAT-003 | C93: WH-002 | D93: 2124 | E93: 317 | F93: 1807 | G93: 26-08-2024
A94: INV-4092 | B94: MAT-003 | C94: WH-002 | D94: 400 | E94: 5 | F94: 395 | G94: September 28, 2024
A95: INV-4093 | B95: MAT-003 | C95: WH-002 | D95: 796 | E95: 116 | F95: 680 | G95: 26/10/2024
A96: INV-4094 | B96: MAT-003 | C96: WH-002 | D96: 4249 | E96: 818 | F96: 3431 | G96: 11/25/2024
... A125: INV-4123 | B125: MAT-004 | C125: WH-002 | D125: 1191 | E125: 289 | F125: 902 | G125: April 27, 2024
A126: INV-4124 | B126: MAT-004 | C126: WH-002 | D126: 3709 | E126: 758 | G126: 05/27/2024
A127: INV-4125 | B127: MAT-004 | C127: WH-002 | D127: 3641 | E127: 1003 | F127: 2638 | G127: 27/06/2024
A128: INV-4126 | B128: MAT-004 | C128: WH-002 | D128: 1453 | E128: 222 | F128: 1231 | G128: July 27, 2024
A129: INV-4127 | B129: MAT-004 | C129: WH-002 | D129: 4608 | E129: 990 | F129: 3618 | G129: 2024-08-27
A130: INV-4128 | B130: MAT-004 | C130: WH-002 | D130: 2211 | E130: 88 | F130: 2123 | G130: 28-09-2024
A131: INV-4129 | B131: MAT-004 | C131: WH-002 | D131: 4006 | E131: 1167 | F131: 2839 | G131: 2024-10-28
A132: INV-4130 | B132: MAT-004 | C132: WH-002 | D132: 435 | E132: 126 | F132: 309 | G132: 26/11/2024
A133: INV-4131 | B133: MAT-004 | C133: WH-002 | D133: 1937 | E133: 363 | F133: 1574 | G133: 2024-12-27
A134: INV-4132 | B134: MAT-004 | C134: WH-003 | D134: 2463 | E134: 569 | G134: 01/26/2024
A135: INV-4133 | B135: MAT-004 | C135: WH-003 | D135: 2177 | E135: 416 | F135: 1761 | G135: 26/02/2024
A136: INV-4134 | B136: MAT-004 | C136: WH-003 | D136: 4220 | E136: 917 | F136: 3303 | G136: 2024-03-25
A137: INV-4135 | B137: MAT-004 | C137: WH-003 | D137: 2015 | E137: 414 | F137: 1601 | G137: April 27, 2024
A138: INV-4136 | B138: MAT-004 | C138: WH-003 | D138: 3223 | E138: 484 | F138: 2739 | G138: 27/05/2024
A139: INV-4137 | B139: MAT-004 | C139: WH-003 | D139: 4708 | E139: 677 | F139: 4031 | G139: 2024-06-28
A140: INV-4138 | B140: MAT-004 | C140: WH-003 | D140: 2711 | E140: 257 | F140: 2454 | G140: 2024-07-26
A141: INV-4139 | B141: MAT-004 | C141: WH-003 | D141: 1179 | E141: 274 | F141: 905 | G141: 26-08-2024
A142: INV-4140 | B142: MAT-004 | C142: WH-003 | D142: 1972 | E142: 495 | F142: 1477 | G142: 09/27/2024
A143: INV-4141 | B143: MAT-004 | C143: WH-003 | D143: 1790 | E143: 303 | F143: 1487 | G143: 2024-10-26
A144: INV-4142 | B144: MAT-004 | C144: WH-003 | D144: 315 | E144: 90 | F144: 225 | G144: 11/27/2024
A145: INV-4143 | B145: MAT-004 | C145: WH-003 | D145: 646 | E145: 141 | F145: 505 | G145: 26/12/2024
A146: INV-4144 | B146: MAT-005 | C146: WH-001 | D146: 1040 | E146: 6 | F146: 1034 | G146: 28/01/2024
...

Sheet Inventory_Transactions
A1: Column1 | B1: Column2 | C1: Column3 | D1: Column4 | E1: Column5 | F1: Column6 | G1: Column7 | H1: Column8
A2: TransactionID | B2: MaterialID | C2: TransactionType | D2: Quantity | E2: SourceLocation | F2: DestinationLocation | G2: ReferenceDocument | H2: Timestamp
A3: IT-6000 | B3: MAT-010 | C3: Adjustment | D3: 16 | E3: External | F3: Customer | G3: REF-7653 | H3: 08/01/2024
A4: IT-6001 | B4: MAT-001 | C4: Goods Issue | D4: 226 | E4: External | F4: Production | G4: REF-6231 | H4: 2024-12-18
A5: IT-6002 | B5: MAT-003 | C5: Transfer | D5: 264 | E5: Supplier | F5: WH-001 | H5: 23/07/2024
A6: IT-6003 | B6: MAT-007 | C6: Goods Issue | D6: 493 | E6: WH-002 | F6: WH-003 | G6: REF-9433 | H6: 2024-11-11
A7: IT-6004 | B7: MAT-001 | C7: Goods Receipt | D7: 484 | E7: External | G7: REF-5609 | H7: 11/09/2024
A8: IT-6005 | B8: MAT-009 | C8: Goods Receipt | D8: 434 | E8: WH-001 | F8: Production | G8: REF-1741 | H8: May 26, 2024
A9: IT-6006 | B9: MAT-004 | C9: Transfer | D9: 284 | E9: WH-003 | F9: WH-001 | H9: 10/14/2024
A10: IT-6007 | B10: MAT-006 | C10: Transfer | D10: 286 | E10: WH-003 | G10: REF-3245 | H10: 20/07/2024
A11: IT-6008 | B11: MAT-008 | C11: Goods Issue | D11: 311 | E11: Supplier | F11: WH-002 | G11: REF-5902 | H11: September 22, 2024
A12: IT-6009 | B12: MAT-009 | C12: Return | D12: -363 | E12: Supplier | F12: WH-003 | G12: REF-7824 | H12: 09/17/2024
A13: IT-6010 | B13: MAT-008 | C13: Transfer | D13: 496 | E13: Supplier | F13: Customer | H13: 01-11-2024
A14: IT-6011 | B14: MAT-010 | C14: Adjustment | D14: 57 | E14: WH-002 | F14: WH-001 | G14: REF-9221 | H14: 17/01/2024
A15: IT-6012 | B15: MAT-003 | C15: Write-Off | D15: 107 | E15: Supplier | F15: WH-003 | G15: REF-8531 | H15: 2024-02-01
A16: IT-6013 | B16: MAT-006 | C16: Adjustment | D16: 396 | E16: WH-003 | F16: Customer | G16: REF-5876 | H16: 06-10-2024
A17: IT-6014 | B17: MAT-008 | C17: Transfer | D17: 246 | E17: WH-003 | F17: Customer | G17: REF-9899 | H17: 19/12/2024
A18: IT-6015 | B18: MAT-003 | C18: Transfer | D18: 22 | E18: WH-003 | F18: WH-001 | G18: REF-4310 | H18: 2024-06-25
A19: IT-6016 | B19: MAT-005 | C19: Goods Issue | D19: 56 | E19: Supplier | F19: Customer | H19: 14/10/2024
A20: IT-6017 | B20: MAT-008 | C20: Goods Receipt | D20: 349 | E20: WH-002 | F20: WH-001 | G20: REF-8793 | H20: 18-06-2024
A21: IT-6018 | B21: MAT-006 | C21: Transfer | D21: 331 | E21: WH-001 | F21: WH-001 | G21: REF-1611 | H21: 27-05-2024
A22: IT-6019 | B22: MAT-003 | C22: Goods Receipt | D22: 429 | E22: External | F22: Production | H22: August 01, 2024
A23: IT-6020 | B23: MAT-002 | C23: Transfer | D23: 146 | E23: External | F23: Customer | G23: REF-5470 | H23: 11/04/2024
A24: IT-6021 | B24: MAT-003 | C24: Adjustment | D24: 235 USD | E24: WH-003 | F24: WH-002 | G24: REF-4164 | H24: 18/06/2024
A25: IT-6022 | B25: MAT-009 | C25: Transfer | D25: 45 | E25: External | F25: WH-001 | G25: REF-5272 | H25: 06/08/2024
A26: IT-6023 | B26: MAT-006 | C26: Transfer | D26: 299 | E26: Supplier | F26: WH-001 | G26: REF-8625 | H26: 16/05/2024
A27: IT-6024 | B27: MAT-009 | C27: Adjustment | D27: 395 | E27: WH-003 | F27: WH-001 | G27: REF-3188 | H27: 17/12/2024
A28: IT-6025 | B28: MAT-006 | C28: Return | D28: 360 | E28: Supplier | F28: Production | G28: REF-2341 | H28: November 06, 2024
A29: IT-6026 | B29: MAT-006 | C29: Goods Receipt | D29: 470 | E29: Supplier | F29: WH-001 | G29: REF-3455 | H29: December 26, 2024
A30: IT-6027 | B30: MAT-002 | C30: Adjustment | D30: 106 | E30: Supplier | F30: Production | G30: REF-9409 | H30: August 14, 2024
A31: IT-6028 | B31: MAT-009 | C31: Return | D31: 345 | E31: WH-003 | F31: WH-001 | G31: REF-1742 | H31: 01/30/2024
A32: IT-6029 | B32: MAT-001 | C32: Goods Receipt | D32: 479 | E32: External | F32: WH-001 | G32: REF-7887 | H32: 04/10/2024
A33: IT-6030 | B33: MAT-007 | C33: Return | D33: 42 | E33: Supplier | F33: WH-002 | H33: 17-08-2024
A34: IT-6031 | B34: MAT-001 | C34: Transfer | D34: 238 | E34: Supplier | F34: Production | G34: REF-5516 | H34: 01/02/2024
A35: IT-6032 | B35: MAT-007 | C35: Write-Off | D35: 393 | F35: WH-002 | G35: REF-1797 | H35: 01/17/2024
A36: IT-6033 | B36: MAT-008 | C36: Goods Issue | D36: 277 | E36: WH-002 | F36: WH-001 | G36: REF-6224 | H36: 2024-07-24
A37: IT-6034 | B37: MAT-005 | C37: Goods Issue | D37: 339 | E37: Supplier | F37: WH-002 | G37: REF-3869 | H37: 01/05/2024
A38: IT-6035 | B38: MAT-008 | C38: Goods Receipt | D38: 498 | E38: WH-003 | F38: Production | G38: REF-7167 | H38: October 11, 2024
A39: IT-6036 | B39: MAT-004 | C39: Goods Issue | D39: 154 | E39: WH-002 | F39: Production | G39: REF-3196 | H39: 2024-08-30
A40: IT-6037 | B40: MAT-006 | C40: Adjustment | D40: 41 | E40: External | F40: WH-003 | G40: REF-1647 | H40: 14-04-2024
A41: IT-6038 | B41: MAT-009 | C41: Goods Issue | D41: 246 | E41: WH-002 | F41: WH-003 | G41: REF-2922 | H41: 27/10/2024
A42: IT-6039 | B42: MAT-010 | C42: Adjustment | D42: 105 | E42: External | F42: WH-002 | G42: REF-6886 | H42: 2024-05-04
A43: IT-6040 | B43: MAT-008 | C43: Return | D43: 51 | E43: External | F43: WH-003 | G43: REF-4625 | H43: 09/19/2024
A44: IT-6041 | B44: MAT-009 | C44: Write-Off | D44: 297 | E44: External | F44: WH-003 | G44: REF-9180 | H44: 2024-05-13
A45: IT-6042 | B45: MAT-008 | C45: Adjustment | D45: 329 | E45: External | F45: Production | G45: REF-9000 | H45: May 11, 2024
A46: IT-6043 | B46: MAT-001 | C46: Write-Off | D46: 18 | E46: WH-001 | F46: WH-001 | H46: November 24, 2024
A47: IT-6044 | B47: MAT-006 | C47: Goods Receipt | D47: -317 | E47: Supplier | F47: Production | G47: REF-1274 | H47: 2024-08-21
A48: IT-6045 | B48: MAT-005 | C48: Goods Receipt | D48: 258 | E48: External | F48: WH-002 | G48: REF-9625 | H48: 2024-10-01
A49: IT-6046 | B49: MAT-007 | C49: Goods Receipt | D49: 192 | E49: External | F49: Production | G49: REF-2320 | H49: 05/16/2024
A50: IT-6047 | B50: MAT-007 | C50: Return | D50: -194 | E50: Supplier | F50: Production | G50: REF-8109 | H50: 2024-02-17
A51: IT-6048 | B51: MAT-002 | C51: Write-Off | D51: 471 | E51: WH-001 | F51: WH-002 | G51: REF-1762 | H51: 2024-10-16
A52: IT-6049 | B52: MAT-010 | C52: Adjustment | D52: 17 USD | E52: WH-002 | F52: WH-003 | G52: REF-7525 | H52: 2024-10-05
A53: IT-6050 | B53: MAT-010 | C53: Goods Issue | D53: 291 | E53: External | F53: Customer | G53: REF-2284 | H53: 2024-03-24
A54: IT-6051 | B54: MAT-002 | C54: Return | D54: 119 | E54: WH-001 | F54: WH-003 | H54: 2024-01-28
A55: IT-6052 | B55: MAT-008 | C55: Goods Issue | D55: 183 | E55: Supplier | F55: Production | G55: REF-5839 | H55: 08/18/2024
A56: IT-6053 | B56: MAT-005 | C56: Goods Issue | D56: 195 | F56: Production | G56: REF-6896 | H56: 02/12/2024
A57: IT-6054 | B57: MAT-002 | C57: Goods Issue | D57: 221 | F57: Customer | G57: REF-2524 | H57: 2024-03-08
A58: IT-6055 | B58: MAT-001 | C58: Transfer | D58: 212 | E58: External | F58: WH-001 | G58: REF-9537 | H58: 16/07/2024
A59: IT-6056 | B59: MAT-003 | C59: Transfer | D59: 155 | E59: WH-003 | F59: Production | G59: REF-2260 | H59: 27-03-2024
A60: IT-6057 | B60: MAT-008 | C60: Write-Off | D60: 316 | E60: WH-002 | F60: Production | G60: REF-7224 | H60: 2024-11-16
A61: IT-6058 | B61: MAT-006 | C61: Return | D61: 418 | E61: Supplier | F61: WH-002 | G61: REF-3910 | H61: 2024-08-13
A62: IT-6059 | B62: MAT-008 | C62: Write-Off | D62: 401 | E62: WH-002 | F62: WH-003 | G62: REF-4273 | H62: May 29, 2024
A63: IT-6060 | B63: MAT-009 | C63: Goods Receipt | D63: 488 | E63: External | F63: WH-002 | G63: REF-7703 | H63: 02-04-2024
A64: IT-6061 | B64: MAT-005 | C64: Goods Issue | D64: 130 | E64: WH-002 | F64: Production | G64: REF-7566 | H64: 20/11/2024
A65: IT-6062 | B65: MAT-001 | C65: Transfer | D65: 360 | E65: Supplier | F65: Customer | G65: REF-6816 | H65: October 05, 2024
A66: IT-6063 | B66: MAT-010 | C66: Adjustment | D66: 347 | F66: WH-003 | G66: REF-9366 | H66: January 23, 2024
A67: IT-6064 | B67: MAT-010 | C67: Goods Issue | D67: 229 | E67: WH-003 | F67: Production | G67: REF-1402 | H67: 2024-10-24
A68: IT-6065 | B68: MAT-002 | C68: Goods Receipt | D68: 426 | E68: WH-002 | F68: WH-003 | H68: 31/07/2024
A69: IT-6066 | B69: MAT-002 | C69: Transfer | D69: 23 | E69: WH-001 | F69: WH-001 | G69: REF-4996 | H69: June 12, 2024
A70: IT-6067 | B70: MAT-006 | C70: Write-Off | D70: 219 | E70: External | F70: WH-002 | H70: March 22, 2024
A71: IT-6068 | B71: MAT-008 | C71: Write-Off | D71: 220 | E71: External | F71: WH-001 | G71: REF-2025 | H71: April 11, 2024
A72: IT-6069 | B72: MAT-006 | C72: Transfer | D72: 101 | E72: External | F72: WH-001 | G72: REF-7367 | H72: April 05, 2024
A73: IT-6070 | B73: MAT-006 | C73: Transfer | D73: 433 | E73: External | F73: Customer | G73: REF-2388 | H73: 2024-02-28
A74: IT-6071 | B74: MAT-004 | C74: Transfer | D74: 60 | E74: WH-002 | F74: WH-003 | G74: REF-7286 | H74: 01/03/2024
A75: IT-6072 | B75: MAT-009 | C75: Adjustment | D75: 471 | E75: WH-002 | F75: Customer | G75: REF-1878 | H75: 11/21/2024
A76: IT-6073 | B76: MAT-003 | C76: Goods Issue | D76: 418 | E76: External | F76: Customer | G76: REF-8272 | H76: 09/05/2024
A77: IT-6074 | B77: MAT-001 | C77: Goods Issue | D77: 150 | E77: WH-001 | F77: WH-003 | G77: REF-9115 | H77: 10/16/2024
A78: IT-6075 | B78: MAT-002 | C78: Transfer | D78: 397 | E78: Supplier | F78: WH-003 | G78: REF-4580 | H78: 10/20/2024
A79: IT-6076 | B79: MAT-004 | C79: Transfer | D79: 448 | E79: WH-001 | F79: Production | G79: REF-2923 | H79: 30-11-2024
A80: IT-6077 | B80: MAT-010 | C80: Adjustment | D80: 180 | E80: Supplier | F80: Production | G80: REF-1972 | H80: April 17, 2024
A81: IT-6078 | B81: MAT-010 | C81: Write-Off | D81: 87 | E81: WH-003 | F81: WH-003 | H81: 23/05/2024
A82: IT-6079 | B82: MAT-005 | C82: Adjustment | D82: 65 | E82: WH-002 | F82: WH-002 | G82: REF-7434 | H82: January 31, 2024
A83: IT-6080 | B83: MAT-005 | C83: Adjustment | D83: 213 | E83: External | F83: Production | G83: REF-5558 | H83: 2024-11-19
A84: IT-6081 | B84: MAT-008 | C84: Transfer | D84: 298 | E84: WH-001 | F84: WH-001 | G84: REF-2037 | H84: 20/08/2024
A85: IT-6082 | B85: MAT-007 | C85: Goods Issue | D85: 254 | E85: WH-003 | F85: WH-003 | G85: REF-8951 | H85: 04/21/2024
A86: IT-6083 | B86: MAT-002 | C86: Adjustment | D86: 402 | E86: External | G86: REF-8009 | H86: 24-01-2024
A87: IT-6084 | B87: MAT-005 | C87: Goods Issue | D87: 448 | E87: WH-003 | F87: WH-001 | H87: 2024-11-28
A88: IT-6085 | B88: MAT-004 | C88: Return | D88: 336 USD | E88: WH-001 | F88: WH-001 | G88: REF-4705 | H88: 24/12/2024
A89: IT-6086 | B89: MAT-001 | C89: Adjustment | D89: 176 | E89: WH-001 | F89: Production | H89: 2024-01-05
A90: IT-6087 | B90: MAT-003 | C90: Return | D90: 397 | E90: WH-002 | F90: WH-002 | G90: REF-6753 | H90: 02-06-2024
A91: IT-6088 | B91: MAT-010 | C91: Adjustment | D91: 227 | E91: WH-002 | F91: WH-001 | G91: REF-6759 | H91: 2024-07-29
A92: IT-6089 | B92: MAT-004 | C92: Transfer | D92: 331 | E92: WH-001 | F92: WH-002 | G92: REF-1439 | H92: 2024-03-12
A93: IT-6090 | B93: MAT-009 | C93: Write-Off | D93: 261 | E93: WH-002 | F93: Production | G93: REF-9108 | H93: 15-04-2024
A94: IT-6091 | B94: MAT-010 | C94: Goods Receipt | D94: 271 | E94: WH-001 | F94: WH-003 | G94: REF-6986 | H94: 12-09-2024
A95: IT-6092 | B95: MAT-002 | C95: Goods Receipt | D95: 301 | F95: WH-001 | G95: REF-9300 | H95: August 29, 2024
A96: IT-6093 | B96: MAT-007 | C96: Adjustment | D96: 206 | E96: WH-001 | G96: REF-4329 | H96: 31-07-2024
A97: IT-6094 | B97: MAT-006 | C97: Return | D97: 301 | E97: WH-001 | G97: REF-2412 | H97: 10/01/2024
A98: IT-6095 | B98: MAT-010 | C98: Write-Off | D98: 29 | E98: WH-003 | F98: WH-002 | G98: REF-6680 | H98: 2024-08-20
A99: IT-6096 | B99: MAT-006 | C99: Goods Issue | D99: 384 | E99: WH-003 | F99: WH-001 | G99: REF-2046 | H99: March 26, 2024
A100: IT-6097 | B100: MAT-002 | C100: Return | D100: 234 | E100: Supplier | F100: WH-003 | G100: REF-2685 | H100: 11/17/2024
...

Sheet Customer
A1: CustomerID | B1: CustomerName | C1: Country | D1: Segment | E1: Channel
A2: CUST-001 | B2: Williams Sonoma | C2: USA | D2: Retailer | E2: In-Store
A3: CUST-002 | B3: Sur La Table | C3: USA | D3: Retailer | E3: In-Store
A4: CUST-003 | B4: Bed-Bath-and-Beyond | C4: USA | D4: Retailer | E4: In-Store
A5: CUST-004 | B5: Crate and Barrel | C5: USA | D5: Retailer | E5: In-Store
A6: CUST-005 | B6: Amazon | C6: USA | D6: E-Commerce | E6: Online
A7: CUST-006 | B7: Wayfair | C7: USA | D7: E-Commerce | E7: Online
A8: CUST-007 | B8: Costco-Wholesale | C8: USA | D8: Wholesale | E8: In-Store
A9: CUST-008 | B9: Target | C9: USA | D9: Retailer | E9: In-Store
A10: CUST-009 | B10: Best Buy | C10: USA | D10: Retailer | E10: In-Store
A11: CUST-010 | B11: Harvey Norman | C11: Australia | D11: Retailer | E11: In-Store
A12: CUST-011 | B12: John Lewis | C12: UK | D12: Retailer | E12: In-Store
A13: CUST-012 | B13: Fnac | C13: France | D13: Retailer
A14: CUST-013 | B14: MediaMarkt | C14: Germany | D14: Retailer | E14: In-Store
A15: CUST-014 | B15: Kitchen Direct | C15: USA | D15: Distributor | E15: B2B
A16: CUST-015 | B16: ElectroWorld | C16: Italy | D16: Retailer | E16: In-Store

Sheet Product_Master
A1: ProductID | B1: ProductCode | C1: ProductName | D1: ProductCategory | E1: ProductFamily | F1: Brand | G1: LifecycleStatus | H1: LaunchDate | I1: DiscontinueDate | J1: Voltage | K1: PowerConsumption | L1: Dimensions_Height | M1: Dimensions_Width | N1: Dimensions_Depth | O1: Weight | P1: Material | Q1: Color | R1: EnergyRating | S1: StandardCost | T1: ListPrice | U1: Currency | V1: MarginPercent | W1: HSCode | X1: CountryOfOrigin | Y1: ComplianceCertifications | Z1: ParentProductID | AA1: IsVariant
A2: PRD-001 | B2: SMG-001 | C2: Stand Mixer 5L | D2: Stand Mixers | E2: Baking | F2: SMEG | G2: Active | H2: 2018-02-21 | J2: 220V | K2: 1219W | L2: 82.5 | M2: 36.1 | N2: 44 | O2: 3.6 | P2: Stainless Steel | Q2: Silver | R2: A++ | S2: 180 | T2: 399 | U2: EUR | V2: 54.89 | W2: 8509.79 | X2: Italy | Y2: CE, RoHS, WEEE | AA2: Yes
A3: PRD-002 | B3: SMG-002 | C3: Stand Mixer 7L Professional | D3: Stand Mixers | E3: Baking | F3: SMEG | G3: Active | H3: 30/11/2021 | J3: 220V | K3: 1681W | L3: 43.6 | M3: 36.5 | N3: 29.4 | O3: 46.9 | P3: Stainless Steel | Q3: Pastel Blue | R3: B | S3: 260 | T3: 599 | U3: EUR | V3: 56.59 | X3: Italy | Y3: CE, RoHS, WEEE | Z3: PRD-001 | AA3: No
A4: PRD-003 | B4: SMG-003 | C4: Electric Oven 60cm | D4: Electric Ovens | E4: Cooking | F4: SMEG | G4: Active | H4: 12/13/2021 | J4: 220V | K4: 1985W | L4: 79.9 | M4: 90.7 | N4: 42.1 | O4: 26 | P4: Stainless Steel | Q4: Black | R4: A+ | S4: 540 | T4: 1299 | U4: EUR | V4: 58.43 | W4: 8509.44 | X4: Italy | Y4: CE, RoHS, WEEE | AA4: No
A5: PRD-004 | B5: SMG-004 | C5: Electric Oven 90cm Built-in | D5: Electric Ovens | E5: Cooking | F5: SMEG | G5: Active | H5: 01/12/2018 | J5: 220V / 110V | K5: 3081W | L5: 42.7 | M5: 83.8 | N5: 27.5 | O5: 45.6 | P5: Mixed | Q5: Black | R5: A+++ | S5: 790 | T5: 1899 | U5: EUR | V5: 58.4 | W5: 8509.82 | X5: Italy | Y5: CE, RoHS, WEEE | Z5: PRD-001 | AA5: No
A6: PRD-005 | B6: SMG-005 | C6: Cooktop 60cm Gas | D6: Cooktops | E6: Cooking | F6: SMEG | G6: Discontinued | H6: 2018-10-20 | J6: 220V / 110V | K6: 3099W | L6: 72.3 | M6: 60 | N6: 51.3 | O6: 21.2 | P6: Stainless Steel | Q6: Silver | S6: 310 | T6: 749 | U6: EUR | V6: 58.61 | W6: 8509.16 | X6: Italy | Y6: CE, RoHS, WEEE | AA6: No
A7: PRD-006 | B7: SMG-006 | C7: Cooktop 90cm Induction | D7: Cooktops | E7: Cooking | F7: SMEG | G7: Active | H7: 28/02/2020 | J7: 110V | K7: 2967W | L7: 58.7 | M7: 96 | N7: 55.6 | O7: 8.1 | P7: Aluminum | Q7: Black | R7: A+++ | S7: 490 | T7: 1199 | U7: EUR | V7: 59.13 | W7: 8509.3 | X7: Italy | Y7: CE, RoHS, WEEE | Z7: PRD-001 | AA7: No
A8: PRD-007 | B8: SMG-007 | C8: Range Hood 60cm | D8: Range Hoods | E8: Ventilation | F8: SMEG | G8: Active | H8: 11/05/2020 | I8: 45838 | J8: 110V | K8: 3417W | L8: 33.9 | M8: 56.2 | N8: 32.3 | O8: 52.5 | P8: Stainless Steel | Q8: Silver | R8: A+ | S8: 220 | T8: 549 | U8: EUR | V8: 59.93 | W8: 8509.24 | X8: Italy | Y8: CE, RoHS, WEEE | Z8: PRD-001 | AA8: No
A9: PRD-008 | B9: SMG-008 | C9: Range Hood 90cm | D9: Range Hoods | E9: Ventilation | F9: SMEG | G9: Active | H9: 29-04-2018 | I9: 45838 | J9: 220V | K9: 1150W | L9: 77.1 | M9: 98.5 | N9: 49 | O9: 8.7 | P9: Stainless Steel | Q9: Black | R9: B | S9: 330 | T9: 799 | U9: EUR | V9: 58.7 | W9: 8509.64 | X9: Italy | Y9: CE, RoHS, WEEE | Z9: PRD-001 | AA9: No
A10: PRD-009 | B10: SMG-009 | C10: Dishwasher 60cm | D10: Dishwashers | E10: Cleaning | F10: SMEG | G10: Active | H10: 2020-03-28 | J10: 220V / 110V | K10: 2649W | L10: 35.7 | M10: 53.7 | N10: 51.5 | O10: 14.2 | P10: Stainless Steel | Q10: Cream | S10: 370 | T10: 899 | U10: EUR | V10: 58.84 | W10: 8509.14 | X10: Italy | AA10: No
A11: PRD-010 | B11: SMG-010 | C11: Refrigerator French Door | D11: Refrigerators | E11: Cooling | F11: SMEG | G11: Active | H11: 09-01-2021 | I11: 45838 | J11: 220V / 110V | K11: 3160W | L11: 74.9 | M11: 86.5 | N11: 33.6 | O11: 7.1 | P11: Mixed | Q11: Pastel Blue | R11: A | S11: 850 | T11: 1999 | U11: EUR | V11: 57.48 | W11: 8509.16 | X11: Italy | Y11: CE, RoHS, WEEE | AA11: No
A12: PRD-011 | B12: SMG-011 | C12: Toaster 2-Slot | D12: Toasters | E12: Small Appliances | F12: SMEG | G12: Active | H12: 06/28/2022 | J12: 220V | K12: 2996W | L12: 49.5 | M12: 49.5 | N12: 36.2 | O12: 50.9 | P12: Stainless Steel | Q12: Cream | R12: B | S12: 80 | T12: 229 | U12: EUR | V12: 65.07 | W12: 8509.21 | X12: Italy | Y12: CE, RoHS, WEEE | AA12: No
A13: PRD-012 | B13: SMG-012 | C13: Toaster 4-Slot | D13: Toasters | E13: Small Appliances | F13: SMEG | G13: Discontinued | H13: 14/03/2019 | I13: 45838 | J13: 220V | L13: 47.3 | M13: 94.9 | N13: 60.3 | O13: 17.1 | P13: Mixed | Q13: Red | R13: A++ | S13: 115 | T13: 319 | U13: EUR | V13: 63.95 | W13: 8509.17 | X13: Italy | Y13: CE, RoHS, WEEE | Z13: PRD-001 | AA13: Yes
A14: PRD-013 | B14: SMG-013 | C14: Blender Professional | D14: Blenders | E14: Small Appliances | F14: SMEG | G14: Active | H14: 11/04/2021 | J14: 220V / 110V | L14: 55.5 | M14: 89.6 | N14: 28.1 | O14: 5.6 | P14: Mixed | Q14: Cream | R14: B | S14: 105 | T14: 289 | U14: EUR | V14: 63.67 | X14: Italy | Z14: PRD-001 | AA14: No
A15: PRD-014 | B15: SMG-014 | C15: Coffee Maker Filter | D15: Coffee Makers | E15: Small Appliances | F15: SMEG | G15: Active | H15: 2019-02-23 | J15: 110V | K15: 1336W | L15: 41 | M15: 52.1 | N15: 58.8 | O15: 5.8 | P15: Stainless Steel | Q15: Cream | R15: B | S15: 70 | T15: 199 | U15: EUR | V15: 64.82 | X15: Italy | Y15: CE, RoHS, WEEE | AA15: No
A16: PRD-015 | B16: SMG-015 | C16: Coffee Maker Espresso | D16: Coffee Makers | E16: Small Appliances | F16: SMEG | G16: Active | H16: 07-08-2019 | J16: 220V / 110V | K16: 2039W | L16: 89.1 | M16: 75.8 | N16: 25.4 | O16: 45.3 | P16: Stainless Steel | Q16: Red | S16: 220 | T16: 549 | U16: EUR | V16: 59.93 | W16: 8509.23 | X16: Italy | Y16: CE, RoHS, WEEE | AA16: No
A17: PRD-016 | B17: SMG-016 | C17: Food Processor 3L | D17: Food Processors | E17: Small Appliances | F17: SMEG | G17: Active | H17: 2019-02-21 | J17: 110V | L17: 49.7 | M17: 49.4 | N17: 25.2 | O17: 42.9 | P17: Aluminum | Q17: Red | R17: A | S17: 60 | T17: 169 | U17: EUR | V17: 64.5 | W17: 8509.64 | X17: Italy | Y17: CE, RoHS, WEEE | Z17: PRD-001 | AA17: No

Sheet Purchase_Order
A1: PO_ID | B1: SupplierID | C1: OrderDate | D1: ExpectedDeliveryDate | E1: Status | F1: TotalAmount | G1: Currency
A2: PO-2000 | B2: SUP-007 | C2: 2024-03-23 | D2: April 11, 2024 | E2: Received | F2: 30302.8 | G2: EUR
A3: PO-2001 | B3: SUP-004 | C3: February 10, 2024 | D3: February 26, 2024 | E3: Received | F3: 29015.26 | G3: EUR
A4: PO-2002 | B4: SUP-003 | C4: February 21, 2024 | D4: March 17, 2024 | E4: Received | F4: 57209.4 | G4: USD
A5: PO-2003 | B5: SUP-005 | C5: 2024-03-23 | D5: 15-05-2024 | E5: Partial | G5: USD
A6: PO-2004 | B6: SUP-007 | C6: 27-09-2024 | D6: 22-11-2024 | E6: Received | F6: 46569.12 | G6: USD
A7: PO-2005 | B7: SUP-001 | C7: 06-11-2024 | D7: 18-12-2024 | E7: partial | F7: 58994.5 | G7: USD
A8: PO-2006 | B8: SUP-004 | C8: 27-08-2024 | E8: Received | F8: 61831.64 | G8: EUR
A9: PO-2007 | B9: SUP-006 | C9: 16-02-2024 | D9: 2024-04-09 | E9: RECEIVED | F9: 31038.24 | G9: EUR
A10: PO-2008 | B10: SUP-003 | C10: 04/04/2024 | D10: May 21, 2024 | E10: Cancelled | F10: 6959.68 | G10: EUR
A11: PO-2009 | B11: SUP-002 | C11: 12/08/2024 | D11: 30/01/2025 | E11: received | F11: 34002.11 | G11: EUR
A12: PO-2010 | B12: SUP-007 | C12: 12/04/2024 | D12: 23/05/2024 | E12: Received | F12: 11441.33 | G12: EUR
A13: PO-2011 | B13: SUP-002 | C13: 12/19/2024 | D13: 17-01-2025 | E13: Pending | F13: 93261.72 | G13: USD
A14: PO-2012 | B14: SUP-006 | C14: 02-03-2024 | D14: 05-04-2024 | E14: Cancelled | F14: 31371.69 | G14: EUR
A15: PO-2013 | B15: SUP-008 | C15: September 27, 2024 | D15: 11/19/2024 | E15: Pending | F15: 51139.26 | G15: EUR
A16: PO-2014 | B16: SUP-002 | C16: 10-02-2024 | D16: March 07, 2024 | E16: Received | F16: 3656.2 | G16: USD
A17: PO-2015 | B17: SUP-003 | C17: 30-10-2024 | D17: 24-12-2024 | E17: Cancelled | F17: 10591.28 | G17: USD
A18: PO-2016 | B18: SUP-008 | C18: 2024-05-04 | D18: 06/22/2024 | E18: Pending | F18: 41509.31 | G18: EUR
A19: PO-2017 | B19: SUP-002 | C19: October 27, 2024 | D19: 12/13/2024 | E19: cancelled | F19: 14892.36 | G19: EUR
A20: PO-2018 | B20: SUP-003 | C20: 08/13/2024 | D20: 03/09/2024 | E20: Partial | F20: 7853.6 | G20: EUR
... A23: PO-2021 | B23: SUP-004 | C23: 2024-07-08 | D23: 07/08/2024 | E23: RECEIVED | F23: 5929.12 | G23: EUR
A24: PO-2022 | B24: SUP-008 | C24: 2024-02-15 | D24: 04/04/2024 | E24: Received | G24: USD
A25: PO-2023 | B25: SUP-005 | C25: 08/30/2024 | D25: 28-09-2024 | E25: received | F25: 5087.04 | G25: EUR
A26: PO-2024 | B26: SUP-005 | C26: 04/29/2024 | D26: 05/15/2024 | E26: Cancelled | F26: 90132.17 | G26: EUR
A27: PO-2025 | B27: SUP-007 | C27: July 18, 2024 | D27: August 06, 2024 | E27: Received | F27: 140045.17 | G27: USD
A28: PO-2026 | B28: SUP-008 | C28: 28/03/2024 | D28: 04/17/2024 | E28: Received | F28: 12967.27 | G28: USD
A29: PO-2027 | B29: SUP-002 | C29: 08/12/2024 | D29: 2024-08-30 | E29: Partial | F29: 164083.68 | G29: EUR
A30: PO-2028 | B30: SUP-002 | C30: 06/20/2024 | D30: 08/03/2024 | E30: Pending | F30: 13690.7 | G30: EUR
A31: PO-2029 | B31: SUP-003 | C31: July 28, 2024 | D31: 2024-08-23 | E31: Cancelled | F31: 16911.96 | G31: EUR
A32: PO-2030 | B32: SUP-008 | C32: October 03, 2024 | D32: November 10, 2024 | E32: cancelled | G32: USD
A33: PO-2031 | B33: SUP-001 | C33: 2024-02-24 | D33: 29/03/2024 | E33: received | F33: 16567.2 | G33: USD
A34: PO-2032 | B34: SUP-008 | C34: November 04, 2024 | D34: December 25, 2024 | E34: Received | F34: 1691.5 | G34: EUR
A35: PO-2033 | B35: SUP-007 | C35: 09-03-2024 | D35: 19/04/2024 | E35: Partial | F35: 37103.74 | G35: EUR
A36: PO-2034 | B36: SUP-001 | C36: 30/09/2024 | D36: 14/11/2024 | E36: Cancelled | F36: 14605.76 | G36: USD
A37: PO-2035 | B37: SUP-003 | C37: January 12, 2024 | D37: 02/02/2024 | E37: Received | F37: 88743 | G37: EUR
A38: PO-2036 | B38: SUP-003 | C38: 2024-04-20 | D38: 2024-05-31 | E38: Partial | F38: 82193.65 | G38: EUR
A39: PO-2037 | B39: SUP-006 | C39: May 31, 2024 | D39: 2024-07-23 | E39: Cancelled | F39: 59121.79 | G39: USD
A40: PO-2038 | B40: SUP-001 | C40: 2024-03-13 | E40: Cancelled | F40: 19198.19 | G40: USD
A41: PO-2039 | B41: SUP-007 | C41: 2024-12-14 | D41: 13/01/2025 | E41: Pending | F41: 28040.58 | G41: USD
A42: PO-2040 | B42: SUP-003 | C42: 14/10/2024 | D42: 11/11/2024 | E42: received | F42: 8166.69 | G42: EUR
A43: PO-2041 | B43: SUP-005 | C43: 22/09/2024 | D43: 14/11/2024 | E43: Partial | F43: 18852.11 | G43: USD
A44: PO-2042 | B44: SUP-001 | C44: 09/06/2024 | D44: October 19, 2024 | E44: Partial | F44: 77918.68 | G44: USD
A45: PO-2043 | B45: SUP-008 | C45: 16-04-2024 | D45: 2024-05-21 | E45: pending | F45: 10169.28 | G45: EUR
A46: PO-2044 | B46: SUP-007 | C46: April 10, 2024 | D46: 01/06/2024 | E46: Cancelled | F46: 63247.31 | G46: EUR
A47: PO-2045 | B47: SUP-006 | C47: 02/17/2024 | D47: April 06, 2024 | E47: Cancelled | F47: 50089.2 | G47: EUR
A48: PO-2046 | B48: SUP-008 | C48: 19-01-2024 | D48: February 09, 2024 | E48: Partial | F48: 53408.88 | G48: EUR
A49: PO-2047 | B49: SUP-004 | C49: November 30, 2024 | E49: Cancelled | F49: 1327.41 | G49: EUR
A50: PO-2048 | B50: SUP-006 | C50: 16/08/2024 | D50: October 13, 2024 | E50: Pending | F50: 105600.63 | G50: EUR
A51: PO-2049 | B51: SUP-006 | C51: 08/06/2024 | D51: 30/08/2024 | E51: Cancelled | F51: 110679.04 | G51: EUR
A52: PO-2050 | B52: SUP-005 | C52: May 17, 2024 | D52: 06/20/2024 | E52: Cancelled | G52: USD
A53: PO-2051 | B53: SUP-006 | C53: March 25, 2024 | D53: 2024-04-23 | E53: Pending | F53: 12423.21 | G53: USD
A54: PO-2052 | B54: SUP-008 | C54: 2024-08-10 | D54: September 24, 2024 | E54: Partial | F54: 24469.63 | G54: USD
A55: PO-2053 | B55: SUP-006 | C55: 2024-09-13 | E55: Received | F55: 7652.82 | G55: EUR
A56: PO-2054 | B56: SUP-005 | C56: 09/05/2024 | D56: July 08, 2024 | E56: Partial | F56: 32002.77 | G56: EUR
A57: PO-2055 | B57: SUP-005 | C57: July 09, 2024 | D57: 25/08/2024 | E57: Partial | F57: 15152.28 | G57: EUR
A58: PO-2056 | B58: SUP-002 | C58: 04/01/2024 | D58: 30/01/2024 | E58: Received | F58: 168169.24 | G58: USD
A59: PO-2057 | B59: SUP-001 | C59: 15-12-2024 | D59: 08-02-2025 | E59: Partial | F59: 2598 | G59: USD
A60: PO-2058 | B60: SUP-008 | C60: 03-01-2024 | D60: 03/01/2024 | E60: Received | F60: 572.88 | G60: EUR
A61: PO-2059 | B61: SUP-001 | C61: 09/27/2024 | D61: 11/17/2024 | E61: Pending | F61: 1920.71 | G61: EUR
A62: PO-2060 | B62: SUP-002 | C62: March 03, 2024 | D62: 2024-04-18 | E62: Cancelled | G62: EUR
A63: PO-2061 | B63: SUP-005 | C63: 23/06/2024 | D63: 2024-07-08 | E63: Partial | F63: 27457.6 | G63: USD
A64: PO-2062 | B64: SUP-008 | C64: 14-05-2024 | D64: 10-06-2024 | E64: Cancelled | F64: 73165.75 | G64: EUR
A65: PO-2063 | B65: SUP-001 | C65: 12/23/2024 | D65: February 17, 2025 | E65: Received | F65: 414.48 | G65: EUR
A66: PO-2064 | B66: SUP-004 | C66: 03-06-2024 | D66: 07/20/2024 | E66: Pending | F66: 321.44 | G66: USD
A67: PO-2065 | B67: SUP-008 | C67: July 08, 2024 | D67: 2024-08-23 | E67: Received | F67: 25577.24 | G67: USD
A68: PO-2066 | B68: SUP-005 | C68: 31-03-2024 | D68: 24-05-2024 | E68: Pending | G68: USD
A69: PO-2067 | B69: SUP-002 | C69: 2024-04-04 | D69: 19/05/2024 | E69: Pending | F69: 24692.74 | G69: USD
A70: PO-2068 | B70: SUP-001 | C70: November 08, 2024 | E70: Partial | F70: 123281.56 | G70: EUR
A71: PO-2069 | B71: SUP-006 | C71: 2024-11-27 | D71: 2025-01-06 | E71: Received | G71: USD
A72: PO-2070 | B72: SUP-006 | C72: 29/04/2024 | D72: June 01, 2024 | E72: Pending | F72: 20719.92 | G72: EUR
A73: PO-2071 | B73: SUP-008 | C73: 08/19/2024 | D73: 15/10/2024 | E73: Received | F73: 512.19 | G73: USD
A74: PO-2072 | B74: SUP-002 | C74: 09/14/2024 | D74: 16-10-2024 | E74: Received | F74: 6437.2 | G74: EUR
A75: PO-2073 | B75: SUP-001 | C75: 10-05-2024 | D75: 05/25/2024 | E75: Cancelled | F75: 14441.82 | G75: USD
A76: PO-2074 | B76: SUP-003 | C76: 16/05/2024 | D76: June 18, 2024 | E76: PARTIAL | F76: 23423.53 | G76: EUR
A77: PO-2075 | B77: SUP-002 | C77: May 29, 2024 | D77: July 15, 2024 | E77: Pending | F77: 69487 | G77: EUR
A78: PO-2076 | B78: SUP-007 | C78: 22/12/2024 | D78: 30/01/2025 | E78: Cancelled | F78: 95672.82 | G78: USD
A79: PO-2077 | B79: SUP-004 | C79: 16-10-2024 | D79: November 15, 2024 | E79: Pending | F79: 73246.09 | G79: USD
A80: PO-2078 | B80: SUP-006 | C80: 20/09/2024 | D80: 02/11/2024 | E80: Partial | F80: 65651.45 | G80: EUR
A81: PO-2079 | B81: SUP-001 | C81: 2024-08-01 | E81: Pending | F81: 8433.98 | G81: EUR
A82: PO-2080 | B82: SUP-006 | C82: 26/10/2024 | D82: 04/12/2024 | E82: received | F82: 6281.45 | G82: EUR
A83: PO-2081 | B83: SUP-007 | C83: 05/08/2024 | D83: 09/17/2024 | E83: cancelled | F83: 13627.64 | G83: EUR
A84: PO-2082 | B84: SUP-001 | C84: 2024-03-17 | D84: 04/12/2024 | E84: Received | F84: 3637.92 | G84: USD
A85: PO-2083 | B85: SUP-008 | C85: 2024-12-27 | D85: 2025-01-27 | E85: Partial | F85: 2059.72 | G85: EUR
A86: PO-2084 | B86: SUP-007 | C86: 03-06-2024 | D86: 27/07/2024 | E86: Received | F86: 25143.65 | G86: EUR
A87: PO-2085 | B87: SUP-005 | C87: 2024-04-16 | E87: Pending | F87: 34490.55 | G87: EUR
A88: PO-2086 | B88: SUP-004 | C88: 2024-05-15 | D88: 06/03/2024 | E88: Received | F88: 101700.9 | G88: USD
A89: PO-2087 | B89: SUP-007 | C89: 05-07-2024 | D89: 26/07/2024 | E89: Received | F89: 10359.31 | G89: EUR
A90: PO-2088 | B90: SUP-003 | C90: 2024-11-27 | D90: December 13, 2024 | E90: Received | F90: 38920.43 | G90: USD
A91: PO-2089 | B91: SUP-004 | C91: January 02, 2024 | E91: Received | F91: 17499.88 | G91: EUR
A92: PO-2090 | B92: SUP-007 | C92: 26-03-2024 | D92: May 25, 2024 | E92: Cancelled | F92: 26657.37 | G92: EUR
A93: PO-2091 | B93: SUP-008 | C93: April 28, 2024 | D93: 22-05-2024 | E93: Pending | F93: 22251.6 | G93: USD
A94: PO-2092 | B94: SUP-005 | C94: 01/09/2024 | D94: 2024-10-08 | E94: Pending | G94: EUR
A95: PO-2093 | B95: SUP-006 | C95: 2024-04-03 | D95: 2024-05-10 | E95: Received | F95: 6050.21 | G95: USD
A96: PO-2094 | B96: SUP-003 | C96: 10/05/2024 | D96: 2024-10-27 | E96: Received | F96: 16739.21 | G96: USD
A97: PO-2095 | B97: SUP-004 | C97: 03-01-2024 | D97: 2024-02-07 | E97: CANCELLED | F97: 184556.8 | G97: USD
A98: PO-2096 | B98: SUP-003 | C98: 10/06/2024 | D98: June 30, 2024 | E98: Received | F98: 7534.22 | G98: EUR
A99: PO-2097 | B99: SUP-004 | C99: 06/19/2024 | D99: 08/12/2024 | E99: Pending | F99: 14742.87 | G99: USD
A100: PO-2098 | B100: SUP-006 | C100: 21-10-2024 | D100: 15-11-2024 | E100: Received | F100: 32022.8 | G100: USD
A101: PO-2099 | B101: SUP-008 | C101: 19-12-2024 | D101: 21/01/2025 | E101: Pending | F101: 52986.37 | G101: USD
A102: PO-2100 | B102: SUP-008 | C102: 03/10/2024 | D102: 11/29/2024 | E102: Partial | F102: 14117.06 | G102: EUR
...

Sheet PO_Items
A1: PO_Item_ID | B1: PO_ID | C1: MaterialID | D1: MaterialName | E1: Quantity | F1: UnitPrice | G1: ReceivedQuantity
A2: POI-8000 | B2: PO-2000 | C2: MAT-007 | D2: Electronic Control Module | E2: 776 | F2: 39.05 | G2: 772
A3: POI-8001 | B3: PO-2001 | C3: MAT-006 | D3: Tempered Glass Panel | E3: 948 | F3: 18.43 | G3: 678
A4: POI-8002 | B4: PO-2001 | C4: MAT-001 | D4: Stainless Steel Sheet | E4: 1959 | F4: 4 | G4: 112
A5: POI-8003 | B5: PO-2001 | C5: MAT-003 | D5: Aluminum Frame | E5: 994 | F5: 3.73 | G5: 424
A6: POI-8004 | B6: PO-2002 | C6: MAT-009 | D6: Motor Assembly | E6: 937 | F6: 43.74 | G6: 142
A7: POI-8005 | B7: PO-2002 | C7: MAT-001 | E7: 1599 | F7: 4.44 | G7: 1048
A8: POI-8006 | B8: PO-2002 | C8: MAT-002 | D8: Copper Wiring Bundle | E8: 1179 | F8: 7.74 | G8: 558
A9: POI-8007 | B9: PO-2003 | C9: MAT-004 | D9: Ceramic Heating Element | E9: 1654 | F9: 12.04 | G9: 147
A10: POI-8008 | B10: PO-2003 | C10: MAT-003 | D10: Aluminum Frame | E10: 401 | F10: 4.18 | G10: 155
A11: POI-8009 | B11: PO-2003 | C11: MAT-008 | D11: Thermal Insulation | E11: 327 | F11: 6.37 | G11: 136
A12: POI-8010 | B12: PO-2003 | C12: MAT-004 | D12: Ceramic Heating Element | E12: 1482 | F12: 12.52 | G12: 365
A13: POI-8011 | B13: PO-2004 | C13: MAT-003 | D13: Aluminum Frame | E13: 976 | F13: 4.17 | G13: 969
A14: POI-8012 | B14: PO-2004 | C14: MAT-007 | D14: Electronic Control Module | E14: 1080 | F14: 38.99 | G14: 39
A15: POI-8013 | B15: PO-2004 | C15: MAT-010 | D15: Packaging Materials | E15: 250 | F15: 1.56 | G15: 140
A16: POI-8014 | B16: PO-2005 | C16: MAT-006 | D16: Tempered Glass Panel | E16: 1825 | F16: 20.31 | G16: 1701
A17: POI-8015 | B17: PO-2005 | C17: MAT-006 | E17: 1325 | F17: 16.55 | G17: 960
A18: POI-8016 | B18: PO-2006 | C18: MAT-009 | D18: Motor Assembly | E18: 993 | F18: 45.36 | G18: 376
A19: POI-8017 | B19: PO-2006 | C19: MAT-004 | D19: Ceramic Heating Element | E19: 1006 | F19: 11.06 | G19: 141
A20: POI-8018 | B20: PO-2006 | C20: MAT-001 | D20: Stainless Steel Sheet | E20: 1452 | F20: 3.9 | G20: 471
A21: POI-8019 | B21: PO-2007 | C21: MAT-009 | D21: Motor Assembly | E21: 514 | F21: 50.52 | G21: 308
A22: POI-8020 | B22: PO-2007 | C22: MAT-003 | D22: Aluminum Frame | E22: 338 | F22: 3.81 | G22: 221
A23: POI-8021 | B23: PO-2007 | C23: MAT-004 | D23: Ceramic Heating Element | E23: 227 | F23: 11.9 | G23: 226
A24: POI-8022 | B24: PO-2007 | C24: MAT-004 | D24: Ceramic Heating Element | E24: 86 | F24: 12.58 | G24: 78
A25: POI-8023 | B25: PO-2008 | C25: MAT-004 | D25: Ceramic Heating Element | E25: 335 | F25: 13.44 | G25: 110
A26: POI-8024 | B26: PO-2008 | C26: MAT-005 | D26: ABS Plastic Housing | E26: 1097 | F26: 2.24 | G26: 382
A27: POI-8025 | B27: PO-2009 | C27: MAT-001 | D27: Stainless Steel Sheet | E27: 1449 | F27: 4.19 | G27: 13
A28: POI-8026 | B28: PO-2009 | C28: MAT-007 | D28: Electronic Control Module | E28: 640 | F28: 32.27 | G28: 200
A29: POI-8027 | B29: PO-2009 | C29: MAT-002 | D29: Copper Wiring Bundle | E29: 712 | F29: 8.25 | G29: 159
... A50: POI-8048 | B50: PO-2017 | C50: MAT-001 | D50: Stainless Steel Sheet | E50: 1110 | F50: 4.07 | G50: 447
A51: POI-8049 | B51: PO-2017 | C51: MAT-010 | E51: 295 | F51: 1.72 | G51: 43
A52: POI-8050 | B52: PO-2018 | C52: MAT-010 | D52: Packaging Materials | E52: 1193 | F52: 1.68 | G52: 12
A53: POI-8051 | B53: PO-2018 | C53: MAT-003 | D53: Aluminum Frame | E53: 1496 | F53: 3.91 | G53: 1330
A54: POI-8052 | B54: PO-2019 | C54: MAT-004 | D54: Ceramic Heating Element | E54: 321 | F54: 11.52 | G54: 53
A55: POI-8053 | B55: PO-2019 | C55: MAT-004 | D55: Ceramic Heating Element | E55: 1053 | F55: 10.84 | G55: 655
A56: POI-8054 | B56: PO-2019 | C56: MAT-008 | D56: Thermal Insulation | E56: 1508 | F56: 6.93 | G56: 156
A57: POI-8055 | B57: PO-2019 | C57: MAT-001 | D57: Stainless Steel Sheet | E57: 547 | F57: 4.28 | G57: 162
A58: POI-8056 | B58: PO-2020 | C58: MAT-008 | D58: Thermal Insulation | E58: 267 | F58: 7.19 | G58: 87
A59: POI-8057 | B59: PO-2020 | C59: MAT-010 | D59: Packaging Materials | E59: 170 | F59: 1.65 | G59: 25
A60: POI-8058 | B60: PO-2020 | C60: MAT-001 | E60: 1867 | F60: 3.97 | G60: 1236
A61: POI-8059 | B61: PO-2021 | C61: MAT-010 | D61: Packaging Materials | E61: 863 | F61: 1.54 | G61: 522
A62: POI-8060 | B62: PO-2021 | C62: MAT-010 | D62: Packaging Materials | E62: 80 | F62: 1.39 | G62: 34
A63: POI-8061 | B63: PO-2021 | C63: MAT-001 | D63: Stainless Steel Sheet | E63: 1151 | F63: 3.9 | G63: 287
A64: POI-8062 | B64: PO-2022 | C64: MAT-010 | E64: 457 | F64: 1.67 | G64: 272
A65: POI-8063 | B65: PO-2023 | C65: MAT-009 | D65: Motor Assembly | E65: 112 | F65: 45.42 | G65: 66
A66: POI-8064 | B66: PO-2024 | C66: MAT-005 | D66: ABS Plastic Housing | E66: 683 | F66: 2.09 | G66: 475
A67: POI-8065 | B67: PO-2024 | C67: MAT-009 | D67: Motor Assembly | E67: 1333 | F67: 50.26 | G67: 300
A68: POI-8066 | B68: PO-2024 | C68: MAT-006 | D68: Tempered Glass Panel | E68: 1202 | F68: 18.06 | G68: 615
A69: POI-8067 | B69: PO-2025 | C69: MAT-001 | D69: Stainless Steel Sheet | E69: 842 | F69: 4.52 | G69: 108
A70: POI-8068 | B70: PO-2025 | C70: MAT-007 | D70: Electronic Control Module | E70: 1453 | F70: 37.83 | G70: 1139
A71: POI-8069 | B71: PO-2025 | C71: MAT-005 | D71: ABS Plastic Housing | E71: 1800 | F71: 2.11 | G71: 1630
A72: POI-8070 | B72: PO-2025 | C72: MAT-009 | D72: Motor Assembly | E72: 1431 | F72: 54.14 | G72: 1312
A73: POI-8071 | B73: PO-2026 | C73: MAT-010 | D73: Packaging Materials | E73: 889 | F73: 1.67 | G73: 665
A74: POI-8072 | B74: PO-2026 | C74: MAT-007 | D74: Electronic Control Module | E74: 362 | F74: 31.72 | G74: 298
A75: POI-8073 | B75: PO-2027 | C75: MAT-007 | D75: Electronic Control Module | E75: 1737 | F75: 36.11 | G75: 769
A76: POI-8074 | B76: PO-2027 | C76: MAT-004 | D76: Ceramic Heating Element | E76: 1724 | F76: 12.11 | G76: 204
... A82: POI-8080 | B82: PO-2029 | C82: MAT-004 | D82: Ceramic Heating Element | E82: 434 | F82: 11.84 | G82: 422
A83: POI-8081 | B83: PO-2030 | C83: MAT-003 | E83: 1742 | F83: 4.24 | G83: 1415
A84: POI-8082 | B84: PO-2030 | C84: MAT-001 | D84: Stainless Steel Sheet | E84: 182 | F84: 4.53 | G84: 56
A85: POI-8083 | B85: PO-2031 | C85: MAT-006 | D85: Tempered Glass Panel | E85: 936 | F85: 17.7 | G85: 0
A86: POI-8084 | B86: PO-2032 | C86: MAT-005 | D86: ABS Plastic Housing | E86: 850 | F86: 1.99 | G86: 619
A87: POI-8085 | B87: PO-2033 | C87: MAT-002 | D87: Copper Wiring Bundle | E87: 895 | F87: 9.14 | G87: 398
A88: POI-8086 | B88: PO-2033 | C88: MAT-008 | D88: Thermal Insulation | E88: 1425 | F88: 7.42 | G88: 136
A89: POI-8087 | B89: PO-2033 | C89: MAT-008 | D89: Thermal Insulation | E89: 1928 | F89: 7 | G89: 651
A90: POI-8088 | B90: PO-2033 | C90: MAT-003 | D90: Aluminum Frame | E90: 1274 | F90: 3.81 | G90: 1168
A91: POI-8089 | B91: PO-2034 | C91: MAT-006 | D91: Tempered Glass Panel | E91: 133 | F91: 17.65 | G91: 41
A92: POI-8090 | B92: PO-2034 | C92: MAT-005 | D92: ABS Plastic Housing | E92: 654 | F92: 2.33 | G92: 547
A93: POI-8091 | B93: PO-2034 | C93: MAT-002 | D93: Copper Wiring Bundle | E93: 1163 | F93: 9.23 | G93: 1099
A94: POI-8092 | B94: PO-2035 | C94: MAT-005 | D94: ABS Plastic Housing | E94: 1762 | F94: 2.22 | G94: 1344
A95: POI-8093 | B95: PO-2035 | C95: MAT-009 | D95: Motor Assembly | E95: 1808 | F95: 46.92 | G95: 1130
... A100: POI-8098 | B100: PO-2037 | C100: MAT-010 | D100: Packaging Materials | E100: 1958 | F100: 1.35 | G100: 1270
A101: POI-8099 | B101: PO-2037 | C101: MAT-002 | E101: 1473 | F101: 9.5 | G101: 1169
A102: POI-8100 | B102: PO-2038 | C102: MAT-006 | D102: Tempered Glass Panel | E102: 979 | F102: 19.61 | G102: 881
A103: POI-8101 | B103: PO-2039 | C103: MAT-006 | D103: Tempered Glass Panel | E103: 1539 | F103: 18.22 | G103: 320
A104: POI-8102 | B104: PO-2040 | C104: MAT-006 | D104: Tempered Glass Panel | E104: 447 | F104: 18.27 | G104: 60
A105: POI-8103 | B105: PO-2041 | C105: MAT-003 | D105: Aluminum Frame | E105: 515 | F105: 4.04 | G105: 493
A106: POI-8104 | B106: PO-2041 | C106: MAT-006 | D106: Tempered Glass Panel | E106: 911 | F106: 18.41 | G106: 626
A107: POI-8105 | B107: PO-2042 | C107: MAT-008 | D107: Thermal Insulation | E107: 1828 | F107: 6.88 | G107: 585
A108: POI-8106 | B108: PO-2042 | C108: MAT-007 | D108: Electronic Control Module | E108: 1674 | F108: 34.51 | G108: 693
A109: POI-8107 | B109: PO-2042 | C109: MAT-008 | D109: Thermal Insulation | E109: 1174 | F109: 6.45 | G109: 612
A110: POI-8108 | B110: PO-2043 | C110: MAT-002 | D110: Copper Wiring Bundle | E110: 1177 | F110: 8.64 | G110: 1086
A111: POI-8109 | B111: PO-2044 | C111: MAT-002 | D111: Copper Wiring Bundle | E111: 87 | F111: 8.06 | G111: 67
A112: POI-8110 | B112: PO-2044 | C112: MAT-009 | D112: Motor Assembly | E112: 948 | F112: 53.43 | G112: 840
A113: POI-8111 | B113: PO-2044 | C113: MAT-003 | D113: Aluminum Frame | E113: 1068 | F113: 3.88 | G113: 856
... A156: POI-8154 | B156: PO-2061 | C156: MAT-006 | D156: Tempered Glass Panel | E156: 366 | F156: -20 | G156: 140
A157: POI-8155 | B157: PO-2061 | C157: MAT-002 | E157: 1403 | F157: -9.71 | G157: 875
A158: POI-8156 | B158: PO-2061 | C158: MAT-010 | D158: Packaging Materials | E158: 1716 | F158: 1.45 | G158: 1569
A159: POI-8157 | B159: PO-2062 | C159: MAT-009 | D159: Motor Assembly | E159: 605 | F159: 49.07 | G159: 99
A160: POI-8158 | B160: PO-2062 | C160: MAT-001 | D160: Stainless Steel Sheet | E160: 1602 | F160: 4.28 | G160: 1039
A161: POI-8159 | B161: PO-2062 | C161: MAT-003 | D161: Aluminum Frame | E161: 440 | F161: 4.33 | G161: 75
A162: POI-8160 | B162: PO-2062 | C162: MAT-006 | D162: Tempered Glass Panel | E162: 1784 | F162: 19.46 | G162: 1357
A163: POI-8161 | B163: PO-2063 | C163: MAT-001 | D163: Stainless Steel Sheet | E163: 88 | F163: 4.71 | G163: 76
A164: POI-8162 | B164: PO-2064 | C164: MAT-005 | D164: ABS Plastic Housing | E164: 164 | F164: -1.96 | G164: 150
A165: POI-8163 | B165: PO-2065 | C165: MAT-008 | E165: 722 | F165: 6.01 | G165: 706
A166: POI-8164 | B166: PO-2065 | C166: MAT-004 | D166: Ceramic Heating Element | E166: 274 | F166: 12.33 | G166: 114
A167: POI-8165 | B167: PO-2065 | C167: MAT-009 | D167: Motor Assembly | E167: 328 | F167: 54.45 | G167: 251
A168: POI-8166 | B168: PO-2066 | C168: MAT-003 | D168: Aluminum Frame | E168: 1997 | F168: 3.8 | G168: 573
A169: POI-8167 | B169: PO-2066 | C169: MAT-006 | D169: Tempered Glass Panel | E169: 978 | F169: 16.41 | G169: 481
A170: POI-8168 | B170: PO-2067 | C170: MAT-002 | D170: Copper Wiring Bundle | E170: 1334 | F170: 7.73 | G170: 319
A171: POI-8169 | B171: PO-2067 | C171: MAT-007 | D171: Electronic Control Module | E171: 387 | F171: 37.16 | G171: 246
...

Sheet Production_Order
A1: ProductionOrderID | B1: ProductID | C1: ProductName | D1: PlannedQuantity | E1: StartDate | F1: EndDate | G1: Status | H1: Priority
A2: PRO-3000 | B2: PRD-001 | C2: Stand Mixer 5L | D2: 1055 | E2: 2024-01-12 | F2: 01/02/2024 | G2: In Progress | H2: Medium
A3: PRO-3001 | B3: PRD-001 | C3: Stand Mixer 5L | D3: 1117 | E3: 01/10/2024 | F3: 2024-01-24 | G3: Planned | H3: Medium
A4: PRO-3002 | B4: PRD-001 | C4: Stand Mixer 5L | D4: 1368 | E4: 01/13/2024 | F4: January 29, 2024 | G4: Completed | H4: Low
A5: PRO-3003 | B5: PRD-002 | C5: Stand Mixer 7L Professional | D5: 136 | E5: 06-01-2024 | F5: 2024-01-23 | G5: completed | H5: High
A6: PRO-3004 | B6: PRD-003 | D6: 151 | E6: 06-01-2024 | F6: 2024-01-18 | G6: Cancelled | H6: Medium
A7: PRO-3005 | B7: PRD-004 | C7: Electric Oven 90cm Built-in | D7: 960 | E7: 11/01/2024 | F7: 2024-02-04 | G7: Cancelled | H7: Low
A8: PRO-3006 | B8: PRD-004 | C8: Electric Oven 90cm Built-in | D8: 115 | E8: 10/01/2024 | F8: 17-01-2024 | G8: Planned | H8: Low
A9: PRO-3007 | B9: PRD-005 | C9: Cooktop 60cm Gas | D9: 336 | E9: 2024-01-06 | F9: January 22, 2024 | G9: In Progress | H9: Low
A10: PRO-3008 | B10: PRD-005 | C10: Cooktop 60cm Gas | D10: 208 | E10: 01/02/2024 | F10: 2024-01-08 | G10: Completed | H10: Low
A11: PRO-3009 | B11: PRD-005 | C11: Cooktop 60cm Gas | D11: 730 | E11: 01/04/2024 | F11: 29/01/2024 | G11: Cancelled | H11: Medium
A12: PRO-3010 | B12: PRD-006 | C12: Cooktop-90cm-Induction | D12: 1376 | E12: 04-01-2024 | F12: 2024-01-27 | G12: completed | H12: Low
A13: PRO-3011 | B13: PRD-006 | C13: cooktop 90cm induction | D13: 380 | E13: 01/02/2024 | F13: 18/01/2024 | G13: In Progress | H13: Medium
A14: PRO-3012 | B14: PRD-007 | C14: Range Hood 60cm | D14: 807 | E14: 01/04/2024 | F14: 2024-01-09 | G14: In Progress | H14: High
A15: PRO-3013 | B15: PRD-007 | C15: Range Hood 60cm | D15: 461 | E15: 14-01-2024 | F15: February 05, 2024 | G15: planned | H15: High
A16: PRO-3014 | B16: PRD-007 | C16: range hood 60cm | D16: 402 | E16: 01/13/2024 | F16: 2024-02-07 | G16: Completed | H16: Medium
A17: PRO-3015 | B17: PRD-008 | C17: range hood 90cm | D17: 1090 | E17: January 04, 2024 | F17: 12-01-2024 | G17: In Progress | H17: High
A18: PRO-3016 | B18: PRD-008 | C18: Range Hood 90cm | D18: 114 | E18: January 04, 2024 | F18: 2024-01-22 | G18: Cancelled | H18: Low
A19: PRO-3017 | B19: PRD-009 | C19: Dishwasher 60cm | D19: 1390 | E19: 13/01/2024 | F19: 25-01-2024 | G19: Cancelled | H19: Low
A20: PRO-3018 | B20: PRD-010 | C20: Refrigerator French Door | D20: 1475 | E20: 04/01/2024 | G20: Planned | H20: Medium
A21: PRO-3019 | B21: PRD-011 | D21: 947 | E21: 03-01-2024 | F21: 01/19/2024 | G21: Completed | H21: Low
A22: PRO-3020 | B22: PRD-012 | C22: Toaster_4-Slot | D22: 371 | E22: 01/05/2024 | F22: 18-01-2024 | G22: Completed | H22: Low
A23: PRO-3021 | B23: PRD-013 | C23: Blender Professional | D23: 987 | E23: 06-01-2024 | G23: In Progress | H23: High
A24: PRO-3022 | B24: PRD-014 | C24: Coffee_Maker_Filter | D24: 719 | E24: 01-01-2024 | F24: January 21, 2024 | G24: In Progress | H24: High
A25: PRO-3023 | B25: PRD-014 | C25: Coffee Maker Filter | D25: 368 | E25: January 09, 2024 | F25: 01/20/2024 | G25: Cancelled | H25: Medium
A26: PRO-3024 | B26: PRD-014 | D26: 651 | E26: January 13, 2024 | F26: January 19, 2024 | G26: Completed | H26: Low
A27: PRO-3025 | B27: PRD-015 | C27: Coffee Maker Espresso | D27: 185 | E27: January 09, 2024 | F27: 2024-01-28 | G27: Completed | H27: Medium
A28: PRO-3026 | B28: PRD-015 | C28: Coffee-Maker-Espresso | D28: 630 | E28: 01/08/2024 | F28: 22-01-2024 | G28: Completed
A29: PRO-3027 | B29: PRD-016 | C29: Food_Processor_3L | D29: 480 | E29: 2024-01-05 | F29: 01/28/2024 | G29: Completed | H29: High
A30: PRO-3028 | B30: PRD-016 | C30: Food Processor 3L | D30: 723 | E30: 10-01-2024 | F30: 21-01-2024 | G30: Planned | H30: Medium
A31: PRO-3029 | B31: PRD-001 | C31: Stand Mixer 5L | D31: 1422 | E31: 08/02/2024 | F31: 2024-02-28 | G31: In Progress | H31: High
A32: PRO-3030 | B32: PRD-001 | C32: Stand Mixer 5L | D32: 687 | E32: 2024-02-06 | F32: 2024-02-14 | G32: In Progress | H32: Medium
A33: PRO-3031 | B33: PRD-001 | C33: Stand Mixer 5L | D33: 1208 | E33: February 06, 2024 | F33: February 22, 2024 | G33: cancelled | H33: Medium
A34: PRO-3032 | B34: PRD-002 | C34: Stand Mixer 7L Professional | D34: 1500 | E34: February 08, 2024 | F34: 2024-02-27 | G34: In Progress | H34: Medium
A35: PRO-3033 | B35: PRD-002 | C35: Stand Mixer 7L Professional | D35: 353 | E35: 13-02-2024 | F35: 02/21/2024 | G35: COMPLETED | H35: High
A36: PRO-3034 | B36: PRD-003 | C36: electric oven 60cm | D36: 1026 | E36: 02/02/2024 | F36: 27-02-2024 | G36: PLANNED | H36: High
A37: PRO-3035 | B37: PRD-003 | C37: Electric-Oven-60cm | D37: 1406 | E37: 01-02-2024 | F37: 10/02/2024 | G37: Cancelled | H37: Low
A38: PRO-3036 | B38: PRD-004 | C38: Electric Oven 90cm Built-in | D38: 103 | E38: February 09, 2024 | F38: February 17, 2024 | G38: Completed | H38: Medium
A39: PRO-3037 | B39: PRD-004 | C39: Electric_Oven_90cm_Built-in | D39: 829 | E39: February 02, 2024 | G39: In Progress | H39: Low
A40: PRO-3038 | B40: PRD-004 | C40: Electric Oven 90cm Built-in | D40: 777 | E40: 07/02/2024 | F40: 25-02-2024 | G40: Cancelled
A41: PRO-3039 | B41: PRD-005 | C41: Cooktop-60cm-Gas | D41: 888 | E41: 10/02/2024 | F41: 2024-02-21 | G41: In Progress | H41: Medium
A42: PRO-3040 | B42: PRD-006 | C42: cooktop 90cm induction | D42: 715 | E42: 01-02-2024 | F42: 2024-02-17 | G42: CANCELLED | H42: Low
A43: PRO-3041 | B43: PRD-007 | C43: RANGE HOOD 60CM | D43: 1368 | E43: 2024-02-11 | F43: 07-03-2024 | G43: COMPLETED | H43: Medium
A44: PRO-3042 | B44: PRD-008 | C44: Range Hood 90cm | D44: 929 | E44: 02/10/2024 | G44: Planned | H44: High
A45: PRO-3043 | B45: PRD-008 | C45: Range Hood 90cm | D45: 1226 | E45: 01-02-2024 | F45: 06-02-2024 | G45: IN PROGRESS | H45: High
A46: PRO-3044 | B46: PRD-008 | C46: range hood 90cm | D46: 757 | E46: 2024-02-05 | F46: February 26, 2024 | G46: Cancelled | H46: Low
A47: PRO-3045 | B47: PRD-009 | C47: Dishwasher 60cm | D47: 208 | E47: 04/02/2024 | F47: 17/02/2024 | G47: in progress | H47: High
A48: PRO-3046 | B48: PRD-009 | C48: Dishwasher 60cm | D48: 1389 | E48: 04-02-2024 | F48: February 24, 2024 | G48: Completed | H48: Medium
A49: PRO-3047 | B49: PRD-010 | C49: Refrigerator French Door | D49: 1281 | E49: 02/02/2024 | F49: 25-02-2024 | G49: Cancelled | H49: Medium
A50: PRO-3048 | B50: PRD-010 | C50: Refrigerator French Door | D50: 457 | E50: 09/02/2024 | F50: 02/18/2024 | G50: Completed | H50: Low
A51: PRO-3049 | B51: PRD-011 | C51: Toaster-2-Slot | D51: 870 | E51: 02/07/2024 | F51: 2024-02-16 | G51: Completed | H51: Low
A52: PRO-3050 | B52: PRD-012 | C52: Toaster_4-Slot | D52: 700 | E52: 08-02-2024 | F52: 04/03/2024 | G52: In Progress | H52: Low
A53: PRO-3051 | B53: PRD-012 | C53: Toaster 4-Slot | D53: 1176 | E53: 02/09/2024 | F53: 03/03/2024 | G53: Cancelled | H53: Low
A54: PRO-3052 | B54: PRD-013 | C54: Blender Professional | D54: 1074 | E54: 09-02-2024 | F54: February 16, 2024 | G54: In Progress | H54: Medium
A55: PRO-3053 | B55: PRD-013 | C55: blender professional | D55: 758 | E55: 02/13/2024 | F55: February 29, 2024 | G55: Completed
A56: PRO-3054 | B56: PRD-013 | C56: Blender Professional | D56: 938 | E56: 04-02-2024 | F56: 24-02-2024 | G56: Completed | H56: Low
A57: PRO-3055 | B57: PRD-014 | C57: Coffee Maker Filter | D57: 528 | E57: February 06, 2024 | F57: 2024-02-27 | G57: Planned
A58: PRO-3056 | B58: PRD-014 | C58: Coffee Maker Filter | D58: 558 | E58: 08-02-2024 | F58: 21-02-2024 | G58: Planned | H58: High
A59: PRO-3057 | B59: PRD-014 | C59: coffee maker filter | D59: 333 | E59: 02/11/2024 | F59: March 07, 2024 | G59: Planned | H59: Low
A60: PRO-3058 | B60: PRD-015 | C60: Coffee Maker Espresso | D60: 1158 | E60: 2024-02-09 | F60: 03/01/2024 | G60: Completed | H60: Low
A61: PRO-3059 | B61: PRD-016 | D61: 434 | E61: 2024-02-02 | F61: 15/02/2024 | G61: Cancelled | H61: Medium
A62: PRO-3060 | B62: PRD-016 | C62: food processor 3l | D62: 1203 | E62: 07/02/2024 | F62: February 18, 2024 | G62: PLANNED | H62: Medium
A63: PRO-3061 | B63: PRD-016 | C63: Food Processor 3L | D63: 1331 | E63: 2024-02-08 | F63: February 27, 2024 | G63: In Progress | H63: Low
A64: PRO-3062 | B64: PRD-001 | C64: stand mixer 5l | D64: 233 | E64: 2024-03-04 | F64: 03/28/2024 | G64: Planned | H64: Low
A65: PRO-3063 | B65: PRD-002 | C65: Stand Mixer 7L Professional | D65: 586 | E65: 07/03/2024 | F65: 16/03/2024 | G65: completed | H65: High
A66: PRO-3064 | B66: PRD-002 | C66: stand mixer 7l professional | D66: 387 | E66: 2024-03-04 | F66: 03/23/2024 | G66: In Progress | H66: Low
A67: PRO-3065 | B67: PRD-003 | D67: 1100 | E67: 03/04/2024 | F67: 10-03-2024 | G67: In Progress | H67: Medium
A68: PRO-3066 | B68: PRD-004 | C68: Electric Oven 90cm Built-in | D68: 1079 | E68: 01-03-2024 | F68: 17/03/2024 | G68: Completed | H68: Low
A69: PRO-3067 | B69: PRD-004 | C69: electric oven 90cm built-in | D69: 1117 | E69: 2024-03-04 | F69: 10-03-2024 | G69: Cancelled | H69: High
A70: PRO-3068 | B70: PRD-004 | C70: Electric Oven 90cm Built-in | D70: 306 | E70: March 12, 2024 | F70: 03/29/2024 | G70: Completed | H70: Low
A71: PRO-3069 | B71: PRD-005 | C71: Cooktop 60cm Gas | D71: 963 | E71: 2024-03-13 | F71: 21/03/2024 | G71: Completed
A72: PRO-3070 | B72: PRD-006 | C72: cooktop 90cm induction | D72: 448 | E72: 03/05/2024 | G72: Completed | H72: Medium
A73: PRO-3071 | B73: PRD-007 | C73: Range Hood 60cm | D73: 1101 | E73: 02-03-2024 | F73: 21-03-2024 | G73: Cancelled | H73: High
A74: PRO-3072 | B74: PRD-007 | C74: Range Hood 60cm | D74: 381 | E74: 06/03/2024 | F74: March 19, 2024 | G74: Completed | H74: Low
A75: PRO-3073 | B75: PRD-008 | C75: Range Hood 90cm | D75: 427 | E75: 03/12/2024 | F75: 25/03/2024 | G75: planned | H75: Medium
A76: PRO-3074 | B76: PRD-009 | C76: dishwasher 60cm | D76: 547 | E76: 03/02/2024 | F76: 20/03/2024 | G76: IN PROGRESS | H76: High
A77: PRO-3075 | B77: PRD-009 | C77: Dishwasher 60cm | D77: 195 | E77: 03/05/2024 | F77: March 12, 2024 | G77: planned | H77: Medium
A78: PRO-3076 | B78: PRD-010 | C78: Refrigerator French Door | D78: 619 | E78: 13/03/2024 | F78: 2024-03-26 | G78: In Progress | H78: High
A79: PRO-3077 | B79: PRD-011 | C79: Toaster 2-Slot | D79: 1147 | E79: 03-03-2024 | F79: 14-03-2024 | G79: Planned | H79: Low
A80: PRO-3078 | B80: PRD-011 | C80: Toaster 2-Slot | D80: 1003 | E80: 2024-03-04 | F80: 21-03-2024 | G80: Planned | H80: High
A81: PRO-3079 | B81: PRD-011 | C81: Toaster 2-Slot | D81: 349 | E81: 08-03-2024 | F81: 03/14/2024 | G81: Completed | H81: Low
A82: PRO-3080 | B82: PRD-012 | C82: toaster 4-slot | D82: 1245 | E82: 03/03/2024 | F82: 03/16/2024 | G82: Cancelled | H82: Low
A83: PRO-3081 | B83: PRD-012 | C83: Toaster 4-Slot | D83: 1238 | E83: 03/07/2024 | F83: 14-03-2024 | G83: cancelled | H83: High
A84: PRO-3082 | B84: PRD-013 | C84: blender professional | D84: 202 | E84: 03/07/2024 | F84: 15-03-2024 | G84: Cancelled | H84: Low
... A88: PRO-3086 | B88: PRD-015 | C88: Coffee Maker Espresso | D88: 1302 | E88: 2024-03-05 | F88: March 22, 2024 | G88: Planned | H88: High
A89: PRO-3087 | B89: PRD-016 | C89: FOOD PROCESSOR 3L | D89: 1421 | E89: 10/03/2024 | G89: Completed | H89: Medium
A90: PRO-3088 | B90: PRD-016 | C90: Food Processor 3L | D90: 140 | E90: 03/03/2024 | G90: Completed | H90: Medium
A91: PRO-3089 | B91: PRD-016 | C91: Food_Processor_3L | D91: 588 | E91: 2024-03-10 | F91: 29-03-2024 | G91: Completed | H91: Low
A92: PRO-3090 | B92: PRD-001 | C92: STAND MIXER 5L | D92: 916 | E92: April 10, 2024 | F92: 04/05/2024 | G92: Planned | H92: High
A93: PRO-3091 | B93: PRD-001 | C93: Stand-Mixer-5L | D93: 1144 | E93: 2024-04-02 | F93: 24-04-2024 | G93: in progress | H93: Low
A94: PRO-3092 | B94: PRD-001 | C94: Stand Mixer 5L | D94: 826 | E94: April 13, 2024 | F94: 05/05/2024 | G94: Planned | H94: Low
A95: PRO-3093 | B95: PRD-002 | C95: Stand Mixer 7L Professional | D95: 1070 | E95: 14-04-2024 | F95: 08-05-2024 | G95: Completed | H95: High
A96: PRO-3094 | B96: PRD-002 | C96: Stand Mixer 7L Professional | D96: 853 | E96: 04/01/2024 | F96: 04/25/2024 | G96: In Progress | H96: Medium
A97: PRO-3095 | B97: PRD-002 | C97: Stand Mixer 7L Professional | D97: 1174 | E97: 07-04-2024 | F97: April 29, 2024 | G97: CANCELLED | H97: High
A98: PRO-3096 | B98: PRD-003 | C98: Electric Oven 60cm | D98: 1025 | E98: 2024-04-08 | F98: 04/26/2024 | G98: Completed | H98: High
A99: PRO-3097 | B99: PRD-003 | C99: Electric Oven 60cm | D99: 1360 | E99: 11-04-2024 | F99: 16/04/2024 | G99: completed | H99: High
A100: PRO-3098 | B100: PRD-004 | C100: Electric_Oven_90cm_Built-in | D100: 1117 | E100: April 11, 2024 | F100: April 20, 2024 | G100: Completed | H100: Medium
A101: PRO-3099 | B101: PRD-004 | C101: ELECTRIC OVEN 90CM BUILT-IN | D101: 846 | E101: 2024-04-08 | F101: 21-04-2024 | G101: Completed
A102: PRO-3100 | B102: PRD-005 | C102: Cooktop 60cm Gas | D102: 1009 | E102: 06-04-2024 | G102: In Progress | H102: Medium
A103: PRO-3101 | B103: PRD-005 | D103: 748 | E103: 2024-04-14 | F103: 29-04-2024 | G103: In Progress
...

Sheet Product_Costing
A1: CostID | B1: ProductID | C1: Month | D1: MaterialCost | E1: LaborCost | F1: OverheadCost | G1: TotalCost | H1: StandardCost | I1: ActualCost | J1: Variance
A2: CST-0001 | B2: PRD-001 | C2: 45292 | D2: 98.96 | E2: 55.43 | F2: 32.58 | G2: 186.97 | H2: 180 | I2: 186.97 | J2: 6.97
A3: CST-0002 | B3: PRD-001 | C3: 45323 | D3: 89.45 | E3: 56.78 | F3: 37.82 | G3: 184.05 | H3: 180 | I3: 184.05 | J3: 4.05
A4: CST-0003 | B4: PRD-001 | C4: 45352 | D4: 98.84 | E4: 50.64 | F4: 33.28 | G4: 182.76 | H4: 180 | I4: 182.76 | J4: 2.76
A5: CST-0004 | B5: PRD-001 | C5: 45383 | D5: 86.05 | E5: 56.94 | F5: 37.53 | G5: 180.52 | H5: 180 | I5: 180.52 | J5: 0.52
A6: CST-0005 | B6: PRD-001 | C6: 45413 | D6: 90.19 | E6: 56.13 | F6: 38.64 | G6: 184.96 | H6: 180 | I6: 184.96 | J6: 4.96
A7: CST-0006 | B7: PRD-001 | C7: 45444 | D7: 85.33 | E7: 54.86 | F7: 38.65 | G7: 178.84 | H7: 180 | I7: 178.84 | J7: -1.16
A8: CST-0007 | B8: PRD-001 | C8: 45474 | D8: 87.63 | E8: 49.3 | F8: 36.28 | G8: 173.21 | H8: 180 | I8: 173.21 | J8: -6.79
A9: CST-0008 | B9: PRD-001 | C9: 45505 | D9: 97.6 | E9: 51.18 | F9: 34.28 | G9: 183.06 | H9: 180 | I9: 183.06 USD | J9: 3.06
A10: CST-0009 | B10: PRD-001 | C10: 45536 | D10: 87.25 | E10: 51.03 | F10: 33.86 | G10: 172.14 | H10: 180 | I10: 172.14 | J10: -7.86
A11: CST-0010 | B11: PRD-001 | C11: 45566 | D11: 84.43 | E11: 55.81 | F11: 38.67 | G11: 178.91 | H11: 180 | I11: 178.91 USD | J11: -1.09
A12: CST-0011 | B12: PRD-001 | C12: 45597 | D12: 91.43 | E12: 56.75 | F12: 39.25 | G12: 187.43 | H12: 180 | I12: 187.43 | J12: 7.43
A13: CST-0012 | B13: PRD-001 | C13: 45627 | D13: 90.07 | E13: 56.31 | F13: 37.11 | G13: 183.49 | H13: 180 | I13: 183.49 | J13: 3.49
... A21: CST-0020 | B21: PRD-002 | C21: 45505 | D21: 124.38 | E21: 84.03 | F21: 52 | G21: 260.41 | H21: 260 | I21: 260.41 | J21: 0.41
A22: CST-0021 | B22: PRD-002 | C22: 45536 | D22: 142.97 | E22: 74.16 | F22: 53.58 | G22: 270.71 | H22: 260 | I22: 270.71
A23: CST-0022 | B23: PRD-002 | C23: 45566 | D23: 141.51 | E23: 71.15 | F23: 56.69 | G23: 269.35 | H23: 260 | I23: 269.35 | J23: 9.35
A24: CST-0023 | B24: PRD-002 | C24: 45597 | D24: 128.22 | E24: 85.56 | F24: 56.9 | G24: 270.68 | H24: 260 | I24: 270.68 | J24: 10.68
A25: CST-0024 | B25: PRD-002 | C25: 45627 | D25: 118.88 | E25: 81.9 | F25: 52.35 | G25: 253.13 | H25: 260 | I25: 253.13 | J25: -6.87
A26: CST-0025 | B26: PRD-003 | C26: 45292 | D26: 294.37 | E26: 150.73 | F26: 116.53 | G26: 561.63 | H26: 540 | I26: 561.63 | J26: 21.63
A27: CST-0026 | B27: PRD-003 | C27: 45323 | D27: 243.1 | E27: 155.92 | F27: 106.42 | G27: 505.44 | H27: 540 | I27: 505.44 USD | J27: -34.56
A28: CST-0027 | B28: PRD-003 | C28: 45352 | D28: 284.8 | E28: 170.02 | F28: 113.18 | G28: 568 | H28: 540 | I28: 568.0 | J28: 28
A29: CST-0028 | B29: PRD-003 | C29: 45383 | D29: 243.33 | E29: 159.37 | F29: 97.58 | G29: 500.28 | H29: 540 | I29: 500.28 | J29: -39.72
A30: CST-0029 | B30: PRD-003 | C30: 45413 | D30: 253.76 | E30: 172.67 | F30: 110.68 | G30: 537.11 | H30: 540 | I30: 537.11 | J30: -2.89
A31: CST-0030 | B31: PRD-003 | C31: 45444 | D31: 250.24 | E31: 155.92 | F31: 98.77 | G31: 504.93 | H31: 540 | I31: 504.93 USD | J31: -35.07
A32: CST-0031 | B32: PRD-003 | C32: 45474 | D32: 269.55 | E32: 163.44 | F32: 104.1 | G32: 537.09 | H32: 540 | I32: 537.09 | J32: -2.91
A33: CST-0032 | B33: PRD-003 | C33: 45505 | D33: 250.97 | E33: 148.27 | F33: 104.74 | G33: 503.98 | H33: 540 | I33: 503.98 | J33: -36.02
A34: CST-0033 | B34: PRD-003 | C34: 45536 | D34: 291.43 | E34: 170.88 | F34: 109.56 | G34: 571.87 | H34: 540 | I34: 571.87 | J34: 31.87
... A53: CST-0052 | B53: PRD-005 | C53: 45383 | D53: 160.3 | E53: 99.6 | F53: 63.99 | G53: 323.89 | H53: 310 | I53: 323.89 | J53: 13.89
A54: CST-0053 | B54: PRD-005 | C54: 45413 | D54: 156.77 | E54: 100.65 | F54: 61.59 | G54: 319.01 | H54: 310 | I54: 319.01
A55: CST-0054 | B55: PRD-005 | C55: 45444 | D55: 147.35 | E55: 88.48 | F55: 62.9 | G55: 298.73 | H55: 310 | I55: 298.73
A56: CST-0055 | B56: PRD-005 | C56: 45474 | D56: 143.37 | E56: 101.18 | F56: 66.39 | G56: 310.94 | H56: 310 | I56: 310.94 USD | J56: 0.94
A57: CST-0056 | B57: PRD-005 | C57: 45505 | D57: 147.44 | E57: 91.04 | F57: 64.23 | G57: 302.71 | H57: 310 | I57: 302.71 | J57: -7.29
A58: CST-0057 | B58: PRD-005 | C58: 45536 | D58: 151.78 | E58: 96.24 | F58: 61.84 | G58: 309.86 | H58: 310 | I58: 309.86 | J58: -0.14
A59: CST-0058 | B59: PRD-005 | C59: 45566 | D59: 151.23 | E59: 90.71 | F59: 55.86 | G59: 297.8 | H59: 310 | I59: 297.8 | J59: -12.2
A60: CST-0059 | B60: PRD-005 | C60: 45597 | D60: 163.29 | E60: 99.53 | F60: 65.66 | G60: 328.48 | H60: 310 | I60: 328.48 | J60: 18.48
A61: CST-0060 | B61: PRD-005 | C61: 45627 | D61: 156.34 | E61: 87.29 | F61: 62.21 | G61: 305.84 | H61: 310 | I61: 305.84 | J61: -4.16
A62: CST-0061 | B62: PRD-006 | C62: 45292 | D62: 262.52 | E62: 155.54 | F62: 101.5 | G62: 519.56 | H62: 490 | I62: 519.56 | J62: 29.56
A63: CST-0062 | B63: PRD-006 | C63: 45323 | D63: 248.96 | E63: 155.05 | F63: 90.49 | G63: 494.5 | H63: 490 | I63: 494.5 USD | J63: 4.5
A64: CST-0063 | B64: PRD-006 | C64: 45352 | D64: 258.43 | E64: 141.96 | F64: 107.3 | G64: 507.69 | H64: 490 | I64: 507.69 | J64: 17.69
A65: CST-0064 | B65: PRD-006 | C65: 45383 | D65: 247.97 | E65: 160.15 | F65: 106.53 | G65: 514.65 | H65: 490 | I65: 514.65 | J65: 24.65
A66: CST-0065 | B66: PRD-006 | C66: 45413 | D66: 240.12 | E66: 147.68 | F66: 97.21 | G66: 485.01 | H66: 490 | I66: 485.01 | J66: -4.99
A67: CST-0066 | B67: PRD-006 | C67: 45444 | D67: 232.68 | E67: 139.48 | F67: 95.76 | G67: 467.92 | H67: 490 | I67: 467.92 | J67: -22.08
... A91: CST-0090 | B91: PRD-008 | C91: 45444 | D91: 176.04 | E91: 94.15 | F91: 68.77 | G91: 338.96 | H91: 330 | I91: 338.96 | J91: 8.96
A92: CST-0091 | B92: PRD-008 | C92: 45474 | D92: 148.66 | E92: 103.88 | F92: 62.99 | G92: 315.53 | H92: 330 | I92: 315.53
A93: CST-0092 | B93: PRD-008 | C93: 45505 | D93: 156.37 | E93: 106.16 | F93: 61.02 | G93: 323.55 | H93: 330 | I93: 323.55 | J93: -6.45
A94: CST-0093 | B94: PRD-008 | C94: 45536 | D94: 163.17 | E94: 108.74 | F94: 65.82 | G94: 337.73 | H94: 330 | I94: 337.73 | J94: 7.73
A95: CST-0094 | B95: PRD-008 | C95: 45566 | D95: 172.69 | E95: 99.07 | F95: 71.26 | G95: 343.02 | H95: 330 | I95: 343.02 | J95: 13.02
A96: CST-0095 | B96: PRD-008 | C96: 45597 | D96: 155.3 | E96: 94.39 | F96: 72.53 | G96: 322.22 | H96: 330 | I96: 322.22 | J96: -7.78
A97: CST-0096 | B97: PRD-008 | C97: 45627 | D97: 153.42 | E97: 106.2 | F97: 60.92 | G97: 320.54 | H97: 330 | I97: 320.54 | J97: -9.46
A98: CST-0097 | B98: PRD-009 | C98: 45292 | D98: 173.71 | E98: 109.03 | F98: 75.94 | G98: 358.68 | H98: 370 | I98: 358.68 | J98: -11.32
A99: CST-0098 | B99: PRD-009 | C99: 45323 | D99: 201.27 | E99: 111.19 | F99: 78.97 | G99: 391.43 | H99: 370 | I99: 391.43 | J99: 21.43
A100: CST-0099 | B100: PRD-009 | C100: 45352 | D100: 202.3 | E100: 105.3 | F100: 76.47 | G100: 384.07 | H100: 370 | I100: 384.07 | J100: 14.07
A101: CST-0100 | B101: PRD-009 | C101: 45383 | D101: 178.44 | E101: 121.52 | F101: 77.62 | G101: 377.58 | H101: 370 | I101: 377.58 | J101: 7.58
A102: CST-0101 | B102: PRD-009 | C102: 45413 | D102: 195.96 | E102: 115.29 | F102: 73.93 | G102: 385.18 | H102: 370 | I102: 385.18 | J102: 15.18
A103: CST-0102 | B103: PRD-009 | C103: 45444 | D103: 166.57 | E103: 114 | F103: 73.64 | G103: 354.21 | H103: 370 | I103: 354.21 | J103: -15.79
A104: CST-0103 | B104: PRD-009 | C104: 45474 | D104: 202.13 | E104: 103.4 | F104: 72.18 | G104: 377.71 | H104: 370 | I104: 377.71 | J104: 7.71
... A140: CST-0139 | B140: PRD-012 | C140: 45474 | D140: 61.69 | E140: 36.07 | F140: 24.07 | G140: 121.83 | H140: 115 | I140: 121.83 | J140: 6.83
A141: CST-0140 | B141: PRD-012 | C141: 45505 | D141: 53.01 | E141: 36.25 | F141: 23.47 | G141: 112.73 | H141: 115 | I141: 112.73 USD
A142: CST-0141 | B142: PRD-012 | C142: 45536 | D142: 61.54 | E142: 33.28 | F142: 23.19 | G142: 118.01 | H142: 115 | I142: 118.01 | J142: 3.01
A143: CST-0142 | B143: PRD-012 | C143: 45566 | D143: 59.28 | E143: 37.88 | F143: 20.89 | G143: 118.05 | H143: 115 | I143: -118.05 | J143: 3.05
A144: CST-0143 | B144: PRD-012 | C144: 45597 | D144: 59.94 | E144: 31.22 | F144: 25.27 | G144: 116.43 | H144: 115 | I144: 116.43 | J144: 1.43
A145: CST-0144 | B145: PRD-012 | C145: 45627 | D145: 62.02 | E145: 33.39 | F145: 25.21 | G145: 120.62 | H145: 115 | I145: 120.62 | J145: 5.62
A146: CST-0145 | B146: PRD-013 | C146: 45292 | D146: 54.82 | E146: 32.49 | F146: 22.3 | G146: 109.61 | H146: 105 | I146: 109.61 | J146: 4.61
A147: CST-0146 | B147: PRD-013 | C147: 45323 | D147: 48.36 | E147: 29.84 | F147: 19.19 | G147: 97.39 | H147: 105 | I147: 97.39 | J147: -7.61
A148: CST-0147 | B148: PRD-013 | C148: 45352 | D148: 47.48 | E148: 29.21 | F148: 21.57 | G148: 98.26 | H148: 105 | I148: 98.26 | J148: -6.74
A149: CST-0148 | B149: PRD-013 | C149: 45383 | D149: 51.77 | E149: 31.17 | F149: 20.67 | G149: 103.61 | H149: 105 | I149: 103.61 | J149: -1.39
A150: CST-0149 | B150: PRD-013 | C150: 45413 | D150: 54.45 | E150: 32.93 | F150: 21.28 | G150: 108.66 | H150: 105 | I150: 108.66 | J150: 3.66
A151: CST-0150 | B151: PRD-013 | C151: 45444 | D151: 52.05 | E151: 33.44 | F151: 21.51 | G151: 107 | H151: 105 | I151: 107.0 | J151: 2
A152: CST-0151 | B152: PRD-013 | C152: 45474 | D152: 56.72 | E152: 32.91 | F152: 21.42 | G152: 111.05 | H152: 105 | I152: 111.05 | J152: 6.05
A153: CST-0152 | B153: PRD-013 | C153: 45505 | D153: 48.81 | E153: 29.89 | F153: 19.23 | G153: 97.93 | H153: 105 | I153: 97.93 | J153: -7.07
... A170: CST-0169 | B170: PRD-015 | C170: 45292 | D170: 116.14 | E170: 59.83 | F170: 47.56 | G170: 223.53 | H170: 220 | I170: 223.53 | J170: 3.53
A171: CST-0170 | B171: PRD-015 | C171: 45323 | D171: 118.67 | E171: 59.63 | F171: 47.18 | G171: 225.48 | H171: 220 | I171: 225.48
A172: CST-0171 | B172: PRD-015 | C172: 45352 | D172: 101.86 | E172: 63.31 | F172: 47.23 | G172: 212.4 | H172: 220 | I172: 212.4 USD | J172: -7.6
A173: CST-0172 | B173: PRD-015 | C173: 45383 | D173: 113.53 | E173: 66.94 | F173: 41.95 | G173: 222.42 | H173: 220 | I173: 222.42 | J173: 2.42
A174: CST-0173 | B174: PRD-015 | C174: 45413 | D174: 101.1 | E174: 71.02 | F174: 45.25 | G174: 217.37 | H174: 220 | I174: 217.37
A175: CST-0174 | B175: PRD-015 | C175: 45444 | D175: 103.77 | E175: 71.94 | F175: 46.08 | G175: 221.79 | H175: 220 | I175: 221.79 | J175: 1.79
A176: CST-0175 | B176: PRD-015 | C176: 45474 | D176: 115.47 | E176: 72.16 | F176: 47.14 | G176: 234.77 | H176: 220 | I176: 234.77 | J176: 14.77
A177: CST-0176 | B177: PRD-015 | C177: 45505 | D177: 109.7 | E177: 69.23 | F177: 43.74 | G177: 222.67 | H177: 220 | I177: 222.67
A178: CST-0177 | B178: PRD-015 | C178: 45536 | D178: 119.39 | E178: 60.45 | F178: 47.28 | G178: 227.12 | H178: 220 | I178: 227.12 | J178: 7.12
A179: CST-0178 | B179: PRD-015 | C179: 45566 | D179: 104.43 | E179: 65.58 | F179: 44.51 | G179: 214.52 | H179: 220 | I179: 214.52 | J179: -5.48
A180: CST-0179 | B180: PRD-015 | C180: 45597 | D180: 108.83 | E180: 68.79 | F180: 46.52 | G180: 224.14 | H180: 220 | I180: 224.14 | J180: 4.14
A181: CST-0180 | B181: PRD-015 | C181: 45627 | D181: 119.53 | E181: 71.71 | F181: 40.85 | G181: 232.09 | H181: 220 | I181: 232.09 | J181: 12.09
A182: CST-0181 | B182: PRD-016 | C182: 45292 | D182: 27.78 | E182: 17.15 | F182: 11.66 | G182: 56.59 | H182: 60 | I182: 56.59 | J182: -3.41
A183: CST-0182 | B183: PRD-016 | C183: 45323 | D183: 29.74 | E183: 17.11 | F183: 11.87 | G183: 58.72 | H183: 60 | I183: 58.72 | J183: -1.28
A184: CST-0183 | B184: PRD-016 | C184: 45352 | D184: 31.83 | E184: 18.09 | F184: 11.63 | G184: 61.55 | H184: 60 | I184: 61.55 | J184: 1.55
A185: CST-0184 | B185: PRD-016 | C185: 45383 | D185: 28.85 | E185: 19.78 | F185: 11.35 | G185: 59.98 | H185: 60 | I185: 59.98 | J185: -0.02
A186: CST-0185 | B186: PRD-016 | C186: 45413 | D186: 29.38 | E186: 18.96 | F186: 11.97 | G186: 60.31 | H186: 60 | I186: 60.31 | J186: 0.31
A187: CST-0186 | B187: PRD-016 | C187: 45444 | D187: 31.7 | E187: 18.93 | F187: 12.71 | G187: 63.34 | H187: 60 | I187: 63.34 | J187: 3.34
A188: CST-0187 | B188: PRD-016 | C188: 45474 | D188: 31.15 | E188: 18.32 | F188: 12.15 | G188: 61.62 | H188: 60 | I188: 61.62 | J188: 1.62
A189: CST-0188 | B189: PRD-016 | C189: 45505 | D189: 29.68 | E189: 17.91 | F189: 12.91 | G189: 60.5 | H189: 60 | I189: 60.5 | J189: 0.5
... A194: CST-0192 | B194: PRD-016 | C194: 45627 | D194: 31.76 | E194: 18.07 | F194: 12.63 | G194: 62.46 | H194: 60 | I194: 62.46 | J194: 2.46
A195: CST-0021 | B195: PRD-002 | C195: 45536 | D195: 142.97 | E195: 74.16 | F195: 53.58 | G195: 270.71 | H195: 260 | I195: 270.71
A196: CST-0058 | B196: PRD-005 | C196: 45566 | D196: 151.23 | E196: 90.71 | F196: 55.86 | G196: 297.8 | H196: 310 | I196: 297.8 | J196: -12.2
A197: CST-0147 | B197: PRD-013 | C197: 45352 | D197: 47.48 | E197: 29.21 | F197: 21.57 | G197: 98.26 | H197: 105 | I197: 98.26 | J197: -6.74
A198: CST-0084 | B198: PRD-007 | C198: 45627 | D198: 102.16 | E198: 69.57 | F198: 46.99 | G198: 218.72 | H198: 220 | I198: 218.72 | J198: -1.28
A199: CST-0159 | B199: PRD-014 | C199: 45352 | D199: 38.37 | E199: 22.75 | F199: 13.68 | G199: 74.8 | H199: 70 | I199: 74.8 | J199: 4.8
A200: CST-0184 | B200: PRD-016 | C200: 45383 | D200: 28.85 | E200: 19.78 | F200: 11.35 | G200: 59.98 | H200: 60 | I200: 59.98 | J200: -0.02

Sheet Analysis
A2: Row Labels | B2: Sum of Revenue | D2: Gross Margin % by Month
A3: Jan | B3: 6721287.4 | D3: Row Labels | E3: Sum of Revenue | F3: Sum of CalculatedProfit | G3: Margin % | I3: COGS RATIO BY MONTH
A4: Feb | B4: 5648713.5 | D4: 45292 | E4: 6721287.4 | F4: 3710347.3 | G4: =IFERROR(F4/E4,0) -> 0.55202926 | I4: Month | J4: Sum of Revenue | K4: Sum of COGS | L4: COGS Ratio
A5: Mar | B5: 7867659.7 | D5: 45323 | E5: 5648713.5 | F5: 3212513.6 | G5: =IFERROR(F5/E5,0) -> 0.56871598 | I5: =DATE(2024,1,1) -> 45292 | J5: =SUMIFS(Fact_Sales[Revenue],Fact_Sales[Month],$I5) -> 5737328 | K5: =SUMIFS(Fact_Sales[COGS],Fact_Sales[Month],$I5) -> 3010940.1 | L5: =IFERROR(K5/J5,0) -> 0.52479833
A6: Apr | B6: 6574729 | D6: 45352 | E6: 7867659.7 | F6: 4386834.2 | G6: =IFERROR(F6/E6,0) -> 0.55757803 | I6: =EDATE(I5,1) -> 45323 | J6: =SUMIFS(Fact_Sales[Revenue],Fact_Sales[Month],$I6) -> 5390639.4 | K6: =SUMIFS(Fact_Sales[COGS],Fact_Sales[Month],$I6) -> 2436199.9 | L6: =IFERROR(K6/J6,0) -> 0.45193152
A7: May | B7: 6405937.8 | D7: 45383 | E7: 6574729 | F7: 3697373.4 | G7: =IFERROR(F7/E7,0) -> 0.56236134 | I7: =EDATE(I6,1) -> 45352 | J7: =SUMIFS(Fact_Sales[Revenue],Fact_Sales[Month],$I7) -> 6725694.9 | K7: =SUMIFS(Fact_Sales[COGS],Fact_Sales[Month],$I7) -> 3480825.5 | L7: =IFERROR(K7/J7,0) -> 0.51754139
A8: Jun | B8: 6092987 | D8: 45413 | E8: 6405937.8 | F8: 3582609.5 | G8: =IFERROR(F8/E8,0) -> 0.55926385 | I8: =EDATE(I7,1) -> 45383 | J8: =SUMIFS(Fact_Sales[Revenue],Fact_Sales[Month],$I8) -> 6094753.2 | K8: =SUMIFS(Fact_Sales[COGS],Fact_Sales[Month],$I8) -> 2877355.6 | L8: =IFERROR(K8/J8,0) -> 0.47210371
A9: Jul | B9: 6080831.1 | D9: 45444 | E9: 6092987 | F9: 3439614.8 | G9: =IFERROR(F9/E9,0) -> 0.56452029 | I9: =EDATE(I8,1) -> 45413 | J9: =SUMIFS(Fact_Sales[Revenue],Fact_Sales[Month],$I9) -> 5901918.1 | K9: =SUMIFS(Fact_Sales[COGS],Fact_Sales[Month],$I9) -> 2823328.4 | L9: =IFERROR(K9/J9,0) -> 0.4783747
A10: Aug | B10: 7096428.7 | D10: 45474 | E10: 6080831.1 | F10: 3446397.5 | G10: =IFERROR(F10/E10,0) -> 0.56676422 | I10: =EDATE(I9,1) -> 45444 | J10: =SUMIFS(Fact_Sales[Revenue],Fact_Sales[Month],$I10) -> 5665791.7 | K10: =SUMIFS(Fact_Sales[COGS],Fact_Sales[Month],$I10) -> 2653372.2 | L10: =IFERROR(K10/J10,0) -> 0.46831447
A11: Sep | B11: 6604655.3 | D11: 45505 | E11: 7096428.7 | F11: 3996518.6 | G11: =IFERROR(F11/E11,0) -> 0.56317321 | I11: =EDATE(I10,1) -> 45474 | J11: =SUMIFS(Fact_Sales[Revenue],Fact_Sales[Month],$I11) -> 5730508.5 | K11: =SUMIFS(Fact_Sales[COGS],Fact_Sales[Month],$I11) -> 2634433.7 | L11: =IFERROR(K11/J11,0) -> 0.45972075
A12: Oct | B12: 6764313.7 | D12: 45536 | E12: 6604655.3 | F12: 3715466.6 | G12: =IFERROR(F12/E12,0) -> 0.56255269 | I12: =EDATE(I11,1) -> 45505 | J12: =SUMIFS(Fact_Sales[Revenue],Fact_Sales[Month],$I12) -> 6582685.5 | K12: =SUMIFS(Fact_Sales[COGS],Fact_Sales[Month],$I12) -> 3099910.2 | L12: =IFERROR(K12/J12,0) -> 0.47091877
A13: Nov | B13: 5271256.4 | D13: 45566 | E13: 6764313.7 | F13: 3785150.1 | G13: =IFERROR(F13/E13,0) -> 0.55957637 | I13: =EDATE(I12,1) -> 45536 | J13: =SUMIFS(Fact_Sales[Revenue],Fact_Sales[Month],$I13) -> 6369309.3 | K13: =SUMIFS(Fact_Sales[COGS],Fact_Sales[Month],$I13) -> 2889188.7 | L13: =IFERROR(K13/J13,0) -> 0.45361099
A14: Dec | B14: 6872157 | D14: 45597 | E14: 5271256.4 | F14: 2937847.7 | G14: =IFERROR(F14/E14,0) -> 0.55733349 | I14: =EDATE(I13,1) -> 45566 | J14: =SUMIFS(Fact_Sales[Revenue],Fact_Sales[Month],$I14) -> 6226802.7 | K14: =SUMIFS(Fact_Sales[COGS],Fact_Sales[Month],$I14) -> 2765020.9 | L14: =IFERROR(K14/J14,0) -> 0.44405147
A15: Grand Total | B15: 78000957 | D15: 45627 | E15: 6872157 | F15: 3859671.5 | G15: =IFERROR(F15/E15,0) -> 0.56163902 | I15: =EDATE(I14,1) -> 45597 | J15: =SUMIFS(Fact_Sales[Revenue],Fact_Sales[Month],$I15) -> 4914988.2 | K15: =SUMIFS(Fact_Sales[COGS],Fact_Sales[Month],$I15) -> 2333408.7 | L15: =IFERROR(K15/J15,0) -> 0.47475367
D16: Grand Total | E16: 78000957 | F16: 43770345 | G16: =IFERROR(F16/E16,0) -> 0.56115138 | I16: =EDATE(I15,1) -> 45627 | J16: =SUMIFS(Fact_Sales[Revenue],Fact_Sales[Month],$I16) -> 6390534.5 | K16: =SUMIFS(Fact_Sales[COGS],Fact_Sales[Month],$I16) -> 3012485.5 | L16: =IFERROR(K16/J16,0) -> 0.47139805
I17: Grand Total | J17: =SUM(J5:J16) -> 71730954 | K17: =SUM(K5:K16) -> 34016469 | L17: =IFERROR(K17/J17,0) -> 0.47422302
I18: Dec
I19: Grand Total | J19: =SUM(Fact_Sales[Revenue]) -> 71730954 | K19: =SUM(Fact_Sales[COGS]) -> 34016469 | L19: =IFERROR(K19/J19,0) -> 0.47422302
A21: NET PROFIT CALCULATION
A22: Total Profit (Fact_Sales) | B22: =F16 -> 43770345
A23: Total OpEx (5 accounts) | B23: =SUMIFS(GL_Transactions!D:D,GL_Transactions!C:C,"Admin Expenses")+SUMIFS(GL_Transactions!D:D,GL_Transactions!C:C,"Depreciation")+SUMIFS(GL_Transactions!D:D,GL_Transactions!C:C,"Logistics")+SUMIFS(GL_Transactions!D:D,GL_Transactions!C:C,"Marketing")+SUMIFS(GL_Transactions!D:D,GL_Transactions!C:C,"Utilities") -> 20086512
A24: Net Profit | B24: =B22-B23 -> 23683833
A27: Row Labels | B27: Sum of Quantity | C27: Sum of Revenue
A28: PRD-001 | B28: 8128 | C28: 3038863.8
A29: PRD-002 | B29: 6757 | C29: 3804249
A30: PRD-003 | B30: 7453 | C30: 9131840.1
A31: PRD-004 | B31: 6327 | C31: 11314717
A32: PRD-005 | B32: 7044 | C32: 4942688.5
A33: PRD-006 | B33: 6417 | C33: 7232787.6
A34: PRD-007 | B34: 6077 | C34: 3149503.2
A35: PRD-008 | B35: 6676 | C35: 4920282
A36: PRD-009 | B36: 7257 | C36: 6174421.9
A37: PRD-010 | B37: 7751 | C37: 14480156
A38: PRD-011 | B38: 5640 | C38: 1219012.8
A39: PRD-012 | B39: 6120 | C39: 1811680.7
... A44: Grand Total | B44: 106855 | C44: 78000957
A47: =C44/B44 -> 729.97012
A49: AVG UNITS SOLD BY COUNTRY
A50: Country | B50: Total Units | C50: Avg Units / Order
A51: Australia | B51: {=SUMPRODUCT((COUNTIFS(Customer[CustomerID],Fact_Sales[CustomerID],Customer[Country],$A51)>0)*Fact_Sales[Quantity])} -> 8153 | C51: {=IFERROR(B51/SUMPRODUCT((COUNTIFS(Customer[CustomerID],Fact_Sales[CustomerID],Customer[Country],$A51)>0)*1),0)} -> 101.9125
A52: France | B52: {=SUMPRODUCT((COUNTIFS(Customer[CustomerID],Fact_Sales[CustomerID],Customer[Country],$A52)>0)*Fact_Sales[Quantity])} -> 7779 | C52: {=IFERROR(B52/SUMPRODUCT((COUNTIFS(Customer[CustomerID],Fact_Sales[CustomerID],Customer[Country],$A52)>0)*1),0)} -> 102.35526
A53: Germany | B53: {=SUMPRODUCT((COUNTIFS(Customer[CustomerID],Fact_Sales[CustomerID],Customer[Country],$A53)>0)*Fact_Sales[Quantity])} -> 7281 | C53: {=IFERROR(B53/SUMPRODUCT((COUNTIFS(Customer[CustomerID],Fact_Sales[CustomerID],Customer[Country],$A53)>0)*1),0)} -> 107.07353
